Workbook

Sheet ListOption
A1: symbol | B1: last_price | C1: bid_price | D1: ask_price | E1: mark_price_live
A2: SOL-26JUN26-70-P-USDT | B2: 0.7 | C2: 0.63 | D2: 0.67 | E2: 0.6109535
A3: SOL-26JUN26-72-P-USDT | B3: 1.56 | C3: 0.85 | D3: 0.9 | E3: 0.84884646
A4: SOL-26JUN26-74-P-USDT | B4: 1.25 | C4: 1.16 | D4: 1.21 | E4: 1.1703566

Sheet OptionBoard
A1: symbol | B1: strike | C1: delta | D1: gamma | E1: vega | F1: theta | G1: mark_price | H1: iv | I1: dte | J1: T | K1: type | L1: spot_price | M1: hedge_cost_per_day | N1: open_interest
A2: SOL-12JUN26-60-P-USDT | B2: 60 | C2: -0.09762761 | D2: 0.01634276 | E2: 0.01884251 | F2: -0.10762038 | G2: 0.51653985 | H2: 0.9657 | I2: 8 | J2: 0.021917808 | K2: PUT | L2: 71.72 | M2: 0.064567481 | N2: 111
A3: SOL-12JUN26-62-P-USDT | B3: 62 | C3: -0.13199103 | D3: 0.02124147 | E3: 0.0233593 | F3: -0.12725583 | G3: 0.71085656 | H3: 0.9211 | I3: 8 | J3: 0.021917808 | K3: PUT | L3: 71.72 | M3: 0.08885707 | N3: 10
A4: SOL-12JUN26-64-P-USDT | B4: 64 | C4: -0.17725246 | D4: 0.02703299 | E4: 0.02839573 | F4: -0.14775922 | G4: 0.98082448 | H4: 0.8798 | I4: 8 | J4: 0.021917808 | K4: PUT | L4: 71.72 | M4: 0.12260306 | N4: 104
A5: SOL-12JUN26-66-P-USDT | B5: 66 | C5: -0.2354303 | D5: 0.03341661 | E5: 0.03361236 | F5: -0.16748589 | G5: 1.3539284 | H5: 0.8425 | I5: 8 | J5: 0.021917808 | K5: PUT | L5: 71.72 | M5: 0.16924106 | N5: 2162
A6: SOL-12JUN26-68-P-USDT | B6: 68 | C6: -0.3075575 | D6: 0.03972563 | E6: 0.03841604 | F6: -0.1840335 | G6: 1.8634843 | H6: 0.81 | I6: 8 | J6: 0.021917808 | K6: PUT | L6: 71.72 | M6: 0.23293553 | N6: 105
A7: SOL-12JUN26-70-P-USDT | B7: 70 | C7: -0.39257405 | D7: 0.04491861 | E7: 0.04200178 | F7: -0.1945591 | G7: 2.545212 | H7: 0.7832 | I7: 8 | J7: 0.021917808 | K7: PUT | L7: 71.72 | M7: 0.3181515 | N7: 1154
A8: SOL-12JUN26-72-P-USDT | B8: 72 | C8: -0.48639682 | D8: 0.04782202 | E8: 0.04356657 | F8: -0.19661715 | G8: 3.4298496 | H8: 0.7631 | I8: 8 | J8: 0.021917808 | K8: PUT | L8: 71.72 | M8: 0.4287312 | N8: 260
A9: SOL-12JUN26-74-P-USDT | B9: 74 | C9: -0.58211611 | D9: 0.04763922 | E9: 0.04266518 | F9: -0.18928883 | G9: 4.5332691 | H9: 0.7501 | I9: 8 | J9: 0.021917808 | K9: PUT | L9: 71.72 | M9: 0.56665863 | N9: 140
A10: SOL-12JUN26-75-P-USDT | B10: 75 | C10: -0.62819653 | D10: 0.04636835 | E10: 0.04132142 | F10: -0.1824195 | G10: 5.1660093 | H10: 0.7464 | I10: 8 | J10: 0.021917808 | K10: PUT | L10: 71.72 | M10: 0.64575116 | N10: 346
A11: SOL-12JUN26-76-P-USDT | B11: 76 | C11: -0.6718913 | D11: 0.04441771 | E11: 0.03948008 | F11: -0.17383708 | G11: 5.8493848 | H11: 0.7445 | I11: 8 | J11: 0.021917808 | K11: PUT | L11: 71.72 | M11: 0.7311731 | N11: 183
A12: SOL-12JUN26-68-C-USDT | B12: 68 | C12: 0.69244251 | D12: 0.03972563 | E12: 0.03841604 | F12: -0.1840335 | G12: 5.6634843 | H12: 0.81 | I12: 8 | J12: 0.021917808 | K12: CALL | L12: 71.72 | M12: 0.70793553 | N12: 0
A13: SOL-12JUN26-70-C-USDT | B13: 70 | C13: 0.60742596 | D13: 0.04491861 | E13: 0.04200178 | F13: -0.1945591 | G13: 4.345212 | H13: 0.7832 | I13: 8 | J13: 0.021917808 | K13: CALL | L13: 71.72 | M13: 0.5431515 | N13: 0
... A73: SOL-26JUN26-110-C-USDT | B73: 110 | C73: 0.01119287 | D73: 0.00227565 | E73: 0.00523075 | F73: -0.00845894 | G73: 0.04692859 | H73: 0.7263 | I73: 22 | J73: 0.060273973 | K73: CALL | L73: 71.72 | M73: 0.0021331177 | N73: 100

Sheet Actives
A2: Информация по базовому активу
A4: № | B4: Дата покупки | C4: Актив | D4: Количество | E4: Цена | F4: Нач. Стоимость | G4: Тек.стоимость | H4: Pnl
B5: 46114 | C5: Meteor | D5: =2.0423-D8 | E5: 80.5 | F5: =D5*E5 | G5: =D5*Portfolio!$C$4 | H5: =G5-F5
B6: 46113 | C6: Swap | D6: 1.8 | E6: 84.44 | F6: =D6*E6 | G6: =D6*Portfolio!$C$4 | H6: =G6-F6
B7: 46112 | C7: Swap | D7: 1.0007 | E7: 83.26 | F7: =D7*E7 | G7: =D7*Portfolio!$C$4 | H7: =G7-F7
B8: 46110 | C8: Swap | D8: 1.0019 | E8: 81.84 | F8: =D8*E8 | G8: =D8*Portfolio!$C$4 | H8: =G8-F8
B9: 46108 | C9: Swap | D9: 1.0004 | E9: 82.97 | F9: =D9*E9 | G9: =D9*Portfolio!$C$4 | H9: =G9-F9
B10: 46120 | C10: Swap | D10: 2 | E10: 84.6 | F10: =D10*E10 | G10: =D10*Portfolio!$C$4 | H10: =G10-F10
B11: 46172 | C11: Swap | D11: 2 | E11: 82 | F11: =D11*E11 | G11: =D11*Portfolio!$C$4 | H11: =G11-F11
B13: Total | D13: =SUM(D5:D12) | E13: =F13/D13 | F13: =SUM(F5:F12) | G13: =SUM(G5:G12) | H13: =SUM(H5:H12)
A18: № | B18: Дата операции | C18: Protocol | D18: Pnl
B19: 46114 | C19: Option | D19: -10
B20: 46114 | C20: Meteor | D20: 10.95
B21: 46114 | C21: Meteor | D21: 8.73
B22: 46114 | C22: Meteor | D22: 5.4
B23: 46094 | C23: Option | D23: -15
B24: 46093 | C24: Meteor | D24: 4.73
B25: 46115 | C25: Option | D25: 2.37
B26: 46117 | C26: Option | D26: -1.4
B27: 46118 | C27: Option | D27: -2.36
B28: 46118 | C28: Option | D28: -3.5
B29: 46119 | C29: Option | D29: -5.73
B30: 46119 | C30: Option | D30: -5.67
... B34: 46125 | C34: Option | D34: -1.56
D36: =SUM(D19:D35)

Sheet Hedge_Total
A1: symbol | B1: strike | C1: delta | D1: gamma | E1: vega | F1: theta | G1: mark_price | H1: iv | I1: dte | J1: T | K1: type | L1: spot_price | M1: hedge_cost_per_day | N1: total_price | O1: position | P1: contracts | R1: Start | S1: Current
A2: =Portfolio!H10 | B2: =VLOOKUP(A2,OptionBoard!$A$2:$M$86,2,FALSE()) | C2: =VLOOKUP(A2,OptionBoard!$A$2:$M$86,3,0) | D2: =VLOOKUP(A2,OptionBoard!$A$2:$M$86,4,0) | E2: =VLOOKUP(A2,OptionBoard!$A$2:$M$86,5,0) | F2: =VLOOKUP(A2,OptionBoard!$A$2:$M$86,6,0) | G2: =N2/P2 | H2: =VLOOKUP(A2,OptionBoard!$A$2:$M$86,8,0) | I2: =VLOOKUP(A2,OptionBoard!$A$2:$M$86,9,0) | J2: =VLOOKUP(A2,OptionBoard!$A$2:$M$86,10,0) | K2: =VLOOKUP(A2,OptionBoard!$A$2:$M$86,11,FALSE()) | L2: =VLOOKUP(A2,OptionBoard!$A$2:$M$86,12,0) | M2: =VLOOKUP(A2,OptionBoard!$A$2:$M$86,13,0) | N2: =Portfolio!J10 | O2: buy | P2: =Portfolio!I10 | R2: =G2 | S2: =VLOOKUP(A2,OptionBoard!$A$2:$G$93,7,FALSE()) | U2: =R2-S2
A3: =Portfolio!H11 | B3: =VLOOKUP(A3,OptionBoard!$A$2:$M$86,2,FALSE()) | C3: =VLOOKUP(A3,OptionBoard!$A$2:$M$86,3,0) | D3: =VLOOKUP(A3,OptionBoard!$A$2:$M$86,4,0) | E3: =VLOOKUP(A3,OptionBoard!$A$2:$M$86,5,0) | F3: =VLOOKUP(A3,OptionBoard!$A$2:$M$86,6,0) | G3: =N3/P3 | H3: =VLOOKUP(A3,OptionBoard!$A$2:$M$86,8,0) | I3: =VLOOKUP(A3,OptionBoard!$A$2:$M$86,9,0) | J3: =VLOOKUP(A3,OptionBoard!$A$2:$M$86,10,0) | K3: =VLOOKUP(A3,OptionBoard!$A$2:$M$86,11,FALSE()) | L3: =VLOOKUP(A3,OptionBoard!$A$2:$M$86,12,0) | M3: =VLOOKUP(A3,OptionBoard!$A$2:$M$86,13,0) | N3: =Portfolio!J11 | O3: buy | P3: =Portfolio!I11 | R3: =G3 | S3: =VLOOKUP(A3,OptionBoard!$A$2:$G$93,7,FALSE()) | U3: =R3-S3
A4: =Portfolio!H12 | B4: =VLOOKUP(A4,OptionBoard!$A$2:$M$86,2,FALSE()) | C4: =VLOOKUP(A4,OptionBoard!$A$2:$M$86,3,0) | D4: =VLOOKUP(A4,OptionBoard!$A$2:$M$86,4,0) | E4: =VLOOKUP(A4,OptionBoard!$A$2:$M$86,5,0) | F4: =VLOOKUP(A4,OptionBoard!$A$2:$M$86,6,0) | G4: =N4/P4 | H4: =VLOOKUP(A4,OptionBoard!$A$2:$M$86,8,0) | I4: =VLOOKUP(A4,OptionBoard!$A$2:$M$86,9,0) | J4: =VLOOKUP(A4,OptionBoard!$A$2:$M$86,10,0) | K4: =VLOOKUP(A4,OptionBoard!$A$2:$M$86,11,FALSE()) | L4: =VLOOKUP(A4,OptionBoard!$A$2:$M$86,12,0) | M4: =VLOOKUP(A4,OptionBoard!$A$2:$M$86,13,0) | N4: =Portfolio!J12 | O4: buy | P4: =Portfolio!I12 | R4: =G4 | S4: =VLOOKUP(A4,OptionBoard!$A$2:$G$93,7,FALSE()) | U4: =R4-S4
A5: =Portfolio!H13 | B5: =VLOOKUP(A5,OptionBoard!$A$2:$M$86,2,FALSE()) | C5: =VLOOKUP(A5,OptionBoard!$A$2:$M$86,3,0) | D5: =VLOOKUP(A5,OptionBoard!$A$2:$M$86,4,0) | E5: =VLOOKUP(A5,OptionBoard!$A$2:$M$86,5,0) | F5: =VLOOKUP(A5,OptionBoard!$A$2:$M$86,6,0) | G5: =N5/P5 | H5: =VLOOKUP(A5,OptionBoard!$A$2:$M$86,8,0) | I5: =VLOOKUP(A5,OptionBoard!$A$2:$M$86,9,0) | J5: =VLOOKUP(A5,OptionBoard!$A$2:$M$86,10,0) | K5: =VLOOKUP(A5,OptionBoard!$A$2:$M$86,11,FALSE()) | L5: =VLOOKUP(A5,OptionBoard!$A$2:$M$86,12,0) | M5: =VLOOKUP(A5,OptionBoard!$A$2:$M$86,13,0) | N5: =Portfolio!J13 | O5: buy | P5: =Portfolio!I13 | R5: =G5 | S5: =VLOOKUP(A5,OptionBoard!$A$2:$G$93,7,FALSE()) | U5: =R5-S5
A6: =Portfolio!H14 | B6: =VLOOKUP(A6,OptionBoard!$A$2:$M$86,2,FALSE()) | C6: =VLOOKUP(A6,OptionBoard!$A$2:$M$86,3,0) | D6: =VLOOKUP(A6,OptionBoard!$A$2:$M$86,4,0) | E6: =VLOOKUP(A6,OptionBoard!$A$2:$M$86,5,0) | F6: =VLOOKUP(A6,OptionBoard!$A$2:$M$86,6,0) | G6: =N6/P6 | H6: =VLOOKUP(A6,OptionBoard!$A$2:$M$86,8,0) | I6: =VLOOKUP(A6,OptionBoard!$A$2:$M$86,9,0) | J6: =VLOOKUP(A6,OptionBoard!$A$2:$M$86,10,0) | K6: =VLOOKUP(A6,OptionBoard!$A$2:$M$86,11,FALSE()) | L6: =VLOOKUP(A6,OptionBoard!$A$2:$M$86,12,0) | M6: =VLOOKUP(A6,OptionBoard!$A$2:$M$86,13,0) | N6: =Portfolio!J14 | O6: buy | P6: =Portfolio!I14 | R6: =G6 | S6: =VLOOKUP(A6,OptionBoard!$A$2:$G$93,7,FALSE()) | U6: =R6-S6
A7: =Portfolio!H15 | B7: =VLOOKUP(A7,OptionBoard!$A$2:$M$86,2,FALSE()) | C7: =VLOOKUP(A7,OptionBoard!$A$2:$M$86,3,0) | D7: =VLOOKUP(A7,OptionBoard!$A$2:$M$86,4,0) | E7: =VLOOKUP(A7,OptionBoard!$A$2:$M$86,5,0) | F7: =VLOOKUP(A7,OptionBoard!$A$2:$M$86,6,0) | G7: =N7/P7 | H7: =VLOOKUP(A7,OptionBoard!$A$2:$M$86,8,0) | I7: =VLOOKUP(A7,OptionBoard!$A$2:$M$86,9,0) | J7: =VLOOKUP(A7,OptionBoard!$A$2:$M$86,10,0) | K7: =VLOOKUP(A7,OptionBoard!$A$2:$M$86,11,FALSE()) | L7: =VLOOKUP(A7,OptionBoard!$A$2:$M$86,12,0) | M7: =VLOOKUP(A7,OptionBoard!$A$2:$M$86,13,0) | N7: =Portfolio!J15 | O7: buy | P7: =Portfolio!I15 | R7: =G7 | S7: =VLOOKUP(A7,OptionBoard!$A$2:$G$93,7,FALSE()) | U7: =R7-S7
A8: =Portfolio!H16 | B8: =VLOOKUP(A8,OptionBoard!$A$2:$M$86,2,FALSE()) | C8: =VLOOKUP(A8,OptionBoard!$A$2:$M$86,3,0) | D8: =VLOOKUP(A8,OptionBoard!$A$2:$M$86,4,0) | E8: =VLOOKUP(A8,OptionBoard!$A$2:$M$86,5,0) | F8: =VLOOKUP(A8,OptionBoard!$A$2:$M$86,6,0) | G8: =N8/P8 | H8: =VLOOKUP(A8,OptionBoard!$A$2:$M$86,8,0) | I8: =VLOOKUP(A8,OptionBoard!$A$2:$M$86,9,0) | J8: =VLOOKUP(A8,OptionBoard!$A$2:$M$86,10,0) | K8: =VLOOKUP(A8,OptionBoard!$A$2:$M$86,11,FALSE()) | L8: =VLOOKUP(A8,OptionBoard!$A$2:$M$86,12,0) | M8: =VLOOKUP(A8,OptionBoard!$A$2:$M$86,13,0) | N8: =Portfolio!J16 | O8: buy | P8: =Portfolio!I16 | R8: =G8 | S8: =VLOOKUP(A8,OptionBoard!$A$2:$G$93,7,FALSE()) | U8: =R8-S8
A9: =Portfolio!H17 | B9: =VLOOKUP(A9,OptionBoard!$A$2:$M$86,2,FALSE()) | C9: =VLOOKUP(A9,OptionBoard!$A$2:$M$86,3,0) | D9: =VLOOKUP(A9,OptionBoard!$A$2:$M$86,4,0) | E9: =VLOOKUP(A9,OptionBoard!$A$2:$M$86,5,0) | F9: =VLOOKUP(A9,OptionBoard!$A$2:$M$86,6,0) | G9: 1.76 | H9: =VLOOKUP(A9,OptionBoard!$A$2:$M$86,8,0) | I9: =VLOOKUP(A9,OptionBoard!$A$2:$M$86,9,0) | J9: =VLOOKUP(A9,OptionBoard!$A$2:$M$86,10,0) | K9: =VLOOKUP(A9,OptionBoard!$A$2:$M$86,11,FALSE()) | L9: =VLOOKUP(A9,OptionBoard!$A$2:$M$86,12,0) | M9: =VLOOKUP(A9,OptionBoard!$A$2:$M$86,13,0) | N9: =G9*P9 | O9: buy | P9: =Portfolio!I17 | R9: =G9 | S9: =VLOOKUP(A9,OptionBoard!$A$2:$G$93,7,FALSE()) | U9: =R9-S9
A10: =Portfolio!H18 | B10: =VLOOKUP(A10,OptionBoard!$A$2:$M$86,2,FALSE()) | C10: =VLOOKUP(A10,OptionBoard!$A$2:$M$86,3,0) | D10: =VLOOKUP(A10,OptionBoard!$A$2:$M$86,4,0) | E10: =VLOOKUP(A10,OptionBoard!$A$2:$M$86,5,0) | F10: =VLOOKUP(A10,OptionBoard!$A$2:$M$86,6,0) | G10: 2.15 | H10: =VLOOKUP(A10,OptionBoard!$A$2:$M$86,8,0) | I10: =VLOOKUP(A10,OptionBoard!$A$2:$M$86,9,0) | J10: =VLOOKUP(A10,OptionBoard!$A$2:$M$86,10,0) | K10: =VLOOKUP(A10,OptionBoard!$A$2:$M$86,11,FALSE()) | L10: =VLOOKUP(A10,OptionBoard!$A$2:$M$86,12,0) | M10: =VLOOKUP(A10,OptionBoard!$A$2:$M$86,13,0) | N10: =G10*P10 | O10: buy | P10: =Portfolio!I18 | R10: =G10 | S10: =VLOOKUP(A10,OptionBoard!$A$2:$G$93,7,FALSE()) | U10: =R10-S10
A11: =Portfolio!H19 | B11: =VLOOKUP(A11,OptionBoard!$A$2:$M$86,2,FALSE()) | C11: =VLOOKUP(A11,OptionBoard!$A$2:$M$86,3,0) | D11: =VLOOKUP(A11,OptionBoard!$A$2:$M$86,4,0) | E11: =VLOOKUP(A11,OptionBoard!$A$2:$M$86,5,0) | F11: =VLOOKUP(A11,OptionBoard!$A$2:$M$86,6,0) | G11: 9.61 | H11: =VLOOKUP(A11,OptionBoard!$A$2:$M$86,8,0) | I11: =VLOOKUP(A11,OptionBoard!$A$2:$M$86,9,0) | J11: =VLOOKUP(A11,OptionBoard!$A$2:$M$86,10,0) | K11: =VLOOKUP(A11,OptionBoard!$A$2:$M$86,11,FALSE()) | L11: =VLOOKUP(A11,OptionBoard!$A$2:$M$86,12,0) | M11: =VLOOKUP(A11,OptionBoard!$A$2:$M$86,13,0) | N11: =G11*P11 | O11: buy | P11: =Portfolio!I19 | R11: =G11 | S11: =VLOOKUP(A11,OptionBoard!$A$2:$G$93,7,FALSE()) | U11: =R11-S11
A12: =Portfolio!H20 | B12: =VLOOKUP(A12,OptionBoard!$A$2:$M$86,2,FALSE()) | C12: =VLOOKUP(A12,OptionBoard!$A$2:$M$86,3,0) | D12: =VLOOKUP(A12,OptionBoard!$A$2:$M$86,4,0) | E12: =VLOOKUP(A12,OptionBoard!$A$2:$M$86,5,0) | F12: =VLOOKUP(A12,OptionBoard!$A$2:$M$86,6,0) | G12: 0.48 | H12: =VLOOKUP(A12,OptionBoard!$A$2:$M$86,8,0) | I12: =VLOOKUP(A12,OptionBoard!$A$2:$M$86,9,0) | J12: =VLOOKUP(A12,OptionBoard!$A$2:$M$86,10,0) | K12: =VLOOKUP(A12,OptionBoard!$A$2:$M$86,11,FALSE()) | L12: =VLOOKUP(A12,OptionBoard!$A$2:$M$86,12,0) | M12: =VLOOKUP(A12,OptionBoard!$A$2:$M$86,13,0) | N12: =G12*P12 | O12: buy | P12: =Portfolio!I20 | R12: =G12 | S12: =VLOOKUP(A12,OptionBoard!$A$2:$G$93,7,FALSE())
A13: =Portfolio!H21 | B13: =VLOOKUP(A13,OptionBoard!$A$2:$M$86,2,FALSE()) | C13: =VLOOKUP(A13,OptionBoard!$A$2:$M$86,3,0) | D13: =VLOOKUP(A13,OptionBoard!$A$2:$M$86,4,0) | E13: =VLOOKUP(A13,OptionBoard!$A$2:$M$86,5,0) | F13: =VLOOKUP(A13,OptionBoard!$A$2:$M$86,6,0) | G13: 1.96 | H13: =VLOOKUP(A13,OptionBoard!$A$2:$M$86,8,0) | I13: =VLOOKUP(A13,OptionBoard!$A$2:$M$86,9,0) | J13: =VLOOKUP(A13,OptionBoard!$A$2:$M$86,10,0) | K13: =VLOOKUP(A13,OptionBoard!$A$2:$M$86,11,FALSE()) | L13: =VLOOKUP(A13,OptionBoard!$A$2:$M$86,12,0) | M13: =VLOOKUP(A13,OptionBoard!$A$2:$M$86,13,0) | N13: =G13*P13 | O13: buy | P13: =Portfolio!I21 | R13: =G13 | S13: =VLOOKUP(A13,OptionBoard!$A$2:$G$93,7,FALSE())
A14: =Portfolio!H22 | B14: =VLOOKUP(A14,OptionBoard!$A$2:$M$86,2,FALSE()) | C14: =VLOOKUP(A14,OptionBoard!$A$2:$M$86,3,0) | D14: =VLOOKUP(A14,OptionBoard!$A$2:$M$86,4,0) | E14: =VLOOKUP(A14,OptionBoard!$A$2:$M$86,5,0) | F14: =VLOOKUP(A14,OptionBoard!$A$2:$M$86,6,0) | G14: 2.3 | H14: =VLOOKUP(A14,OptionBoard!$A$2:$M$86,8,0) | I14: =VLOOKUP(A14,OptionBoard!$A$2:$M$86,9,0) | J14: =VLOOKUP(A14,OptionBoard!$A$2:$M$86,10,0) | K14: =VLOOKUP(A14,OptionBoard!$A$2:$M$86,11,FALSE()) | L14: =VLOOKUP(A14,OptionBoard!$A$2:$M$86,12,0) | M14: =VLOOKUP(A14,OptionBoard!$A$2:$M$86,13,0) | N14: =G14*P14 | O14: buy | P14: =Portfolio!I22 | R14: =G14 | S14: =VLOOKUP(A14,OptionBoard!$A$2:$G$93,7,FALSE())
A15: =Portfolio!H23 | B15: =VLOOKUP(A15,OptionBoard!$A$2:$M$86,2,FALSE()) | C15: =VLOOKUP(A15,OptionBoard!$A$2:$M$86,3,0) | D15: =VLOOKUP(A15,OptionBoard!$A$2:$M$86,4,0) | E15: =VLOOKUP(A15,OptionBoard!$A$2:$M$86,5,0) | F15: =VLOOKUP(A15,OptionBoard!$A$2:$M$86,6,0) | G15: 1.42 | H15: =VLOOKUP(A15,OptionBoard!$A$2:$M$86,8,0) | I15: =VLOOKUP(A15,OptionBoard!$A$2:$M$86,9,0) | J15: =VLOOKUP(A15,OptionBoard!$A$2:$M$86,10,0) | K15: =VLOOKUP(A15,OptionBoard!$A$2:$M$86,11,FALSE()) | L15: =VLOOKUP(A15,OptionBoard!$A$2:$M$86,12,0) | M15: =VLOOKUP(A15,OptionBoard!$A$2:$M$86,13,0) | N15: =G15*P15 | O15: buy | P15: =Portfolio!I23 | R15: =G15 | S15: =VLOOKUP(A15,OptionBoard!$A$2:$G$93,7,FALSE())
A18: Now_Greeks | C18: =(IF($O$2="buy",1,-1) * C2 * P2)+(IF($O$3="buy",1,-1) * C3 * P3)+(IF($O$4="buy",1,-1) * C4 * P4)+(IF($O$5="buy",1,-1) * C5 * P5)+(IF($O$6="buy",1,-1) * C6 * P6)+(IF($O$7="buy",1,-1) * C7 * P7)+(IF($O$8="buy",1,-1) * C8 * P8)+(IF($O$9="buy",1,-1) * C9 * P9)+(IF($O$10="buy",1,-1) * C10 * P10)+(IF($O$11="buy",1,-1) * C11 * P11)+(IF($O$12="buy",1,-1) * C12 * P12)+(IF($O$13="buy",1,-1) * C13 * P13)+(IF($O$14="buy",1,-1) * C14 * P14)+(IF($O$15="buy",1,-1) * C15 * P15) | D18: =(IF($O$2="buy",1,-1) * D2 * P2)+(IF($O$3="buy",1,-1) * D3 * P3)+(IF($O$4="buy",1,-1) * D4 * P4)+(IF($O$5="buy",1,-1) * D5 * P5)+(IF($O$6="buy",1,-1) * D6 * P6)+(IF($O$7="buy",1,-1) * D7 * P7)+(IF($O$8="buy",1,-1) * D8 * P8)+(IF($O$9="buy",1,-1) * D9 * P9)+(IF($O$10="buy",1,-1) * D10 * P10)+(IF($O$11="buy",1,-1) * D11 * P11)+(IF($O$12="buy",1,-1) * D12 * P12)+(IF($O$13="buy",1,-1) * D13 * P13)+(IF($O$14="buy",1,-1) * D14 * P14)+(IF($O$15="buy",1,-1) * D15 * P15) | E18: =(IF($O$2="buy",1,-1) * E2 * P2)+(IF($O$3="buy",1,-1) * E3 * P3)+(IF($O$4="buy",1,-1) * E4 * P4)+(IF($O$5="buy",1,-1) * E5 * P5)+(IF($O$6="buy",1,-1) * E6 * P6)+(IF($O$7="buy",1,-1) * E7 * P7)+(IF($O$8="buy",1,-1) * E8 * P8)+(IF($O$9="buy",1,-1) * E9 * P9)+(IF($O$10="buy",1,-1) * E10 * P10)+(IF($O$11="buy",1,-1) * E11 * P11)+(IF($O$12="buy",1,-1) * E12 * P12)+(IF($O$13="buy",1,-1) * E13 * P13)+(IF($O$14="buy",1,-1) * E14 * P14)+(IF($O$15="buy",1,-1) * E15 * P15) | F18: =(IF($O$2="buy",1,-1) * F2 * P2)+(IF($O$3="buy",1,-1) * F3 * P3)+(IF($O$4="buy",1,-1) * F4 * P4)+(IF($O$5="buy",1,-1) * F5 * P5)+(IF($O$6="buy",1,-1) * F6 * P6)+(IF($O$7="buy",1,-1) * F7 * P7)+(IF($O$8="buy",1,-1) * F8 * P8)+(IF($O$9="buy",1,-1) * F9 * P9)+(IF($O$10="buy",1,-1) * F10 * P10)+(IF($O$11="buy",1,-1) * F11 * P11)+(IF($O$12="buy",1,-1) * F12 * P12)+(IF($O$13="buy",1,-1) * F13 * P13)+(IF($O$14="buy",1,-1) * F14 * P14)+(IF($O$15="buy",1,-1) * F15 * P15) | G18: =(IF($O$2="buy",1,-1) * G2 * P2)+(IF($O$3="buy",1,-1) * G3 * P3)+(IF($O$4="buy",1,-1) * G4 * P4)+(IF($O$5="buy",1,-1) * G5 * P5)+(IF($O$6="buy",1,-1) * G6 * P6)+(IF($O$7="buy",1,-1) * G7 * P7)+(IF($O$8="buy",1,-1) * G8 * P8)+(IF($O$9="buy",1,-1) * G9 * P9)+(IF($O$10="buy",1,-1) * G10 * P10)+(IF($O$11="buy",1,-1) * G11 * P11)+(IF($O$12="buy",1,-1) * G12 * P12)+(IF($O$13="buy",1,-1) * G13 * P13)+(IF($O$14="buy",1,-1) * G14 * P14)+(IF($O$15="buy",1,-1) * G15 * P15) | M18: =M2*P2+M3*P3+M5*P5+M4*P4+M6*P6+M7*P7+M8*P8+M9*P9+M10*P10+M11*P11+M12*P12+M13*P13+M14*P14+M15*P15 | S18: =F18/C18
A20: =A2 | C20: delta | D20: gamma | E20: vega | F20: theta | G20: mark_price | I20: d1 | J20: d2
B21: =Portfolio!B28 | C21: =IF($O$2="sell",-1,1) * IF($K$2="call", NORMDIST(I21,0,1,1), NORMDIST(I21,0,1,1)-1 ) * $P$2 | D21: =IF($O$2="sell",-1,1) * NORMDIST(I21,0,1,0)/(B21*$H$2*SQRT($J$2)) * $P$2 | E21: =IF($O$2="sell",-1,1) * (B21*NORMDIST(I21,0,1,0)*SQRT($J$2)/365) * $P$2 | F21: =IF($O$2="sell",-1,1) * (-(B21*NORMDIST(I21,0,1,0)*$H$2)/(2*SQRT($J$2))/365) *$P$2 | G21: =IF($O$2="buy",1,-1)*( IF($K$2="call",B21*NORMDIST(I21,0,1,1) - $B$2*NORMDIST(J21,0,1,1),$B$2*NORMDIST(-J21,0,1,1) - B21*NORMDIST(-I21,0,1,1) ) - $G$2) * $P$2 | I21: =(LN(B21/$B$2)+($H$2^2/2)*($J$2))/($H$2*SQRT($J$2)) | J21: =I21 - $H$2*SQRT($J$2)
B22: =Portfolio!B29 | C22: =IF($O$2="sell",-1,1) * IF($K$2="call", NORMDIST(I22,0,1,1), NORMDIST(I22,0,1,1)-1 ) * $P$2 | D22: =IF($O$2="sell",-1,1) * NORMDIST(I22,0,1,0)/(B22*$H$2*SQRT($J$2)) * $P$2 | E22: =IF($O$2="sell",-1,1) * (B22*NORMDIST(I22,0,1,0)*SQRT($J$2)/365) * $P$2 | F22: =IF($O$2="sell",-1,1) * (-(B22*NORMDIST(I22,0,1,0)*$H$2)/(2*SQRT($J$2))/365) *$P$2 | G22: =IF($O$2="buy",1,-1)*( IF($K$2="call",B22*NORMDIST(I22,0,1,1) - $B$2*NORMDIST(J22,0,1,1),$B$2*NORMDIST(-J22,0,1,1) - B22*NORMDIST(-I22,0,1,1) ) - $G$2) * $P$2 | I22: =(LN(B22/$B$2)+($H$2^2/2)*($J$2))/($H$2*SQRT($J$2)) | J22: =I22 - $H$2*SQRT($J$2)
B23: =Portfolio!B30 | C23: =IF($O$2="sell",-1,1) * IF($K$2="call", NORMDIST(I23,0,1,1), NORMDIST(I23,0,1,1)-1 ) * $P$2 | D23: =IF($O$2="sell",-1,1) * NORMDIST(I23,0,1,0)/(B23*$H$2*SQRT($J$2)) * $P$2 | E23: =IF($O$2="sell",-1,1) * (B23*NORMDIST(I23,0,1,0)*SQRT($J$2)/365) * $P$2 | F23: =IF($O$2="sell",-1,1) * (-(B23*NORMDIST(I23,0,1,0)*$H$2)/(2*SQRT($J$2))/365) *$P$2 | G23: =IF($O$2="buy",1,-1)*( IF($K$2="call",B23*NORMDIST(I23,0,1,1) - $B$2*NORMDIST(J23,0,1,1),$B$2*NORMDIST(-J23,0,1,1) - B23*NORMDIST(-I23,0,1,1) ) - $G$2) * $P$2 | I23: =(LN(B23/$B$2)+($H$2^2/2)*($J$2))/($H$2*SQRT($J$2)) | J23: =I23 - $H$2*SQRT($J$2)
B24: =Portfolio!B31 | C24: =IF($O$2="sell",-1,1) * IF($K$2="call", NORMDIST(I24,0,1,1), NORMDIST(I24,0,1,1)-1 ) * $P$2 | D24: =IF($O$2="sell",-1,1) * NORMDIST(I24,0,1,0)/(B24*$H$2*SQRT($J$2)) * $P$2 | E24: =IF($O$2="sell",-1,1) * (B24*NORMDIST(I24,0,1,0)*SQRT($J$2)/365) * $P$2 | F24: =IF($O$2="sell",-1,1) * (-(B24*NORMDIST(I24,0,1,0)*$H$2)/(2*SQRT($J$2))/365) *$P$2 | G24: =IF($O$2="buy",1,-1)*( IF($K$2="call",B24*NORMDIST(I24,0,1,1) - $B$2*NORMDIST(J24,0,1,1),$B$2*NORMDIST(-J24,0,1,1) - B24*NORMDIST(-I24,0,1,1) ) - $G$2) * $P$2 | I24: =(LN(B24/$B$2)+($H$2^2/2)*($J$2))/($H$2*SQRT($J$2)) | J24: =I24 - $H$2*SQRT($J$2)
B25: =Portfolio!B32 | C25: =IF($O$2="sell",-1,1) * IF($K$2="call", NORMDIST(I25,0,1,1), NORMDIST(I25,0,1,1)-1 ) * $P$2 | D25: =IF($O$2="sell",-1,1) * NORMDIST(I25,0,1,0)/(B25*$H$2*SQRT($J$2)) * $P$2 | E25: =IF($O$2="sell",-1,1) * (B25*NORMDIST(I25,0,1,0)*SQRT($J$2)/365) * $P$2 | F25: =IF($O$2="sell",-1,1) * (-(B25*NORMDIST(I25,0,1,0)*$H$2)/(2*SQRT($J$2))/365) *$P$2 | G25: =IF($O$2="buy",1,-1)*( IF($K$2="call",B25*NORMDIST(I25,0,1,1) - $B$2*NORMDIST(J25,0,1,1),$B$2*NORMDIST(-J25,0,1,1) - B25*NORMDIST(-I25,0,1,1) ) - $G$2) * $P$2 | I25: =(LN(B25/$B$2)+($H$2^2/2)*($J$2))/($H$2*SQRT($J$2)) | J25: =I25 - $H$2*SQRT($J$2)
B26: =Portfolio!B33 | C26: =IF($O$2="sell",-1,1) * IF($K$2="call", NORMDIST(I26,0,1,1), NORMDIST(I26,0,1,1)-1 ) * $P$2 | D26: =IF($O$2="sell",-1,1) * NORMDIST(I26,0,1,0)/(B26*$H$2*SQRT($J$2)) * $P$2 | E26: =IF($O$2="sell",-1,1) * (B26*NORMDIST(I26,0,1,0)*SQRT($J$2)/365) * $P$2 | F26: =IF($O$2="sell",-1,1) * (-(B26*NORMDIST(I26,0,1,0)*$H$2)/(2*SQRT($J$2))/365) *$P$2 | G26: =IF($O$2="buy",1,-1)*( IF($K$2="call",B26*NORMDIST(I26,0,1,1) - $B$2*NORMDIST(J26,0,1,1),$B$2*NORMDIST(-J26,0,1,1) - B26*NORMDIST(-I26,0,1,1) ) - $G$2) * $P$2 | I26: =(LN(B26/$B$2)+($H$2^2/2)*($J$2))/($H$2*SQRT($J$2)) | J26: =I26 - $H$2*SQRT($J$2)
B27: =Portfolio!B34 | C27: =IF($O$2="sell",-1,1) * IF($K$2="call", NORMDIST(I27,0,1,1), NORMDIST(I27,0,1,1)-1 ) * $P$2 | D27: =IF($O$2="sell",-1,1) * NORMDIST(I27,0,1,0)/(B27*$H$2*SQRT($J$2)) * $P$2 | E27: =IF($O$2="sell",-1,1) * (B27*NORMDIST(I27,0,1,0)*SQRT($J$2)/365) * $P$2 | F27: =IF($O$2="sell",-1,1) * (-(B27*NORMDIST(I27,0,1,0)*$H$2)/(2*SQRT($J$2))/365) *$P$2 | G27: =IF($O$2="buy",1,-1)*( IF($K$2="call",B27*NORMDIST(I27,0,1,1) - $B$2*NORMDIST(J27,0,1,1),$B$2*NORMDIST(-J27,0,1,1) - B27*NORMDIST(-I27,0,1,1) ) - $G$2) * $P$2 | I27: =(LN(B27/$B$2)+($H$2^2/2)*($J$2))/($H$2*SQRT($J$2)) | J27: =I27 - $H$2*SQRT($J$2)
B28: =Portfolio!B35 | C28: =IF($O$2="sell",-1,1) * IF($K$2="call", NORMDIST(I28,0,1,1), NORMDIST(I28,0,1,1)-1 ) * $P$2 | D28: =IF($O$2="sell",-1,1) * NORMDIST(I28,0,1,0)/(B28*$H$2*SQRT($J$2)) * $P$2 | E28: =IF($O$2="sell",-1,1) * (B28*NORMDIST(I28,0,1,0)*SQRT($J$2)/365) * $P$2 | F28: =IF($O$2="sell",-1,1) * (-(B28*NORMDIST(I28,0,1,0)*$H$2)/(2*SQRT($J$2))/365) *$P$2 | G28: =IF($O$2="buy",1,-1)*( IF($K$2="call",B28*NORMDIST(I28,0,1,1) - $B$2*NORMDIST(J28,0,1,1),$B$2*NORMDIST(-J28,0,1,1) - B28*NORMDIST(-I28,0,1,1) ) - $G$2) * $P$2 | I28: =(LN(B28/$B$2)+($H$2^2/2)*($J$2))/($H$2*SQRT($J$2)) | J28: =I28 - $H$2*SQRT($J$2)
B29: =Portfolio!B36 | C29: =IF($O$2="sell",-1,1) * IF($K$2="call", NORMDIST(I29,0,1,1), NORMDIST(I29,0,1,1)-1 ) * $P$2 | D29: =IF($O$2="sell",-1,1) * NORMDIST(I29,0,1,0)/(B29*$H$2*SQRT($J$2)) * $P$2 | E29: =IF($O$2="sell",-1,1) * (B29*NORMDIST(I29,0,1,0)*SQRT($J$2)/365) * $P$2 | F29: =IF($O$2="sell",-1,1) * (-(B29*NORMDIST(I29,0,1,0)*$H$2)/(2*SQRT($J$2))/365) *$P$2 | G29: =IF($O$2="buy",1,-1)*( IF($K$2="call",B29*NORMDIST(I29,0,1,1) - $B$2*NORMDIST(J29,0,1,1),$B$2*NORMDIST(-J29,0,1,1) - B29*NORMDIST(-I29,0,1,1) ) - $G$2) * $P$2 | I29: =(LN(B29/$B$2)+($H$2^2/2)*($J$2))/($H$2*SQRT($J$2)) | J29: =I29 - $H$2*SQRT($J$2)
B30: =Portfolio!B37 | C30: =IF($O$2="sell",-1,1) * IF($K$2="call", NORMDIST(I30,0,1,1), NORMDIST(I30,0,1,1)-1 ) * $P$2 | D30: =IF($O$2="sell",-1,1) * NORMDIST(I30,0,1,0)/(B30*$H$2*SQRT($J$2)) * $P$2 | E30: =IF($O$2="sell",-1,1) * (B30*NORMDIST(I30,0,1,0)*SQRT($J$2)/365) * $P$2 | F30: =IF($O$2="sell",-1,1) * (-(B30*NORMDIST(I30,0,1,0)*$H$2)/(2*SQRT($J$2))/365) *$P$2 | G30: =IF($O$2="buy",1,-1)*( IF($K$2="call",B30*NORMDIST(I30,0,1,1) - $B$2*NORMDIST(J30,0,1,1),$B$2*NORMDIST(-J30,0,1,1) - B30*NORMDIST(-I30,0,1,1) ) - $G$2) * $P$2 | I30: =(LN(B30/$B$2)+($H$2^2/2)*($J$2))/($H$2*SQRT($J$2)) | J30: =I30 - $H$2*SQRT($J$2)
B31: =Portfolio!B38 | C31: =IF($O$2="sell",-1,1) * IF($K$2="call", NORMDIST(I31,0,1,1), NORMDIST(I31,0,1,1)-1 ) * $P$2 | D31: =IF($O$2="sell",-1,1) * NORMDIST(I31,0,1,0)/(B31*$H$2*SQRT($J$2)) * $P$2 | E31: =IF($O$2="sell",-1,1) * (B31*NORMDIST(I31,0,1,0)*SQRT($J$2)/365) * $P$2 | F31: =IF($O$2="sell",-1,1) * (-(B31*NORMDIST(I31,0,1,0)*$H$2)/(2*SQRT($J$2))/365) *$P$2 | G31: =IF($O$2="buy",1,-1)*( IF($K$2="call",B31*NORMDIST(I31,0,1,1) - $B$2*NORMDIST(J31,0,1,1),$B$2*NORMDIST(-J31,0,1,1) - B31*NORMDIST(-I31,0,1,1) ) - $G$2) * $P$2 | I31: =(LN(B31/$B$2)+($H$2^2/2)*($J$2))/($H$2*SQRT($J$2)) | J31: =I31 - $H$2*SQRT($J$2)
B32: =Portfolio!B39 | C32: =IF($O$2="sell",-1,1) * IF($K$2="call", NORMDIST(I32,0,1,1), NORMDIST(I32,0,1,1)-1 ) * $P$2 | D32: =IF($O$2="sell",-1,1) * NORMDIST(I32,0,1,0)/(B32*$H$2*SQRT($J$2)) * $P$2 | E32: =IF($O$2="sell",-1,1) * (B32*NORMDIST(I32,0,1,0)*SQRT($J$2)/365) * $P$2 | F32: =IF($O$2="sell",-1,1) * (-(B32*NORMDIST(I32,0,1,0)*$H$2)/(2*SQRT($J$2))/365) *$P$2 | G32: =IF($O$2="buy",1,-1)*( IF($K$2="call",B32*NORMDIST(I32,0,1,1) - $B$2*NORMDIST(J32,0,1,1),$B$2*NORMDIST(-J32,0,1,1) - B32*NORMDIST(-I32,0,1,1) ) - $G$2) * $P$2 | I32: =(LN(B32/$B$2)+($H$2^2/2)*($J$2))/($H$2*SQRT($J$2)) | J32: =I32 - $H$2*SQRT($J$2)
... B47: =Portfolio!B54 | C47: =IF($O$2="sell",-1,1) * IF($K$2="call", NORMDIST(I47,0,1,1), NORMDIST(I47,0,1,1)-1 ) * $P$2 | D47: =IF($O$2="sell",-1,1) * NORMDIST(I47,0,1,0)/(B47*$H$2*SQRT($J$2)) * $P$2 | E47: =IF($O$2="sell",-1,1) * (B47*NORMDIST(I47,0,1,0)*SQRT($J$2)/365) * $P$2 | F47: =IF($O$2="sell",-1,1) * (-(B47*NORMDIST(I47,0,1,0)*$H$2)/(2*SQRT($J$2))/365) *$P$2 | G47: =IF($O$2="buy",1,-1)*( IF($K$2="call",B47*NORMDIST(I47,0,1,1) - $B$2*NORMDIST(J47,0,1,1),$B$2*NORMDIST(-J47,0,1,1) - B47*NORMDIST(-I47,0,1,1) ) - $G$2) * $P$2 | I47: =(LN(B47/$B$2)+($H$2^2/2)*($J$2))/($H$2*SQRT($J$2)) | J47: =I47 - $H$2*SQRT($J$2)
A49: =A3 | C49: delta | D49: gamma | E49: vega | F49: theta | G49: mark_price | I49: d1 | J49: d2
B50: =B21 | C50: =IF($O$3="sell",-1,1) * IF($K$3="call", NORMDIST(I50,0,1,1), NORMDIST(I50,0,1,1)-1 ) * $P$3 | D50: =IF($O$3="sell",-1,1) * NORMDIST(I50,0,1,0)/(B50*$H$3*SQRT($J$3)) * $P$3 | E50: =IF($O$3="sell",-1,1) * (B50*NORMDIST(I50,0,1,0)*SQRT($J$3)/365) * $P$3 | F50: =IF($O$3="sell",-1,1) * (-(B50*NORMDIST(I50,0,1,0)*$H$3)/(2*SQRT($J$3))/365) *$P$3 | G50: =IF($O$3="buy",1,-1)*( IF($K$3="call",B50*NORMDIST(I50,0,1,1) - $B$3*NORMDIST(J50,0,1,1),$B$3*NORMDIST(-J50,0,1,1) - B50*NORMDIST(-I50,0,1,1) ) - $G$3) * $P$3 | I50: =(LN(B50/$B$3)+($H$3^2/2)*($J$3))/($H$3*SQRT($J$3)) | J50: =I50 - $H$3*SQRT($J$3)
B51: =B22 | C51: =IF($O$3="sell",-1,1) * IF($K$3="call", NORMDIST(I51,0,1,1), NORMDIST(I51,0,1,1)-1 ) * $P$3 | D51: =IF($O$3="sell",-1,1) * NORMDIST(I51,0,1,0)/(B51*$H$3*SQRT($J$3)) * $P$3 | E51: =IF($O$3="sell",-1,1) * (B51*NORMDIST(I51,0,1,0)*SQRT($J$3)/365) * $P$3 | F51: =IF($O$3="sell",-1,1) * (-(B51*NORMDIST(I51,0,1,0)*$H$3)/(2*SQRT($J$3))/365) *$P$3 | G51: =IF($O$3="buy",1,-1)*( IF($K$3="call",B51*NORMDIST(I51,0,1,1) - $B$3*NORMDIST(J51,0,1,1),$B$3*NORMDIST(-J51,0,1,1) - B51*NORMDIST(-I51,0,1,1) ) - $G$3) * $P$3 | I51: =(LN(B51/$B$3)+($H$3^2/2)*($J$3))/($H$3*SQRT($J$3)) | J51: =I51 - $H$3*SQRT($J$3)
B52: =B23 | C52: =IF($O$3="sell",-1,1) * IF($K$3="call", NORMDIST(I52,0,1,1), NORMDIST(I52,0,1,1)-1 ) * $P$3 | D52: =IF($O$3="sell",-1,1) * NORMDIST(I52,0,1,0)/(B52*$H$3*SQRT($J$3)) * $P$3 | E52: =IF($O$3="sell",-1,1) * (B52*NORMDIST(I52,0,1,0)*SQRT($J$3)/365) * $P$3 | F52: =IF($O$3="sell",-1,1) * (-(B52*NORMDIST(I52,0,1,0)*$H$3)/(2*SQRT($J$3))/365) *$P$3 | G52: =IF($O$3="buy",1,-1)*( IF($K$3="call",B52*NORMDIST(I52,0,1,1) - $B$3*NORMDIST(J52,0,1,1),$B$3*NORMDIST(-J52,0,1,1) - B52*NORMDIST(-I52,0,1,1) ) - $G$3) * $P$3 | I52: =(LN(B52/$B$3)+($H$3^2/2)*($J$3))/($H$3*SQRT($J$3)) | J52: =I52 - $H$3*SQRT($J$3)
B53: =B24 | C53: =IF($O$3="sell",-1,1) * IF($K$3="call", NORMDIST(I53,0,1,1), NORMDIST(I53,0,1,1)-1 ) * $P$3 | D53: =IF($O$3="sell",-1,1) * NORMDIST(I53,0,1,0)/(B53*$H$3*SQRT($J$3)) * $P$3 | E53: =IF($O$3="sell",-1,1) * (B53*NORMDIST(I53,0,1,0)*SQRT($J$3)/365) * $P$3 | F53: =IF($O$3="sell",-1,1) * (-(B53*NORMDIST(I53,0,1,0)*$H$3)/(2*SQRT($J$3))/365) *$P$3 | G53: =IF($O$3="buy",1,-1)*( IF($K$3="call",B53*NORMDIST(I53,0,1,1) - $B$3*NORMDIST(J53,0,1,1),$B$3*NORMDIST(-J53,0,1,1) - B53*NORMDIST(-I53,0,1,1) ) - $G$3) * $P$3 | I53: =(LN(B53/$B$3)+($H$3^2/2)*($J$3))/($H$3*SQRT($J$3)) | J53: =I53 - $H$3*SQRT($J$3)
B54: =B25 | C54: =IF($O$3="sell",-1,1) * IF($K$3="call", NORMDIST(I54,0,1,1), NORMDIST(I54,0,1,1)-1 ) * $P$3 | D54: =IF($O$3="sell",-1,1) * NORMDIST(I54,0,1,0)/(B54*$H$3*SQRT($J$3)) * $P$3 | E54: =IF($O$3="sell",-1,1) * (B54*NORMDIST(I54,0,1,0)*SQRT($J$3)/365) * $P$3 | F54: =IF($O$3="sell",-1,1) * (-(B54*NORMDIST(I54,0,1,0)*$H$3)/(2*SQRT($J$3))/365) *$P$3 | G54: =IF($O$3="buy",1,-1)*( IF($K$3="call",B54*NORMDIST(I54,0,1,1) - $B$3*NORMDIST(J54,0,1,1),$B$3*NORMDIST(-J54,0,1,1) - B54*NORMDIST(-I54,0,1,1) ) - $G$3) * $P$3 | I54: =(LN(B54/$B$3)+($H$3^2/2)*($J$3))/($H$3*SQRT($J$3)) | J54: =I54 - $H$3*SQRT($J$3)
B55: =B26 | C55: =IF($O$3="sell",-1,1) * IF($K$3="call", NORMDIST(I55,0,1,1), NORMDIST(I55,0,1,1)-1 ) * $P$3 | D55: =IF($O$3="sell",-1,1) * NORMDIST(I55,0,1,0)/(B55*$H$3*SQRT($J$3)) * $P$3 | E55: =IF($O$3="sell",-1,1) * (B55*NORMDIST(I55,0,1,0)*SQRT($J$3)/365) * $P$3 | F55: =IF($O$3="sell",-1,1) * (-(B55*NORMDIST(I55,0,1,0)*$H$3)/(2*SQRT($J$3))/365) *$P$3 | G55: =IF($O$3="buy",1,-1)*( IF($K$3="call",B55*NORMDIST(I55,0,1,1) - $B$3*NORMDIST(J55,0,1,1),$B$3*NORMDIST(-J55,0,1,1) - B55*NORMDIST(-I55,0,1,1) ) - $G$3) * $P$3 | I55: =(LN(B55/$B$3)+($H$3^2/2)*($J$3))/($H$3*SQRT($J$3)) | J55: =I55 - $H$3*SQRT($J$3)
B56: =B27 | C56: =IF($O$3="sell",-1,1) * IF($K$3="call", NORMDIST(I56,0,1,1), NORMDIST(I56,0,1,1)-1 ) * $P$3 | D56: =IF($O$3="sell",-1,1) * NORMDIST(I56,0,1,0)/(B56*$H$3*SQRT($J$3)) * $P$3 | E56: =IF($O$3="sell",-1,1) * (B56*NORMDIST(I56,0,1,0)*SQRT($J$3)/365) * $P$3 | F56: =IF($O$3="sell",-1,1) * (-(B56*NORMDIST(I56,0,1,0)*$H$3)/(2*SQRT($J$3))/365) *$P$3 | G56: =IF($O$3="buy",1,-1)*( IF($K$3="call",B56*NORMDIST(I56,0,1,1) - $B$3*NORMDIST(J56,0,1,1),$B$3*NORMDIST(-J56,0,1,1) - B56*NORMDIST(-I56,0,1,1) ) - $G$3) * $P$3 | I56: =(LN(B56/$B$3)+($H$3^2/2)*($J$3))/($H$3*SQRT($J$3)) | J56: =I56 - $H$3*SQRT($J$3)
B57: =B28 | C57: =IF($O$3="sell",-1,1) * IF($K$3="call", NORMDIST(I57,0,1,1), NORMDIST(I57,0,1,1)-1 ) * $P$3 | D57: =IF($O$3="sell",-1,1) * NORMDIST(I57,0,1,0)/(B57*$H$3*SQRT($J$3)) * $P$3 | E57: =IF($O$3="sell",-1,1) * (B57*NORMDIST(I57,0,1,0)*SQRT($J$3)/365) * $P$3 | F57: =IF($O$3="sell",-1,1) * (-(B57*NORMDIST(I57,0,1,0)*$H$3)/(2*SQRT($J$3))/365) *$P$3 | G57: =IF($O$3="buy",1,-1)*( IF($K$3="call",B57*NORMDIST(I57,0,1,1) - $B$3*NORMDIST(J57,0,1,1),$B$3*NORMDIST(-J57,0,1,1) - B57*NORMDIST(-I57,0,1,1) ) - $G$3) * $P$3 | I57: =(LN(B57/$B$3)+($H$3^2/2)*($J$3))/($H$3*SQRT($J$3)) | J57: =I57 - $H$3*SQRT($J$3)
B58: =B29 | C58: =IF($O$3="sell",-1,1) * IF($K$3="call", NORMDIST(I58,0,1,1), NORMDIST(I58,0,1,1)-1 ) * $P$3 | D58: =IF($O$3="sell",-1,1) * NORMDIST(I58,0,1,0)/(B58*$H$3*SQRT($J$3)) * $P$3 | E58: =IF($O$3="sell",-1,1) * (B58*NORMDIST(I58,0,1,0)*SQRT($J$3)/365) * $P$3 | F58: =IF($O$3="sell",-1,1) * (-(B58*NORMDIST(I58,0,1,0)*$H$3)/(2*SQRT($J$3))/365) *$P$3 | G58: =IF($O$3="buy",1,-1)*( IF($K$3="call",B58*NORMDIST(I58,0,1,1) - $B$3*NORMDIST(J58,0,1,1),$B$3*NORMDIST(-J58,0,1,1) - B58*NORMDIST(-I58,0,1,1) ) - $G$3) * $P$3 | I58: =(LN(B58/$B$3)+($H$3^2/2)*($J$3))/($H$3*SQRT($J$3)) | J58: =I58 - $H$3*SQRT($J$3)
B59: =B30 | C59: =IF($O$3="sell",-1,1) * IF($K$3="call", NORMDIST(I59,0,1,1), NORMDIST(I59,0,1,1)-1 ) * $P$3 | D59: =IF($O$3="sell",-1,1) * NORMDIST(I59,0,1,0)/(B59*$H$3*SQRT($J$3)) * $P$3 | E59: =IF($O$3="sell",-1,1) * (B59*NORMDIST(I59,0,1,0)*SQRT($J$3)/365) * $P$3 | F59: =IF($O$3="sell",-1,1) * (-(B59*NORMDIST(I59,0,1,0)*$H$3)/(2*SQRT($J$3))/365) *$P$3 | G59: =IF($O$3="buy",1,-1)*( IF($K$3="call",B59*NORMDIST(I59,0,1,1) - $B$3*NORMDIST(J59,0,1,1),$B$3*NORMDIST(-J59,0,1,1) - B59*NORMDIST(-I59,0,1,1) ) - $G$3) * $P$3 | I59: =(LN(B59/$B$3)+($H$3^2/2)*($J$3))/($H$3*SQRT($J$3)) | J59: =I59 - $H$3*SQRT($J$3)
B60: =B31 | C60: =IF($O$3="sell",-1,1) * IF($K$3="call", NORMDIST(I60,0,1,1), NORMDIST(I60,0,1,1)-1 ) * $P$3 | D60: =IF($O$3="sell",-1,1) * NORMDIST(I60,0,1,0)/(B60*$H$3*SQRT($J$3)) * $P$3 | E60: =IF($O$3="sell",-1,1) * (B60*NORMDIST(I60,0,1,0)*SQRT($J$3)/365) * $P$3 | F60: =IF($O$3="sell",-1,1) * (-(B60*NORMDIST(I60,0,1,0)*$H$3)/(2*SQRT($J$3))/365) *$P$3 | G60: =IF($O$3="buy",1,-1)*( IF($K$3="call",B60*NORMDIST(I60,0,1,1) - $B$3*NORMDIST(J60,0,1,1),$B$3*NORMDIST(-J60,0,1,1) - B60*NORMDIST(-I60,0,1,1) ) - $G$3) * $P$3 | I60: =(LN(B60/$B$3)+($H$3^2/2)*($J$3))/($H$3*SQRT($J$3)) | J60: =I60 - $H$3*SQRT($J$3)
B61: =B32 | C61: =IF($O$3="sell",-1,1) * IF($K$3="call", NORMDIST(I61,0,1,1), NORMDIST(I61,0,1,1)-1 ) * $P$3 | D61: =IF($O$3="sell",-1,1) * NORMDIST(I61,0,1,0)/(B61*$H$3*SQRT($J$3)) * $P$3 | E61: =IF($O$3="sell",-1,1) * (B61*NORMDIST(I61,0,1,0)*SQRT($J$3)/365) * $P$3 | F61: =IF($O$3="sell",-1,1) * (-(B61*NORMDIST(I61,0,1,0)*$H$3)/(2*SQRT($J$3))/365) *$P$3 | G61: =IF($O$3="buy",1,-1)*( IF($K$3="call",B61*NORMDIST(I61,0,1,1) - $B$3*NORMDIST(J61,0,1,1),$B$3*NORMDIST(-J61,0,1,1) - B61*NORMDIST(-I61,0,1,1) ) - $G$3) * $P$3 | I61: =(LN(B61/$B$3)+($H$3^2/2)*($J$3))/($H$3*SQRT($J$3)) | J61: =I61 - $H$3*SQRT($J$3)
... B76: =B47 | C76: =IF($O$3="sell",-1,1) * IF($K$3="call", NORMDIST(I76,0,1,1), NORMDIST(I76,0,1,1)-1 ) * $P$3 | D76: =IF($O$3="sell",-1,1) * NORMDIST(I76,0,1,0)/(B76*$H$3*SQRT($J$3)) * $P$3 | E76: =IF($O$3="sell",-1,1) * (B76*NORMDIST(I76,0,1,0)*SQRT($J$3)/365) * $P$3 | F76: =IF($O$3="sell",-1,1) * (-(B76*NORMDIST(I76,0,1,0)*$H$3)/(2*SQRT($J$3))/365) *$P$3 | G76: =IF($O$3="buy",1,-1)*( IF($K$3="call",B76*NORMDIST(I76,0,1,1) - $B$3*NORMDIST(J76,0,1,1),$B$3*NORMDIST(-J76,0,1,1) - B76*NORMDIST(-I76,0,1,1) ) - $G$3) * $P$3 | I76: =(LN(B76/$B$3)+($H$3^2/2)*($J$3))/($H$3*SQRT($J$3)) | J76: =I76 - $H$3*SQRT($J$3)
C78: delta | D78: gamma | E78: vega | F78: theta | G78: mark_price | I78: d1 | J78: d2
A79: =A4 | B79: =B50 | C79: =IF($O$4="sell",-1,1) * IF($K$4="call", NORMDIST(I79,0,1,1), NORMDIST(I79,0,1,1)-1 ) * $P$4 | D79: =IF($O$4="sell",-1,1) * NORMDIST(I79,0,1,0)/(B79*$H$4*SQRT($J$4)) * $P$4 | E79: =IF($O$4="sell",-1,1) * (B79*NORMDIST(I79,0,1,0)*SQRT($J$4)/365) * $P$4 | F79: =IF($O$4="sell",-1,1) * (-(B79*NORMDIST(I79,0,1,0)*$H$4)/(2*SQRT($J$4))/365) *$P$4 | G79: =IF($O$4="buy",1,-1)*( IF($K$4="call",B79*NORMDIST(I79,0,1,1) - $B$4*NORMDIST(J79,0,1,1),$B$4*NORMDIST(-J79,0,1,1) - B79*NORMDIST(-I79,0,1,1) ) - $G$4) * $P$4 | I79: =(LN(B79/$B$4)+($H$4^2/2)*($J$4))/($H$4*SQRT($J$4)) | J79: =I79 - $H$4*SQRT($J$4)
B80: =B51 | C80: =IF($O$4="sell",-1,1) * IF($K$4="call", NORMDIST(I80,0,1,1), NORMDIST(I80,0,1,1)-1 ) * $P$4 | D80: =IF($O$4="sell",-1,1) * NORMDIST(I80,0,1,0)/(B80*$H$4*SQRT($J$4)) * $P$4 | E80: =IF($O$4="sell",-1,1) * (B80*NORMDIST(I80,0,1,0)*SQRT($J$4)/365) * $P$4 | F80: =IF($O$4="sell",-1,1) * (-(B80*NORMDIST(I80,0,1,0)*$H$4)/(2*SQRT($J$4))/365) *$P$4 | G80: =IF($O$4="buy",1,-1)*( IF($K$4="call",B80*NORMDIST(I80,0,1,1) - $B$4*NORMDIST(J80,0,1,1),$B$4*NORMDIST(-J80,0,1,1) - B80*NORMDIST(-I80,0,1,1) ) - $G$4) * $P$4 | I80: =(LN(B80/$B$4)+($H$4^2/2)*($J$4))/($H$4*SQRT($J$4)) | J80: =I80 - $H$4*SQRT($J$4)
B81: =B52 | C81: =IF($O$4="sell",-1,1) * IF($K$4="call", NORMDIST(I81,0,1,1), NORMDIST(I81,0,1,1)-1 ) * $P$4 | D81: =IF($O$4="sell",-1,1) * NORMDIST(I81,0,1,0)/(B81*$H$4*SQRT($J$4)) * $P$4 | E81: =IF($O$4="sell",-1,1) * (B81*NORMDIST(I81,0,1,0)*SQRT($J$4)/365) * $P$4 | F81: =IF($O$4="sell",-1,1) * (-(B81*NORMDIST(I81,0,1,0)*$H$4)/(2*SQRT($J$4))/365) *$P$4 | G81: =IF($O$4="buy",1,-1)*( IF($K$4="call",B81*NORMDIST(I81,0,1,1) - $B$4*NORMDIST(J81,0,1,1),$B$4*NORMDIST(-J81,0,1,1) - B81*NORMDIST(-I81,0,1,1) ) - $G$4) * $P$4 | I81: =(LN(B81/$B$4)+($H$4^2/2)*($J$4))/($H$4*SQRT($J$4)) | J81: =I81 - $H$4*SQRT($J$4)
B82: =B53 | C82: =IF($O$4="sell",-1,1) * IF($K$4="call", NORMDIST(I82,0,1,1), NORMDIST(I82,0,1,1)-1 ) * $P$4 | D82: =IF($O$4="sell",-1,1) * NORMDIST(I82,0,1,0)/(B82*$H$4*SQRT($J$4)) * $P$4 | E82: =IF($O$4="sell",-1,1) * (B82*NORMDIST(I82,0,1,0)*SQRT($J$4)/365) * $P$4 | F82: =IF($O$4="sell",-1,1) * (-(B82*NORMDIST(I82,0,1,0)*$H$4)/(2*SQRT($J$4))/365) *$P$4 | G82: =IF($O$4="buy",1,-1)*( IF($K$4="call",B82*NORMDIST(I82,0,1,1) - $B$4*NORMDIST(J82,0,1,1),$B$4*NORMDIST(-J82,0,1,1) - B82*NORMDIST(-I82,0,1,1) ) - $G$4) * $P$4 | I82: =(LN(B82/$B$4)+($H$4^2/2)*($J$4))/($H$4*SQRT($J$4)) | J82: =I82 - $H$4*SQRT($J$4)
B83: =B54 | C83: =IF($O$4="sell",-1,1) * IF($K$4="call", NORMDIST(I83,0,1,1), NORMDIST(I83,0,1,1)-1 ) * $P$4 | D83: =IF($O$4="sell",-1,1) * NORMDIST(I83,0,1,0)/(B83*$H$4*SQRT($J$4)) * $P$4 | E83: =IF($O$4="sell",-1,1) * (B83*NORMDIST(I83,0,1,0)*SQRT($J$4)/365) * $P$4 | F83: =IF($O$4="sell",-1,1) * (-(B83*NORMDIST(I83,0,1,0)*$H$4)/(2*SQRT($J$4))/365) *$P$4 | G83: =IF($O$4="buy",1,-1)*( IF($K$4="call",B83*NORMDIST(I83,0,1,1) - $B$4*NORMDIST(J83,0,1,1),$B$4*NORMDIST(-J83,0,1,1) - B83*NORMDIST(-I83,0,1,1) ) - $G$4) * $P$4 | I83: =(LN(B83/$B$4)+($H$4^2/2)*($J$4))/($H$4*SQRT($J$4)) | J83: =I83 - $H$4*SQRT($J$4)
B84: =B55 | C84: =IF($O$4="sell",-1,1) * IF($K$4="call", NORMDIST(I84,0,1,1), NORMDIST(I84,0,1,1)-1 ) * $P$4 | D84: =IF($O$4="sell",-1,1) * NORMDIST(I84,0,1,0)/(B84*$H$4*SQRT($J$4)) * $P$4 | E84: =IF($O$4="sell",-1,1) * (B84*NORMDIST(I84,0,1,0)*SQRT($J$4)/365) * $P$4 | F84: =IF($O$4="sell",-1,1) * (-(B84*NORMDIST(I84,0,1,0)*$H$4)/(2*SQRT($J$4))/365) *$P$4 | G84: =IF($O$4="buy",1,-1)*( IF($K$4="call",B84*NORMDIST(I84,0,1,1) - $B$4*NORMDIST(J84,0,1,1),$B$4*NORMDIST(-J84,0,1,1) - B84*NORMDIST(-I84,0,1,1) ) - $G$4) * $P$4 | I84: =(LN(B84/$B$4)+($H$4^2/2)*($J$4))/($H$4*SQRT($J$4)) | J84: =I84 - $H$4*SQRT($J$4)
B85: =B56 | C85: =IF($O$4="sell",-1,1) * IF($K$4="call", NORMDIST(I85,0,1,1), NORMDIST(I85,0,1,1)-1 ) * $P$4 | D85: =IF($O$4="sell",-1,1) * NORMDIST(I85,0,1,0)/(B85*$H$4*SQRT($J$4)) * $P$4 | E85: =IF($O$4="sell",-1,1) * (B85*NORMDIST(I85,0,1,0)*SQRT($J$4)/365) * $P$4 | F85: =IF($O$4="sell",-1,1) * (-(B85*NORMDIST(I85,0,1,0)*$H$4)/(2*SQRT($J$4))/365) *$P$4 | G85: =IF($O$4="buy",1,-1)*( IF($K$4="call",B85*NORMDIST(I85,0,1,1) - $B$4*NORMDIST(J85,0,1,1),$B$4*NORMDIST(-J85,0,1,1) - B85*NORMDIST(-I85,0,1,1) ) - $G$4) * $P$4 | I85: =(LN(B85/$B$4)+($H$4^2/2)*($J$4))/($H$4*SQRT($J$4)) | J85: =I85 - $H$4*SQRT($J$4)
B86: =B57 | C86: =IF($O$4="sell",-1,1) * IF($K$4="call", NORMDIST(I86,0,1,1), NORMDIST(I86,0,1,1)-1 ) * $P$4 | D86: =IF($O$4="sell",-1,1) * NORMDIST(I86,0,1,0)/(B86*$H$4*SQRT($J$4)) * $P$4 | E86: =IF($O$4="sell",-1,1) * (B86*NORMDIST(I86,0,1,0)*SQRT($J$4)/365) * $P$4 | F86: =IF($O$4="sell",-1,1) * (-(B86*NORMDIST(I86,0,1,0)*$H$4)/(2*SQRT($J$4))/365) *$P$4 | G86: =IF($O$4="buy",1,-1)*( IF($K$4="call",B86*NORMDIST(I86,0,1,1) - $B$4*NORMDIST(J86,0,1,1),$B$4*NORMDIST(-J86,0,1,1) - B86*NORMDIST(-I86,0,1,1) ) - $G$4) * $P$4 | I86: =(LN(B86/$B$4)+($H$4^2/2)*($J$4))/($H$4*SQRT($J$4)) | J86: =I86 - $H$4*SQRT($J$4)
B87: =B58 | C87: =IF($O$4="sell",-1,1) * IF($K$4="call", NORMDIST(I87,0,1,1), NORMDIST(I87,0,1,1)-1 ) * $P$4 | D87: =IF($O$4="sell",-1,1) * NORMDIST(I87,0,1,0)/(B87*$H$4*SQRT($J$4)) * $P$4 | E87: =IF($O$4="sell",-1,1) * (B87*NORMDIST(I87,0,1,0)*SQRT($J$4)/365) * $P$4 | F87: =IF($O$4="sell",-1,1) * (-(B87*NORMDIST(I87,0,1,0)*$H$4)/(2*SQRT($J$4))/365) *$P$4 | G87: =IF($O$4="buy",1,-1)*( IF($K$4="call",B87*NORMDIST(I87,0,1,1) - $B$4*NORMDIST(J87,0,1,1),$B$4*NORMDIST(-J87,0,1,1) - B87*NORMDIST(-I87,0,1,1) ) - $G$4) * $P$4 | I87: =(LN(B87/$B$4)+($H$4^2/2)*($J$4))/($H$4*SQRT($J$4)) | J87: =I87 - $H$4*SQRT($J$4)
B88: =B59 | C88: =IF($O$4="sell",-1,1) * IF($K$4="call", NORMDIST(I88,0,1,1), NORMDIST(I88,0,1,1)-1 ) * $P$4 | D88: =IF($O$4="sell",-1,1) * NORMDIST(I88,0,1,0)/(B88*$H$4*SQRT($J$4)) * $P$4 | E88: =IF($O$4="sell",-1,1) * (B88*NORMDIST(I88,0,1,0)*SQRT($J$4)/365) * $P$4 | F88: =IF($O$4="sell",-1,1) * (-(B88*NORMDIST(I88,0,1,0)*$H$4)/(2*SQRT($J$4))/365) *$P$4 | G88: =IF($O$4="buy",1,-1)*( IF($K$4="call",B88*NORMDIST(I88,0,1,1) - $B$4*NORMDIST(J88,0,1,1),$B$4*NORMDIST(-J88,0,1,1) - B88*NORMDIST(-I88,0,1,1) ) - $G$4) * $P$4 | I88: =(LN(B88/$B$4)+($H$4^2/2)*($J$4))/($H$4*SQRT($J$4)) | J88: =I88 - $H$4*SQRT($J$4)
B89: =B60 | C89: =IF($O$4="sell",-1,1) * IF($K$4="call", NORMDIST(I89,0,1,1), NORMDIST(I89,0,1,1)-1 ) * $P$4 | D89: =IF($O$4="sell",-1,1) * NORMDIST(I89,0,1,0)/(B89*$H$4*SQRT($J$4)) * $P$4 | E89: =IF($O$4="sell",-1,1) * (B89*NORMDIST(I89,0,1,0)*SQRT($J$4)/365) * $P$4 | F89: =IF($O$4="sell",-1,1) * (-(B89*NORMDIST(I89,0,1,0)*$H$4)/(2*SQRT($J$4))/365) *$P$4 | G89: =IF($O$4="buy",1,-1)*( IF($K$4="call",B89*NORMDIST(I89,0,1,1) - $B$4*NORMDIST(J89,0,1,1),$B$4*NORMDIST(-J89,0,1,1) - B89*NORMDIST(-I89,0,1,1) ) - $G$4) * $P$4 | I89: =(LN(B89/$B$4)+($H$4^2/2)*($J$4))/($H$4*SQRT($J$4)) | J89: =I89 - $H$4*SQRT($J$4)
B90: =B61 | C90: =IF($O$4="sell",-1,1) * IF($K$4="call", NORMDIST(I90,0,1,1), NORMDIST(I90,0,1,1)-1 ) * $P$4 | D90: =IF($O$4="sell",-1,1) * NORMDIST(I90,0,1,0)/(B90*$H$4*SQRT($J$4)) * $P$4 | E90: =IF($O$4="sell",-1,1) * (B90*NORMDIST(I90,0,1,0)*SQRT($J$4)/365) * $P$4 | F90: =IF($O$4="sell",-1,1) * (-(B90*NORMDIST(I90,0,1,0)*$H$4)/(2*SQRT($J$4))/365) *$P$4 | G90: =IF($O$4="buy",1,-1)*( IF($K$4="call",B90*NORMDIST(I90,0,1,1) - $B$4*NORMDIST(J90,0,1,1),$B$4*NORMDIST(-J90,0,1,1) - B90*NORMDIST(-I90,0,1,1) ) - $G$4) * $P$4 | I90: =(LN(B90/$B$4)+($H$4^2/2)*($J$4))/($H$4*SQRT($J$4)) | J90: =I90 - $H$4*SQRT($J$4)
B91: =B62 | C91: =IF($O$4="sell",-1,1) * IF($K$4="call", NORMDIST(I91,0,1,1), NORMDIST(I91,0,1,1)-1 ) * $P$4 | D91: =IF($O$4="sell",-1,1) * NORMDIST(I91,0,1,0)/(B91*$H$4*SQRT($J$4)) * $P$4 | E91: =IF($O$4="sell",-1,1) * (B91*NORMDIST(I91,0,1,0)*SQRT($J$4)/365) * $P$4 | F91: =IF($O$4="sell",-1,1) * (-(B91*NORMDIST(I91,0,1,0)*$H$4)/(2*SQRT($J$4))/365) *$P$4 | G91: =IF($O$4="buy",1,-1)*( IF($K$4="call",B91*NORMDIST(I91,0,1,1) - $B$4*NORMDIST(J91,0,1,1),$B$4*NORMDIST(-J91,0,1,1) - B91*NORMDIST(-I91,0,1,1) ) - $G$4) * $P$4 | I91: =(LN(B91/$B$4)+($H$4^2/2)*($J$4))/($H$4*SQRT($J$4)) | J91: =I91 - $H$4*SQRT($J$4)
... B105: =B76 | C105: =IF($O$4="sell",-1,1) * IF($K$4="call", NORMDIST(I105,0,1,1), NORMDIST(I105,0,1,1)-1 ) * $P$4 | D105: =IF($O$4="sell",-1,1) * NORMDIST(I105,0,1,0)/(B105*$H$4*SQRT($J$4)) * $P$4 | E105: =IF($O$4="sell",-1,1) * (B105*NORMDIST(I105,0,1,0)*SQRT($J$4)/365) * $P$4 | F105: =IF($O$4="sell",-1,1) * (-(B105*NORMDIST(I105,0,1,0)*$H$4)/(2*SQRT($J$4))/365) *$P$4 | G105: =IF($O$4="buy",1,-1)*( IF($K$4="call",B105*NORMDIST(I105,0,1,1) - $B$4*NORMDIST(J105,0,1,1),$B$4*NORMDIST(-J105,0,1,1) - B105*NORMDIST(-I105,0,1,1) ) - $G$4) * $P$4 | I105: =(LN(B105/$B$4)+($H$4^2/2)*($J$4))/($H$4*SQRT($J$4)) | J105: =I105 - $H$4*SQRT($J$4)
C107: delta | D107: gamma | E107: vega | F107: theta | G107: mark_price | I107: d1 | J107: d2
A108: =A5 | B108: =B79 | C108: =IF($O$5="sell",-1,1) * IF($K$5="call", NORMDIST(I108,0,1,1), NORMDIST(I108,0,1,1)-1 ) * $P$5 | D108: =IF($O$5="sell",-1,1) * NORMDIST(I108,0,1,0)/(B108*$H$5*SQRT($J$5)) * $P$5 | E108: =IF($O$5="sell",-1,1) * (B108*NORMDIST(I108,0,1,0)*SQRT($J$5)/365) * $P$5 | F108: =IF($O$5="sell",-1,1) * (-(B108*NORMDIST(I108,0,1,0)*$H$5)/(2*SQRT($J$5))/365) *$P$5 | G108: =IF($O$5="buy",1,-1)*( IF($K$5="call",B108*NORMDIST(I108,0,1,1) - $B$5*NORMDIST(J108,0,1,1),$B$5*NORMDIST(-J108,0,1,1) - B108*NORMDIST(-I108,0,1,1) ) - $G$5) * $P$5 | I108: =(LN(B108/$B$5)+($H$5^2/2)*($J$5))/($H$5*SQRT($J$5)) | J108: =I108 - $H$5*SQRT($J$5)
B109: =B80 | C109: =IF($O$5="sell",-1,1) * IF($K$5="call", NORMDIST(I109,0,1,1), NORMDIST(I109,0,1,1)-1 ) * $P$5 | D109: =IF($O$5="sell",-1,1) * NORMDIST(I109,0,1,0)/(B109*$H$5*SQRT($J$5)) * $P$5 | E109: =IF($O$5="sell",-1,1) * (B109*NORMDIST(I109,0,1,0)*SQRT($J$5)/365) * $P$5 | F109: =IF($O$5="sell",-1,1) * (-(B109*NORMDIST(I109,0,1,0)*$H$5)/(2*SQRT($J$5))/365) *$P$5 | G109: =IF($O$5="buy",1,-1)*( IF($K$5="call",B109*NORMDIST(I109,0,1,1) - $B$5*NORMDIST(J109,0,1,1),$B$5*NORMDIST(-J109,0,1,1) - B109*NORMDIST(-I109,0,1,1) ) - $G$5) * $P$5 | I109: =(LN(B109/$B$5)+($H$5^2/2)*($J$5))/($H$5*SQRT($J$5)) | J109: =I109 - $H$5*SQRT($J$5)
B110: =B81 | C110: =IF($O$5="sell",-1,1) * IF($K$5="call", NORMDIST(I110,0,1,1), NORMDIST(I110,0,1,1)-1 ) * $P$5 | D110: =IF($O$5="sell",-1,1) * NORMDIST(I110,0,1,0)/(B110*$H$5*SQRT($J$5)) * $P$5 | E110: =IF($O$5="sell",-1,1) * (B110*NORMDIST(I110,0,1,0)*SQRT($J$5)/365) * $P$5 | F110: =IF($O$5="sell",-1,1) * (-(B110*NORMDIST(I110,0,1,0)*$H$5)/(2*SQRT($J$5))/365) *$P$5 | G110: =IF($O$5="buy",1,-1)*( IF($K$5="call",B110*NORMDIST(I110,0,1,1) - $B$5*NORMDIST(J110,0,1,1),$B$5*NORMDIST(-J110,0,1,1) - B110*NORMDIST(-I110,0,1,1) ) - $G$5) * $P$5 | I110: =(LN(B110/$B$5)+($H$5^2/2)*($J$5))/($H$5*SQRT($J$5)) | J110: =I110 - $H$5*SQRT($J$5)
B111: =B82 | C111: =IF($O$5="sell",-1,1) * IF($K$5="call", NORMDIST(I111,0,1,1), NORMDIST(I111,0,1,1)-1 ) * $P$5 | D111: =IF($O$5="sell",-1,1) * NORMDIST(I111,0,1,0)/(B111*$H$5*SQRT($J$5)) * $P$5 | E111: =IF($O$5="sell",-1,1) * (B111*NORMDIST(I111,0,1,0)*SQRT($J$5)/365) * $P$5 | F111: =IF($O$5="sell",-1,1) * (-(B111*NORMDIST(I111,0,1,0)*$H$5)/(2*SQRT($J$5))/365) *$P$5 | G111: =IF($O$5="buy",1,-1)*( IF($K$5="call",B111*NORMDIST(I111,0,1,1) - $B$5*NORMDIST(J111,0,1,1),$B$5*NORMDIST(-J111,0,1,1) - B111*NORMDIST(-I111,0,1,1) ) - $G$5) * $P$5 | I111: =(LN(B111/$B$5)+($H$5^2/2)*($J$5))/($H$5*SQRT($J$5)) | J111: =I111 - $H$5*SQRT($J$5)
B112: =B83 | C112: =IF($O$5="sell",-1,1) * IF($K$5="call", NORMDIST(I112,0,1,1), NORMDIST(I112,0,1,1)-1 ) * $P$5 | D112: =IF($O$5="sell",-1,1) * NORMDIST(I112,0,1,0)/(B112*$H$5*SQRT($J$5)) * $P$5 | E112: =IF($O$5="sell",-1,1) * (B112*NORMDIST(I112,0,1,0)*SQRT($J$5)/365) * $P$5 | F112: =IF($O$5="sell",-1,1) * (-(B112*NORMDIST(I112,0,1,0)*$H$5)/(2*SQRT($J$5))/365) *$P$5 | G112: =IF($O$5="buy",1,-1)*( IF($K$5="call",B112*NORMDIST(I112,0,1,1) - $B$5*NORMDIST(J112,0,1,1),$B$5*NORMDIST(-J112,0,1,1) - B112*NORMDIST(-I112,0,1,1) ) - $G$5) * $P$5 | I112: =(LN(B112/$B$5)+($H$5^2/2)*($J$5))/($H$5*SQRT($J$5)) | J112: =I112 - $H$5*SQRT($J$5)
B113: =B84 | C113: =IF($O$5="sell",-1,1) * IF($K$5="call", NORMDIST(I113,0,1,1), NORMDIST(I113,0,1,1)-1 ) * $P$5 | D113: =IF($O$5="sell",-1,1) * NORMDIST(I113,0,1,0)/(B113*$H$5*SQRT($J$5)) * $P$5 | E113: =IF($O$5="sell",-1,1) * (B113*NORMDIST(I113,0,1,0)*SQRT($J$5)/365) * $P$5 | F113: =IF($O$5="sell",-1,1) * (-(B113*NORMDIST(I113,0,1,0)*$H$5)/(2*SQRT($J$5))/365) *$P$5 | G113: =IF($O$5="buy",1,-1)*( IF($K$5="call",B113*NORMDIST(I113,0,1,1) - $B$5*NORMDIST(J113,0,1,1),$B$5*NORMDIST(-J113,0,1,1) - B113*NORMDIST(-I113,0,1,1) ) - $G$5) * $P$5 | I113: =(LN(B113/$B$5)+($H$5^2/2)*($J$5))/($H$5*SQRT($J$5)) | J113: =I113 - $H$5*SQRT($J$5)
B114: =B85 | C114: =IF($O$5="sell",-1,1) * IF($K$5="call", NORMDIST(I114,0,1,1), NORMDIST(I114,0,1,1)-1 ) * $P$5 | D114: =IF($O$5="sell",-1,1) * NORMDIST(I114,0,1,0)/(B114*$H$5*SQRT($J$5)) * $P$5 | E114: =IF($O$5="sell",-1,1) * (B114*NORMDIST(I114,0,1,0)*SQRT($J$5)/365) * $P$5 | F114: =IF($O$5="sell",-1,1) * (-(B114*NORMDIST(I114,0,1,0)*$H$5)/(2*SQRT($J$5))/365) *$P$5 | G114: =IF($O$5="buy",1,-1)*( IF($K$5="call",B114*NORMDIST(I114,0,1,1) - $B$5*NORMDIST(J114,0,1,1),$B$5*NORMDIST(-J114,0,1,1) - B114*NORMDIST(-I114,0,1,1) ) - $G$5) * $P$5 | I114: =(LN(B114/$B$5)+($H$5^2/2)*($J$5))/($H$5*SQRT($J$5)) | J114: =I114 - $H$5*SQRT($J$5)
B115: =B86 | C115: =IF($O$5="sell",-1,1) * IF($K$5="call", NORMDIST(I115,0,1,1), NORMDIST(I115,0,1,1)-1 ) * $P$5 | D115: =IF($O$5="sell",-1,1) * NORMDIST(I115,0,1,0)/(B115*$H$5*SQRT($J$5)) * $P$5 | E115: =IF($O$5="sell",-1,1) * (B115*NORMDIST(I115,0,1,0)*SQRT($J$5)/365) * $P$5 | F115: =IF($O$5="sell",-1,1) * (-(B115*NORMDIST(I115,0,1,0)*$H$5)/(2*SQRT($J$5))/365) *$P$5 | G115: =IF($O$5="buy",1,-1)*( IF($K$5="call",B115*NORMDIST(I115,0,1,1) - $B$5*NORMDIST(J115,0,1,1),$B$5*NORMDIST(-J115,0,1,1) - B115*NORMDIST(-I115,0,1,1) ) - $G$5) * $P$5 | I115: =(LN(B115/$B$5)+($H$5^2/2)*($J$5))/($H$5*SQRT($J$5)) | J115: =I115 - $H$5*SQRT($J$5)
B116: =B87 | C116: =IF($O$5="sell",-1,1) * IF($K$5="call", NORMDIST(I116,0,1,1), NORMDIST(I116,0,1,1)-1 ) * $P$5 | D116: =IF($O$5="sell",-1,1) * NORMDIST(I116,0,1,0)/(B116*$H$5*SQRT($J$5)) * $P$5 | E116: =IF($O$5="sell",-1,1) * (B116*NORMDIST(I116,0,1,0)*SQRT($J$5)/365) * $P$5 | F116: =IF($O$5="sell",-1,1) * (-(B116*NORMDIST(I116,0,1,0)*$H$5)/(2*SQRT($J$5))/365) *$P$5 | G116: =IF($O$5="buy",1,-1)*( IF($K$5="call",B116*NORMDIST(I116,0,1,1) - $B$5*NORMDIST(J116,0,1,1),$B$5*NORMDIST(-J116,0,1,1) - B116*NORMDIST(-I116,0,1,1) ) - $G$5) * $P$5 | I116: =(LN(B116/$B$5)+($H$5^2/2)*($J$5))/($H$5*SQRT($J$5)) | J116: =I116 - $H$5*SQRT($J$5)
B117: =B88 | C117: =IF($O$5="sell",-1,1) * IF($K$5="call", NORMDIST(I117,0,1,1), NORMDIST(I117,0,1,1)-1 ) * $P$5 | D117: =IF($O$5="sell",-1,1) * NORMDIST(I117,0,1,0)/(B117*$H$5*SQRT($J$5)) * $P$5 | E117: =IF($O$5="sell",-1,1) * (B117*NORMDIST(I117,0,1,0)*SQRT($J$5)/365) * $P$5 | F117: =IF($O$5="sell",-1,1) * (-(B117*NORMDIST(I117,0,1,0)*$H$5)/(2*SQRT($J$5))/365) *$P$5 | G117: =IF($O$5="buy",1,-1)*( IF($K$5="call",B117*NORMDIST(I117,0,1,1) - $B$5*NORMDIST(J117,0,1,1),$B$5*NORMDIST(-J117,0,1,1) - B117*NORMDIST(-I117,0,1,1) ) - $G$5) * $P$5 | I117: =(LN(B117/$B$5)+($H$5^2/2)*($J$5))/($H$5*SQRT($J$5)) | J117: =I117 - $H$5*SQRT($J$5)
B118: =B89 | C118: =IF($O$5="sell",-1,1) * IF($K$5="call", NORMDIST(I118,0,1,1), NORMDIST(I118,0,1,1)-1 ) * $P$5 | D118: =IF($O$5="sell",-1,1) * NORMDIST(I118,0,1,0)/(B118*$H$5*SQRT($J$5)) * $P$5 | E118: =IF($O$5="sell",-1,1) * (B118*NORMDIST(I118,0,1,0)*SQRT($J$5)/365) * $P$5 | F118: =IF($O$5="sell",-1,1) * (-(B118*NORMDIST(I118,0,1,0)*$H$5)/(2*SQRT($J$5))/365) *$P$5 | G118: =IF($O$5="buy",1,-1)*( IF($K$5="call",B118*NORMDIST(I118,0,1,1) - $B$5*NORMDIST(J118,0,1,1),$B$5*NORMDIST(-J118,0,1,1) - B118*NORMDIST(-I118,0,1,1) ) - $G$5) * $P$5 | I118: =(LN(B118/$B$5)+($H$5^2/2)*($J$5))/($H$5*SQRT($J$5)) | J118: =I118 - $H$5*SQRT($J$5)
B119: =B90 | C119: =IF($O$5="sell",-1,1) * IF($K$5="call", NORMDIST(I119,0,1,1), NORMDIST(I119,0,1,1)-1 ) * $P$5 | D119: =IF($O$5="sell",-1,1) * NORMDIST(I119,0,1,0)/(B119*$H$5*SQRT($J$5)) * $P$5 | E119: =IF($O$5="sell",-1,1) * (B119*NORMDIST(I119,0,1,0)*SQRT($J$5)/365) * $P$5 | F119: =IF($O$5="sell",-1,1) * (-(B119*NORMDIST(I119,0,1,0)*$H$5)/(2*SQRT($J$5))/365) *$P$5 | G119: =IF($O$5="buy",1,-1)*( IF($K$5="call",B119*NORMDIST(I119,0,1,1) - $B$5*NORMDIST(J119,0,1,1),$B$5*NORMDIST(-J119,0,1,1) - B119*NORMDIST(-I119,0,1,1) ) - $G$5) * $P$5 | I119: =(LN(B119/$B$5)+($H$5^2/2)*($J$5))/($H$5*SQRT($J$5)) | J119: =I119 - $H$5*SQRT($J$5)
B120: =B91 | C120: =IF($O$5="sell",-1,1) * IF($K$5="call", NORMDIST(I120,0,1,1), NORMDIST(I120,0,1,1)-1 ) * $P$5 | D120: =IF($O$5="sell",-1,1) * NORMDIST(I120,0,1,0)/(B120*$H$5*SQRT($J$5)) * $P$5 | E120: =IF($O$5="sell",-1,1) * (B120*NORMDIST(I120,0,1,0)*SQRT($J$5)/365) * $P$5 | F120: =IF($O$5="sell",-1,1) * (-(B120*NORMDIST(I120,0,1,0)*$H$5)/(2*SQRT($J$5))/365) *$P$5 | G120: =IF($O$5="buy",1,-1)*( IF($K$5="call",B120*NORMDIST(I120,0,1,1) - $B$5*NORMDIST(J120,0,1,1),$B$5*NORMDIST(-J120,0,1,1) - B120*NORMDIST(-I120,0,1,1) ) - $G$5) * $P$5 | I120: =(LN(B120/$B$5)+($H$5^2/2)*($J$5))/($H$5*SQRT($J$5)) | J120: =I120 - $H$5*SQRT($J$5)
... B134: =B105 | C134: =IF($O$5="sell",-1,1) * IF($K$5="call", NORMDIST(I134,0,1,1), NORMDIST(I134,0,1,1)-1 ) * $P$5 | D134: =IF($O$5="sell",-1,1) * NORMDIST(I134,0,1,0)/(B134*$H$5*SQRT($J$5)) * $P$5 | E134: =IF($O$5="sell",-1,1) * (B134*NORMDIST(I134,0,1,0)*SQRT($J$5)/365) * $P$5 | F134: =IF($O$5="sell",-1,1) * (-(B134*NORMDIST(I134,0,1,0)*$H$5)/(2*SQRT($J$5))/365) *$P$5 | G134: =IF($O$5="buy",1,-1)*( IF($K$5="call",B134*NORMDIST(I134,0,1,1) - $B$5*NORMDIST(J134,0,1,1),$B$5*NORMDIST(-J134,0,1,1) - B134*NORMDIST(-I134,0,1,1) ) - $G$5) * $P$5 | I134: =(LN(B134/$B$5)+($H$5^2/2)*($J$5))/($H$5*SQRT($J$5)) | J134: =I134 - $H$5*SQRT($J$5)
C137: delta | D137: gamma | E137: vega | F137: theta | G137: mark_price | I137: d1 | J137: d2
A138: =A6 | B138: =B108 | C138: =IF($O$6="sell",-1,1) * IF($K$6="call", NORMDIST(I138,0,1,1), NORMDIST(I138,0,1,1)-1 ) * $P$6 | D138: =IF($O$6="sell",-1,1) * NORMDIST(I138,0,1,0)/(B138*$H$6*SQRT($J$6)) * $P$6 | E138: =IF($O$6="sell",-1,1) * (B138*NORMDIST(I138,0,1,0)*SQRT($J$6)/365) * $P$6 | F138: =IF($O$6="sell",-1,1) * (-(B138*NORMDIST(I138,0,1,0)*$H$6)/(2*SQRT($J$6))/365) *$P$6 | G138: =IF($O$6="buy",1,-1)*( IF($K$6="call",B138*NORMDIST(I138,0,1,1) - $B$6*NORMDIST(J138,0,1,1),$B$6*NORMDIST(-J138,0,1,1) - B138*NORMDIST(-I138,0,1,1) ) - $G$6) * $P$6 | I138: =(LN(B138/$B$6)+($H$6^2/2)*($J$6))/($H$6*SQRT($J$6)) | J138: =I138 - $H$6*SQRT($J$6)
B139: =B109 | C139: =IF($O$6="sell",-1,1) * IF($K$6="call", NORMDIST(I139,0,1,1), NORMDIST(I139,0,1,1)-1 ) * $P$6 | D139: =IF($O$6="sell",-1,1) * NORMDIST(I139,0,1,0)/(B139*$H$6*SQRT($J$6)) * $P$6 | E139: =IF($O$6="sell",-1,1) * (B139*NORMDIST(I139,0,1,0)*SQRT($J$6)/365) * $P$6 | F139: =IF($O$6="sell",-1,1) * (-(B139*NORMDIST(I139,0,1,0)*$H$6)/(2*SQRT($J$6))/365) *$P$6 | G139: =IF($O$6="buy",1,-1)*( IF($K$6="call",B139*NORMDIST(I139,0,1,1) - $B$6*NORMDIST(J139,0,1,1),$B$6*NORMDIST(-J139,0,1,1) - B139*NORMDIST(-I139,0,1,1) ) - $G$6) * $P$6 | I139: =(LN(B139/$B$6)+($H$6^2/2)*($J$6))/($H$6*SQRT($J$6)) | J139: =I139 - $H$6*SQRT($J$6)
B140: =B110 | C140: =IF($O$6="sell",-1,1) * IF($K$6="call", NORMDIST(I140,0,1,1), NORMDIST(I140,0,1,1)-1 ) * $P$6 | D140: =IF($O$6="sell",-1,1) * NORMDIST(I140,0,1,0)/(B140*$H$6*SQRT($J$6)) * $P$6 | E140: =IF($O$6="sell",-1,1) * (B140*NORMDIST(I140,0,1,0)*SQRT($J$6)/365) * $P$6 | F140: =IF($O$6="sell",-1,1) * (-(B140*NORMDIST(I140,0,1,0)*$H$6)/(2*SQRT($J$6))/365) *$P$6 | G140: =IF($O$6="buy",1,-1)*( IF($K$6="call",B140*NORMDIST(I140,0,1,1) - $B$6*NORMDIST(J140,0,1,1),$B$6*NORMDIST(-J140,0,1,1) - B140*NORMDIST(-I140,0,1,1) ) - $G$6) * $P$6 | I140: =(LN(B140/$B$6)+($H$6^2/2)*($J$6))/($H$6*SQRT($J$6)) | J140: =I140 - $H$6*SQRT($J$6)
B141: =B111 | C141: =IF($O$6="sell",-1,1) * IF($K$6="call", NORMDIST(I141,0,1,1), NORMDIST(I141,0,1,1)-1 ) * $P$6 | D141: =IF($O$6="sell",-1,1) * NORMDIST(I141,0,1,0)/(B141*$H$6*SQRT($J$6)) * $P$6 | E141: =IF($O$6="sell",-1,1) * (B141*NORMDIST(I141,0,1,0)*SQRT($J$6)/365) * $P$6 | F141: =IF($O$6="sell",-1,1) * (-(B141*NORMDIST(I141,0,1,0)*$H$6)/(2*SQRT($J$6))/365) *$P$6 | G141: =IF($O$6="buy",1,-1)*( IF($K$6="call",B141*NORMDIST(I141,0,1,1) - $B$6*NORMDIST(J141,0,1,1),$B$6*NORMDIST(-J141,0,1,1) - B141*NORMDIST(-I141,0,1,1) ) - $G$6) * $P$6 | I141: =(LN(B141/$B$6)+($H$6^2/2)*($J$6))/($H$6*SQRT($J$6)) | J141: =I141 - $H$6*SQRT($J$6)
B142: =B112 | C142: =IF($O$6="sell",-1,1) * IF($K$6="call", NORMDIST(I142,0,1,1), NORMDIST(I142,0,1,1)-1 ) * $P$6 | D142: =IF($O$6="sell",-1,1) * NORMDIST(I142,0,1,0)/(B142*$H$6*SQRT($J$6)) * $P$6 | E142: =IF($O$6="sell",-1,1) * (B142*NORMDIST(I142,0,1,0)*SQRT($J$6)/365) * $P$6 | F142: =IF($O$6="sell",-1,1) * (-(B142*NORMDIST(I142,0,1,0)*$H$6)/(2*SQRT($J$6))/365) *$P$6 | G142: =IF($O$6="buy",1,-1)*( IF($K$6="call",B142*NORMDIST(I142,0,1,1) - $B$6*NORMDIST(J142,0,1,1),$B$6*NORMDIST(-J142,0,1,1) - B142*NORMDIST(-I142,0,1,1) ) - $G$6) * $P$6 | I142: =(LN(B142/$B$6)+($H$6^2/2)*($J$6))/($H$6*SQRT($J$6)) | J142: =I142 - $H$6*SQRT($J$6)
B143: =B113 | C143: =IF($O$6="sell",-1,1) * IF($K$6="call", NORMDIST(I143,0,1,1), NORMDIST(I143,0,1,1)-1 ) * $P$6 | D143: =IF($O$6="sell",-1,1) * NORMDIST(I143,0,1,0)/(B143*$H$6*SQRT($J$6)) * $P$6 | E143: =IF($O$6="sell",-1,1) * (B143*NORMDIST(I143,0,1,0)*SQRT($J$6)/365) * $P$6 | F143: =IF($O$6="sell",-1,1) * (-(B143*NORMDIST(I143,0,1,0)*$H$6)/(2*SQRT($J$6))/365) *$P$6 | G143: =IF($O$6="buy",1,-1)*( IF($K$6="call",B143*NORMDIST(I143,0,1,1) - $B$6*NORMDIST(J143,0,1,1),$B$6*NORMDIST(-J143,0,1,1) - B143*NORMDIST(-I143,0,1,1) ) - $G$6) * $P$6 | I143: =(LN(B143/$B$6)+($H$6^2/2)*($J$6))/($H$6*SQRT($J$6)) | J143: =I143 - $H$6*SQRT($J$6)
B144: =B114 | C144: =IF($O$6="sell",-1,1) * IF($K$6="call", NORMDIST(I144,0,1,1), NORMDIST(I144,0,1,1)-1 ) * $P$6 | D144: =IF($O$6="sell",-1,1) * NORMDIST(I144,0,1,0)/(B144*$H$6*SQRT($J$6)) * $P$6 | E144: =IF($O$6="sell",-1,1) * (B144*NORMDIST(I144,0,1,0)*SQRT($J$6)/365) * $P$6 | F144: =IF($O$6="sell",-1,1) * (-(B144*NORMDIST(I144,0,1,0)*$H$6)/(2*SQRT($J$6))/365) *$P$6 | G144: =IF($O$6="buy",1,-1)*( IF($K$6="call",B144*NORMDIST(I144,0,1,1) - $B$6*NORMDIST(J144,0,1,1),$B$6*NORMDIST(-J144,0,1,1) - B144*NORMDIST(-I144,0,1,1) ) - $G$6) * $P$6 | I144: =(LN(B144/$B$6)+($H$6^2/2)*($J$6))/($H$6*SQRT($J$6)) | J144: =I144 - $H$6*SQRT($J$6)
B145: =B115 | C145: =IF($O$6="sell",-1,1) * IF($K$6="call", NORMDIST(I145,0,1,1), NORMDIST(I145,0,1,1)-1 ) * $P$6 | D145: =IF($O$6="sell",-1,1) * NORMDIST(I145,0,1,0)/(B145*$H$6*SQRT($J$6)) * $P$6 | E145: =IF($O$6="sell",-1,1) * (B145*NORMDIST(I145,0,1,0)*SQRT($J$6)/365) * $P$6 | F145: =IF($O$6="sell",-1,1) * (-(B145*NORMDIST(I145,0,1,0)*$H$6)/(2*SQRT($J$6))/365) *$P$6 | G145: =IF($O$6="buy",1,-1)*( IF($K$6="call",B145*NORMDIST(I145,0,1,1) - $B$6*NORMDIST(J145,0,1,1),$B$6*NORMDIST(-J145,0,1,1) - B145*NORMDIST(-I145,0,1,1) ) - $G$6) * $P$6 | I145: =(LN(B145/$B$6)+($H$6^2/2)*($J$6))/($H$6*SQRT($J$6)) | J145: =I145 - $H$6*SQRT($J$6)
B146: =B116 | C146: =IF($O$6="sell",-1,1) * IF($K$6="call", NORMDIST(I146,0,1,1), NORMDIST(I146,0,1,1)-1 ) * $P$6 | D146: =IF($O$6="sell",-1,1) * NORMDIST(I146,0,1,0)/(B146*$H$6*SQRT($J$6)) * $P$6 | E146: =IF($O$6="sell",-1,1) * (B146*NORMDIST(I146,0,1,0)*SQRT($J$6)/365) * $P$6 | F146: =IF($O$6="sell",-1,1) * (-(B146*NORMDIST(I146,0,1,0)*$H$6)/(2*SQRT($J$6))/365) *$P$6 | G146: =IF($O$6="buy",1,-1)*( IF($K$6="call",B146*NORMDIST(I146,0,1,1) - $B$6*NORMDIST(J146,0,1,1),$B$6*NORMDIST(-J146,0,1,1) - B146*NORMDIST(-I146,0,1,1) ) - $G$6) * $P$6 | I146: =(LN(B146/$B$6)+($H$6^2/2)*($J$6))/($H$6*SQRT($J$6)) | J146: =I146 - $H$6*SQRT($J$6)
B147: =B117 | C147: =IF($O$6="sell",-1,1) * IF($K$6="call", NORMDIST(I147,0,1,1), NORMDIST(I147,0,1,1)-1 ) * $P$6 | D147: =IF($O$6="sell",-1,1) * NORMDIST(I147,0,1,0)/(B147*$H$6*SQRT($J$6)) * $P$6 | E147: =IF($O$6="sell",-1,1) * (B147*NORMDIST(I147,0,1,0)*SQRT($J$6)/365) * $P$6 | F147: =IF($O$6="sell",-1,1) * (-(B147*NORMDIST(I147,0,1,0)*$H$6)/(2*SQRT($J$6))/365) *$P$6 | G147: =IF($O$6="buy",1,-1)*( IF($K$6="call",B147*NORMDIST(I147,0,1,1) - $B$6*NORMDIST(J147,0,1,1),$B$6*NORMDIST(-J147,0,1,1) - B147*NORMDIST(-I147,0,1,1) ) - $G$6) * $P$6 | I147: =(LN(B147/$B$6)+($H$6^2/2)*($J$6))/($H$6*SQRT($J$6)) | J147: =I147 - $H$6*SQRT($J$6)
B148: =B118 | C148: =IF($O$6="sell",-1,1) * IF($K$6="call", NORMDIST(I148,0,1,1), NORMDIST(I148,0,1,1)-1 ) * $P$6 | D148: =IF($O$6="sell",-1,1) * NORMDIST(I148,0,1,0)/(B148*$H$6*SQRT($J$6)) * $P$6 | E148: =IF($O$6="sell",-1,1) * (B148*NORMDIST(I148,0,1,0)*SQRT($J$6)/365) * $P$6 | F148: =IF($O$6="sell",-1,1) * (-(B148*NORMDIST(I148,0,1,0)*$H$6)/(2*SQRT($J$6))/365) *$P$6 | G148: =IF($O$6="buy",1,-1)*( IF($K$6="call",B148*NORMDIST(I148,0,1,1) - $B$6*NORMDIST(J148,0,1,1),$B$6*NORMDIST(-J148,0,1,1) - B148*NORMDIST(-I148,0,1,1) ) - $G$6) * $P$6 | I148: =(LN(B148/$B$6)+($H$6^2/2)*($J$6))/($H$6*SQRT($J$6)) | J148: =I148 - $H$6*SQRT($J$6)
B149: =B119 | C149: =IF($O$6="sell",-1,1) * IF($K$6="call", NORMDIST(I149,0,1,1), NORMDIST(I149,0,1,1)-1 ) * $P$6 | D149: =IF($O$6="sell",-1,1) * NORMDIST(I149,0,1,0)/(B149*$H$6*SQRT($J$6)) * $P$6 | E149: =IF($O$6="sell",-1,1) * (B149*NORMDIST(I149,0,1,0)*SQRT($J$6)/365) * $P$6 | F149: =IF($O$6="sell",-1,1) * (-(B149*NORMDIST(I149,0,1,0)*$H$6)/(2*SQRT($J$6))/365) *$P$6 | G149: =IF($O$6="buy",1,-1)*( IF($K$6="call",B149*NORMDIST(I149,0,1,1) - $B$6*NORMDIST(J149,0,1,1),$B$6*NORMDIST(-J149,0,1,1) - B149*NORMDIST(-I149,0,1,1) ) - $G$6) * $P$6 | I149: =(LN(B149/$B$6)+($H$6^2/2)*($J$6))/($H$6*SQRT($J$6)) | J149: =I149 - $H$6*SQRT($J$6)
B150: =B120 | C150: =IF($O$6="sell",-1,1) * IF($K$6="call", NORMDIST(I150,0,1,1), NORMDIST(I150,0,1,1)-1 ) * $P$6 | D150: =IF($O$6="sell",-1,1) * NORMDIST(I150,0,1,0)/(B150*$H$6*SQRT($J$6)) * $P$6 | E150: =IF($O$6="sell",-1,1) * (B150*NORMDIST(I150,0,1,0)*SQRT($J$6)/365) * $P$6 | F150: =IF($O$6="sell",-1,1) * (-(B150*NORMDIST(I150,0,1,0)*$H$6)/(2*SQRT($J$6))/365) *$P$6 | G150: =IF($O$6="buy",1,-1)*( IF($K$6="call",B150*NORMDIST(I150,0,1,1) - $B$6*NORMDIST(J150,0,1,1),$B$6*NORMDIST(-J150,0,1,1) - B150*NORMDIST(-I150,0,1,1) ) - $G$6) * $P$6 | I150: =(LN(B150/$B$6)+($H$6^2/2)*($J$6))/($H$6*SQRT($J$6)) | J150: =I150 - $H$6*SQRT($J$6)
... B164: =B134 | C164: =IF($O$6="sell",-1,1) * IF($K$6="call", NORMDIST(I164,0,1,1), NORMDIST(I164,0,1,1)-1 ) * $P$6 | D164: =IF($O$6="sell",-1,1) * NORMDIST(I164,0,1,0)/(B164*$H$6*SQRT($J$6)) * $P$6 | E164: =IF($O$6="sell",-1,1) * (B164*NORMDIST(I164,0,1,0)*SQRT($J$6)/365) * $P$6 | F164: =IF($O$6="sell",-1,1) * (-(B164*NORMDIST(I164,0,1,0)*$H$6)/(2*SQRT($J$6))/365) *$P$6 | G164: =IF($O$6="buy",1,-1)*( IF($K$6="call",B164*NORMDIST(I164,0,1,1) - $B$6*NORMDIST(J164,0,1,1),$B$6*NORMDIST(-J164,0,1,1) - B164*NORMDIST(-I164,0,1,1) ) - $G$6) * $P$6 | I164: =(LN(B164/$B$6)+($H$6^2/2)*($J$6))/($H$6*SQRT($J$6)) | J164: =I164 - $H$6*SQRT($J$6)
C167: delta | D167: gamma | E167: vega | F167: theta | G167: mark_price | I167: d1 | J167: d2
A168: =A7 | B168: =B138 | C168: =IF($O$7="sell",-1,1) * IF($K$7="call", NORMDIST(I168,0,1,1), NORMDIST(I168,0,1,1)-1 ) * $P$7 | D168: =IF($O$7="sell",-1,1) * NORMDIST(I168,0,1,0)/(B168*$H$7*SQRT($J$7)) * $P$7 | E168: =IF($O$7="sell",-1,1) * (B168*NORMDIST(I168,0,1,0)*SQRT($J$7)/365) * $P$7 | F168: =IF($O$7="sell",-1,1) * (-(B168*NORMDIST(I168,0,1,0)*$H$7)/(2*SQRT($J$7))/365) *$P$7 | G168: =IF($O$7="buy",1,-1)*( IF($K$7="call",B168*NORMDIST(I168,0,1,1) - $B$7*NORMDIST(J168,0,1,1),$B$7*NORMDIST(-J168,0,1,1) - B168*NORMDIST(-I168,0,1,1) ) - $G$7) * $P$7 | I168: =(LN(B168/$B$7)+($H$7^2/2)*($J$7))/($H$7*SQRT($J$7)) | J168: =I168 - $H$7*SQRT($J$7)
B169: =B139 | C169: =IF($O$7="sell",-1,1) * IF($K$7="call", NORMDIST(I169,0,1,1), NORMDIST(I169,0,1,1)-1 ) * $P$7 | D169: =IF($O$7="sell",-1,1) * NORMDIST(I169,0,1,0)/(B169*$H$7*SQRT($J$7)) * $P$7 | E169: =IF($O$7="sell",-1,1) * (B169*NORMDIST(I169,0,1,0)*SQRT($J$7)/365) * $P$7 | F169: =IF($O$7="sell",-1,1) * (-(B169*NORMDIST(I169,0,1,0)*$H$7)/(2*SQRT($J$7))/365) *$P$7 | G169: =IF($O$7="buy",1,-1)*( IF($K$7="call",B169*NORMDIST(I169,0,1,1) - $B$7*NORMDIST(J169,0,1,1),$B$7*NORMDIST(-J169,0,1,1) - B169*NORMDIST(-I169,0,1,1) ) - $G$7) * $P$7 | I169: =(LN(B169/$B$7)+($H$7^2/2)*($J$7))/($H$7*SQRT($J$7)) | J169: =I169 - $H$7*SQRT($J$7)
B170: =B140 | C170: =IF($O$7="sell",-1,1) * IF($K$7="call", NORMDIST(I170,0,1,1), NORMDIST(I170,0,1,1)-1 ) * $P$7 | D170: =IF($O$7="sell",-1,1) * NORMDIST(I170,0,1,0)/(B170*$H$7*SQRT($J$7)) * $P$7 | E170: =IF($O$7="sell",-1,1) * (B170*NORMDIST(I170,0,1,0)*SQRT($J$7)/365) * $P$7 | F170: =IF($O$7="sell",-1,1) * (-(B170*NORMDIST(I170,0,1,0)*$H$7)/(2*SQRT($J$7))/365) *$P$7 | G170: =IF($O$7="buy",1,-1)*( IF($K$7="call",B170*NORMDIST(I170,0,1,1) - $B$7*NORMDIST(J170,0,1,1),$B$7*NORMDIST(-J170,0,1,1) - B170*NORMDIST(-I170,0,1,1) ) - $G$7) * $P$7 | I170: =(LN(B170/$B$7)+($H$7^2/2)*($J$7))/($H$7*SQRT($J$7)) | J170: =I170 - $H$7*SQRT($J$7)
B171: =B141 | C171: =IF($O$7="sell",-1,1) * IF($K$7="call", NORMDIST(I171,0,1,1), NORMDIST(I171,0,1,1)-1 ) * $P$7 | D171: =IF($O$7="sell",-1,1) * NORMDIST(I171,0,1,0)/(B171*$H$7*SQRT($J$7)) * $P$7 | E171: =IF($O$7="sell",-1,1) * (B171*NORMDIST(I171,0,1,0)*SQRT($J$7)/365) * $P$7 | F171: =IF($O$7="sell",-1,1) * (-(B171*NORMDIST(I171,0,1,0)*$H$7)/(2*SQRT($J$7))/365) *$P$7 | G171: =IF($O$7="buy",1,-1)*( IF($K$7="call",B171*NORMDIST(I171,0,1,1) - $B$7*NORMDIST(J171,0,1,1),$B$7*NORMDIST(-J171,0,1,1) - B171*NORMDIST(-I171,0,1,1) ) - $G$7) * $P$7 | I171: =(LN(B171/$B$7)+($H$7^2/2)*($J$7))/($H$7*SQRT($J$7)) | J171: =I171 - $H$7*SQRT($J$7)
B172: =B142 | C172: =IF($O$7="sell",-1,1) * IF($K$7="call", NORMDIST(I172,0,1,1), NORMDIST(I172,0,1,1)-1 ) * $P$7 | D172: =IF($O$7="sell",-1,1) * NORMDIST(I172,0,1,0)/(B172*$H$7*SQRT($J$7)) * $P$7 | E172: =IF($O$7="sell",-1,1) * (B172*NORMDIST(I172,0,1,0)*SQRT($J$7)/365) * $P$7 | F172: =IF($O$7="sell",-1,1) * (-(B172*NORMDIST(I172,0,1,0)*$H$7)/(2*SQRT($J$7))/365) *$P$7 | G172: =IF($O$7="buy",1,-1)*( IF($K$7="call",B172*NORMDIST(I172,0,1,1) - $B$7*NORMDIST(J172,0,1,1),$B$7*NORMDIST(-J172,0,1,1) - B172*NORMDIST(-I172,0,1,1) ) - $G$7) * $P$7 | I172: =(LN(B172/$B$7)+($H$7^2/2)*($J$7))/($H$7*SQRT($J$7)) | J172: =I172 - $H$7*SQRT($J$7)
B173: =B143 | C173: =IF($O$7="sell",-1,1) * IF($K$7="call", NORMDIST(I173,0,1,1), NORMDIST(I173,0,1,1)-1 ) * $P$7 | D173: =IF($O$7="sell",-1,1) * NORMDIST(I173,0,1,0)/(B173*$H$7*SQRT($J$7)) * $P$7 | E173: =IF($O$7="sell",-1,1) * (B173*NORMDIST(I173,0,1,0)*SQRT($J$7)/365) * $P$7 | F173: =IF($O$7="sell",-1,1) * (-(B173*NORMDIST(I173,0,1,0)*$H$7)/(2*SQRT($J$7))/365) *$P$7 | G173: =IF($O$7="buy",1,-1)*( IF($K$7="call",B173*NORMDIST(I173,0,1,1) - $B$7*NORMDIST(J173,0,1,1),$B$7*NORMDIST(-J173,0,1,1) - B173*NORMDIST(-I173,0,1,1) ) - $G$7) * $P$7 | I173: =(LN(B173/$B$7)+($H$7^2/2)*($J$7))/($H$7*SQRT($J$7)) | J173: =I173 - $H$7*SQRT($J$7)
B174: =B144 | C174: =IF($O$7="sell",-1,1) * IF($K$7="call", NORMDIST(I174,0,1,1), NORMDIST(I174,0,1,1)-1 ) * $P$7 | D174: =IF($O$7="sell",-1,1) * NORMDIST(I174,0,1,0)/(B174*$H$7*SQRT($J$7)) * $P$7 | E174: =IF($O$7="sell",-1,1) * (B174*NORMDIST(I174,0,1,0)*SQRT($J$7)/365) * $P$7 | F174: =IF($O$7="sell",-1,1) * (-(B174*NORMDIST(I174,0,1,0)*$H$7)/(2*SQRT($J$7))/365) *$P$7 | G174: =IF($O$7="buy",1,-1)*( IF($K$7="call",B174*NORMDIST(I174,0,1,1) - $B$7*NORMDIST(J174,0,1,1),$B$7*NORMDIST(-J174,0,1,1) - B174*NORMDIST(-I174,0,1,1) ) - $G$7) * $P$7 | I174: =(LN(B174/$B$7)+($H$7^2/2)*($J$7))/($H$7*SQRT($J$7)) | J174: =I174 - $H$7*SQRT($J$7)
B175: =B145 | C175: =IF($O$7="sell",-1,1) * IF($K$7="call", NORMDIST(I175,0,1,1), NORMDIST(I175,0,1,1)-1 ) * $P$7 | D175: =IF($O$7="sell",-1,1) * NORMDIST(I175,0,1,0)/(B175*$H$7*SQRT($J$7)) * $P$7 | E175: =IF($O$7="sell",-1,1) * (B175*NORMDIST(I175,0,1,0)*SQRT($J$7)/365) * $P$7 | F175: =IF($O$7="sell",-1,1) * (-(B175*NORMDIST(I175,0,1,0)*$H$7)/(2*SQRT($J$7))/365) *$P$7 | G175: =IF($O$7="buy",1,-1)*( IF($K$7="call",B175*NORMDIST(I175,0,1,1) - $B$7*NORMDIST(J175,0,1,1),$B$7*NORMDIST(-J175,0,1,1) - B175*NORMDIST(-I175,0,1,1) ) - $G$7) * $P$7 | I175: =(LN(B175/$B$7)+($H$7^2/2)*($J$7))/($H$7*SQRT($J$7)) | J175: =I175 - $H$7*SQRT($J$7)
B176: =B146 | C176: =IF($O$7="sell",-1,1) * IF($K$7="call", NORMDIST(I176,0,1,1), NORMDIST(I176,0,1,1)-1 ) * $P$7 | D176: =IF($O$7="sell",-1,1) * NORMDIST(I176,0,1,0)/(B176*$H$7*SQRT($J$7)) * $P$7 | E176: =IF($O$7="sell",-1,1) * (B176*NORMDIST(I176,0,1,0)*SQRT($J$7)/365) * $P$7 | F176: =IF($O$7="sell",-1,1) * (-(B176*NORMDIST(I176,0,1,0)*$H$7)/(2*SQRT($J$7))/365) *$P$7 | G176: =IF($O$7="buy",1,-1)*( IF($K$7="call",B176*NORMDIST(I176,0,1,1) - $B$7*NORMDIST(J176,0,1,1),$B$7*NORMDIST(-J176,0,1,1) - B176*NORMDIST(-I176,0,1,1) ) - $G$7) * $P$7 | I176: =(LN(B176/$B$7)+($H$7^2/2)*($J$7))/($H$7*SQRT($J$7)) | J176: =I176 - $H$7*SQRT($J$7)
B177: =B147 | C177: =IF($O$7="sell",-1,1) * IF($K$7="call", NORMDIST(I177,0,1,1), NORMDIST(I177,0,1,1)-1 ) * $P$7 | D177: =IF($O$7="sell",-1,1) * NORMDIST(I177,0,1,0)/(B177*$H$7*SQRT($J$7)) * $P$7 | E177: =IF($O$7="sell",-1,1) * (B177*NORMDIST(I177,0,1,0)*SQRT($J$7)/365) * $P$7 | F177: =IF($O$7="sell",-1,1) * (-(B177*NORMDIST(I177,0,1,0)*$H$7)/(2*SQRT($J$7))/365) *$P$7 | G177: =IF($O$7="buy",1,-1)*( IF($K$7="call",B177*NORMDIST(I177,0,1,1) - $B$7*NORMDIST(J177,0,1,1),$B$7*NORMDIST(-J177,0,1,1) - B177*NORMDIST(-I177,0,1,1) ) - $G$7) * $P$7 | I177: =(LN(B177/$B$7)+($H$7^2/2)*($J$7))/($H$7*SQRT($J$7)) | J177: =I177 - $H$7*SQRT($J$7)
...

Sheet Portfolio
J2: DTE | K2: % просадки
B3: Текущая дата | C3: Текущая цена | H3: Ближний слой | J3: 5-10 | K3: 0 | L3: 0.05
B4: =TODAY() | C4: =OptionBoard!L2 | H4: Средний слой | J4: 10-20 | K4: 0.05 | L4: 0.15
H5: Дальный слой | J5: 20-40 | K5: 0.16 | L5: выше
A7: Информация по портфелю
A9: № | B9: Актив | C9: Количество | D9: Ср.Цена | E9: Pnl | F9: Нач. Стои | H9: symbol | I9: кол | J9: cost | K9: strike | L9: DTE | M9: layer
A10: 1 | B10: SOL | C10: =Actives!D13 | D10: =Actives!E13 | E10: =Actives!H13 | F10: =Actives!F13 | H10: =Far_laeyr!B59 | I10: =Far_laeyr!G59 | J10: =Far_laeyr!H59 | K10: =VLOOKUP(H10,OptionBoard!$A$2:$B$73,2,0) | L10: =VLOOKUP(H10,OptionBoard!$A$2:$I$72,9,0) | M10: 3
H11: =Far_laeyr!B60 | I11: =Far_laeyr!G60 | J11: =Far_laeyr!H60 | K11: =VLOOKUP(H11,OptionBoard!$A$2:$B$73,2,0) | L11: =VLOOKUP(H11,OptionBoard!$A$2:$I$72,9,0) | M11: 3
B12: Лимит | C12: =F10*0.05 | H12: =Far_laeyr!B61 | I12: =Far_laeyr!G61 | J12: =Far_laeyr!H61 | K12: =VLOOKUP(H12,OptionBoard!$A$2:$B$73,2,0) | L12: =VLOOKUP(H12,OptionBoard!$A$2:$I$72,9,0) | M12: 3
B13: Ближний слой | C13: =SUMIF(M$10:M$23,"=1",J$10:J$23) | D13: =0.1*$C$12 | E13: =0.2*$C$12 | H13: =Far_laeyr!B62 | I13: =Far_laeyr!G62 | J13: =Far_laeyr!H62 | K13: =VLOOKUP(H13,OptionBoard!$A$2:$B$73,2,0) | L13: =VLOOKUP(H13,OptionBoard!$A$2:$I$72,9,0) | M13: 3
B14: Средний слой | C14: =SUMIF(M$10:M$23,"=2",J$10:J$23) | D14: =0.3*$C$12 | E14: =0.4*$C$12 | H14: =Far_laeyr!B63 | I14: =Far_laeyr!G63 | J14: =Far_laeyr!H63 | K14: =VLOOKUP(H14,OptionBoard!$A$2:$B$73,2,0) | L14: =VLOOKUP(H14,OptionBoard!$A$2:$I$72,9,0) | M14: 3
B15: Дальный слой | C15: =SUMIF(M$10:M$23,"=3",J$10:J$23) | D15: =0.4*$C$12 | E15: =0.5*$C$12 | H15: =Far_laeyr!B64 | I15: =Far_laeyr!G64 | J15: =Far_laeyr!H64 | K15: =VLOOKUP(H15,OptionBoard!$A$2:$B$73,2,0) | L15: =VLOOKUP(H15,OptionBoard!$A$2:$I$72,9,0) | M15: 3
B16: Стоимость хэджа | C16: =SUM(C13:C15) | H16: =Far_laeyr!B65 | I16: =Far_laeyr!G65 | J16: =Far_laeyr!H65 | K16: =VLOOKUP(H16,OptionBoard!$A$2:$B$73,2,0) | L16: =VLOOKUP(H16,OptionBoard!$A$2:$I$72,9,0) | M16: 3
B17: Запас | C17: =C12-C16 | H17: =MID_laeyr!B62 | I17: =MID_laeyr!G62 | J17: =MID_laeyr!H62 | K17: =VLOOKUP(H17,OptionBoard!$A$2:$B$73,2,0) | L17: =VLOOKUP(H17,OptionBoard!$A$2:$I$72,9,0) | M17: 2
H18: =MID_laeyr!B63 | I18: =MID_laeyr!G63 | J18: =MID_laeyr!H63 | K18: =VLOOKUP(H18,OptionBoard!$A$2:$B$73,2,0) | L18: =VLOOKUP(H18,OptionBoard!$A$2:$I$72,9,0) | M18: 2
B19: Доходный Pnl | C19: =Actives!D36 | H19: =MID_laeyr!B64 | I19: =MID_laeyr!G64 | J19: =MID_laeyr!H64 | K19: =VLOOKUP(H19,OptionBoard!$A$2:$B$73,2,0) | L19: =VLOOKUP(H19,OptionBoard!$A$2:$I$72,9,0) | M19: 2
H20: SOL-17APR26-72-P-USDT | I20: 3 | J20: =Hedge_Total!N12 | K20: =VLOOKUP(H20,OptionBoard!$A$2:$B$73,2,0) | L20: =VLOOKUP(H20,OptionBoard!$A$2:$I$72,9,0) | M20: 1
H21: SOL-17APR26-75-P-USDT | I21: 4 | J21: =Hedge_Total!N13 | K21: =VLOOKUP(H21,OptionBoard!$A$2:$B$73,2,0) | L21: =VLOOKUP(H21,OptionBoard!$A$2:$I$72,9,0) | M21: 1
H22: SOL-17APR26-78-P-USDT | I22: 4 | J22: =Hedge_Total!N14 | K22: =VLOOKUP(H22,OptionBoard!$A$2:$B$73,2,0) | L22: =VLOOKUP(H22,OptionBoard!$A$2:$I$72,9,0) | M22: 1
H23: SOL-17APR26-80-P-USDT | I23: 2 | J23: =Hedge_Total!N15 | K23: =VLOOKUP(H23,OptionBoard!$A$2:$B$73,2,0) | L23: =VLOOKUP(H23,OptionBoard!$A$2:$I$72,9,0) | M23: 1
J24: =SUM(J10:J23)
B26: Activ | H26: Total Options | S26: =H10 | U26: =H11 | W26: =H12 | Y26: =H13 | AA26: =H14 | AC26: =H15 | AE26: =H16 | AG26: =H17 | AI26: =H18 | AK26: =H19 | AM26: =H20 | AO26: =H21 | AQ26: =H22 | AS26: =H23
B27: Price | C27: Efficien Pnl | D27: Efficien Intr | E27: Pnl | F27: %loss | H27: Price | I27: Delta | J27: Pnl | K27: Intrin | L27: Pnl %loss | M27: Int %loss | N27: Pnl_loss | O27: Intrin_Loss | R27: Price | S27: Pnl | T27: Intrin | U27: Pnl | V27: Intrin | W27: Pnl | X27: Intrin | Y27: Pnl | Z27: Intrin | AA27: Pnl | AB27: Intrin | AC27: Pnl | AD27: Intrin | AE27: Pnl | AF27: Intrin | AG27: Pnl | AH27: Intrin | AI27: Pnl | AJ27: Intrin | AK27: Pnl | AL27: Intrin | AM27: Pnl | AN27: Intrin | AO27: Pnl | AP27: Intrin | AQ27: Pnl | AR27: Intrin | AS27: Pnl | AT27: Intrin
B28: =ROUND(D10,0) | C28: =J28/$C$16 | D28: =K28/$C$16 | E28: =($C$10*B28)-$F$10 | F28: =(E28/$F$10) | H28: =B28 | I28: =Hedge_Total!C438 | J28: =Hedge_Total!G438 | K28: =T28+V28+X28+Z28+AB28+AD28+AF28+AH28+AJ28+AL28+AN28+AP28+AR28+AT28 | L28: =N28/$F$10 | M28: =O28/$F$10 | N28: =E28+J28 | O28: =E28+K28 | R28: =B28 | S28: =Hedge_Total!G21 | T28: =IF(B28>$K$10,-1*$J$10,(($K$10-B28)*$I$10)-$J$10) | U28: =Hedge_Total!G50 | V28: =IF(B28>$K$11,-1*$J$11,(($K$11-B28)*$I$11)-$J$11) | W28: =Hedge_Total!G79 | X28: =IF(B28>$K$12,-1*$J$12,(($K$12-B28)*$I$12)-$J$12) | Y28: =Hedge_Total!G108 | Z28: =IF(B28>$K$13,-1*$J$13,(($K$13-B28)*$I$13)-$J$13) | AA28: =Hedge_Total!G138 | AB28: =IF(B28>$K$14,-1*$J$14,(($K$14-B28)*$I$14)-$J$14) | AC28: =Hedge_Total!G168 | AD28: =IF(B28>$K$15,-1*$J$15,(($K$15-B28)*$I$15)-$J$15) | AE28: =Hedge_Total!G198 | AF28: =IF(B28>$K$16,-1*$J$16,(($K$16-B28)*$I$16)-$J$16) | AG28: =Hedge_Total!G228 | AH28: =IF(B28>$K$17,-1*$J$17,(($K$17-B28)*$I$17)-$J$17) | AI28: =Hedge_Total!G258 | AJ28: =IF(B28>$K$18,-1*$J$18,(($K$18-B28)*$I$18)-$J$18) | AK28: =Hedge_Total!G288 | AL28: =IF(B28>$K$19,-1*$J$19,(($K$19-B28)*$I$19)-$J$19) | AM28: =Hedge_Total!G318 | AN28: =IF(B28>$K$20,-1*$J$20,(($K$20-B28)*$I$20)-$J$20) | AO28: =Hedge_Total!G348 | AP28: =IF(B28>$K$21,-1*$J$21,(($K$21-B28)*$I$21)-$J$21) | AQ28: =Hedge_Total!G378 | AR28: =IF(B28>$K$22,-1*$J$22,(($K$22-B28)*$I$22)-$J$22) | AS28: =Hedge_Total!G408 | AT28: =IF(B28>$K$23,-1*$J$23,(($K$23-B28)*$I$23)-$J$23)
B29: =B28-1 | C29: =J29/$C$16 | D29: =K29/$C$16 | E29: =($C$10*B29)-$F$10 | F29: =(E29/$F$10) | H29: =H28-1 | I29: =Hedge_Total!C439 | J29: =Hedge_Total!G439 | K29: =T29+V29+X29+Z29+AB29+AD29+AF29+AH29+AJ29+AL29+AN29+AP29+AR29+AT29 | L29: =N29/$F$10 | M29: =O29/$F$10 | N29: =E29+J29 | O29: =E29+K29 | P29: =J30-2*J29+J28 | R29: =R28-1 | S29: =Hedge_Total!G22 | T29: =IF(B29>$K$10,-1*$J$10,(($K$10-B29)*$I$10)-$J$10) | U29: =Hedge_Total!G51 | V29: =IF(B29>$K$11,-1*$J$11,(($K$11-B29)*$I$11)-$J$11) | W29: =Hedge_Total!G80 | X29: =IF(B29>$K$12,-1*$J$12,(($K$12-B29)*$I$12)-$J$12) | Y29: =Hedge_Total!G109 | Z29: =IF(B29>$K$13,-1*$J$13,(($K$13-B29)*$I$13)-$J$13) | AA29: =Hedge_Total!G139 | AB29: =IF(B29>$K$14,-1*$J$14,(($K$14-B29)*$I$14)-$J$14) | AC29: =Hedge_Total!G169 | AD29: =IF(B29>$K$15,-1*$J$15,(($K$15-B29)*$I$15)-$J$15) | AE29: =Hedge_Total!G199 | AF29: =IF(B29>$K$16,-1*$J$16,(($K$16-B29)*$I$16)-$J$16) | AG29: =Hedge_Total!G229 | AH29: =IF(B29>$K$17,-1*$J$17,(($K$17-B29)*$I$17)-$J$17) | AI29: =Hedge_Total!G259 | AJ29: =IF(B29>$K$18,-1*$J$18,(($K$18-B29)*$I$18)-$J$18) | AK29: =Hedge_Total!G289 | AL29: =IF(B29>$K$19,-1*$J$19,(($K$19-B29)*$I$19)-$J$19) | AM29: =Hedge_Total!G319 | AN29: =IF(B29>$K$20,-1*$J$20,(($K$20-B29)*$I$20)-$J$20) | AO29: =Hedge_Total!G349 | AP29: =IF(B29>$K$21,-1*$J$21,(($K$21-B29)*$I$21)-$J$21) | AQ29: =Hedge_Total!G379 | AR29: =IF(B29>$K$22,-1*$J$22,(($K$22-B29)*$I$22)-$J$22) | AS29: =Hedge_Total!G409 | AT29: =IF(B29>$K$23,-1*$J$23,(($K$23-B29)*$I$23)-$J$23)
B30: =B29-1 | C30: =J30/$C$16 | D30: =K30/$C$16 | E30: =($C$10*B30)-$F$10 | F30: =(E30/$F$10) | H30: =H29-1 | I30: =Hedge_Total!C440 | J30: =Hedge_Total!G440 | K30: =T30+V30+X30+Z30+AB30+AD30+AF30+AH30+AJ30+AL30+AN30+AP30+AR30+AT30 | L30: =N30/$F$10 | M30: =O30/$F$10 | N30: =E30+J30 | O30: =E30+K30 | P30: =J31-2*J30+J29 | R30: =R29-1 | S30: =Hedge_Total!G23 | T30: =IF(B30>$K$10,-1*$J$10,(($K$10-B30)*$I$10)-$J$10) | U30: =Hedge_Total!G52 | V30: =IF(B30>$K$11,-1*$J$11,(($K$11-B30)*$I$11)-$J$11) | W30: =Hedge_Total!G81 | X30: =IF(B30>$K$12,-1*$J$12,(($K$12-B30)*$I$12)-$J$12) | Y30: =Hedge_Total!G110 | Z30: =IF(B30>$K$13,-1*$J$13,(($K$13-B30)*$I$13)-$J$13) | AA30: =Hedge_Total!G140 | AB30: =IF(B30>$K$14,-1*$J$14,(($K$14-B30)*$I$14)-$J$14) | AC30: =Hedge_Total!G170 | AD30: =IF(B30>$K$15,-1*$J$15,(($K$15-B30)*$I$15)-$J$15) | AE30: =Hedge_Total!G200 | AF30: =IF(B30>$K$16,-1*$J$16,(($K$16-B30)*$I$16)-$J$16) | AG30: =Hedge_Total!G230 | AH30: =IF(B30>$K$17,-1*$J$17,(($K$17-B30)*$I$17)-$J$17) | AI30: =Hedge_Total!G260 | AJ30: =IF(B30>$K$18,-1*$J$18,(($K$18-B30)*$I$18)-$J$18) | AK30: =Hedge_Total!G290 | AL30: =IF(B30>$K$19,-1*$J$19,(($K$19-B30)*$I$19)-$J$19) | AM30: =Hedge_Total!G320 | AN30: =IF(B30>$K$20,-1*$J$20,(($K$20-B30)*$I$20)-$J$20) | AO30: =Hedge_Total!G350 | AP30: =IF(B30>$K$21,-1*$J$21,(($K$21-B30)*$I$21)-$J$21) | AQ30: =Hedge_Total!G380 | AR30: =IF(B30>$K$22,-1*$J$22,(($K$22-B30)*$I$22)-$J$22) | AS30: =Hedge_Total!G410 | AT30: =IF(B30>$K$23,-1*$J$23,(($K$23-B30)*$I$23)-$J$23)
B31: =B30-1 | C31: =J31/$C$16 | D31: =K31/$C$16 | E31: =($C$10*B31)-$F$10 | F31: =(E31/$F$10) | H31: =H30-1 | I31: =Hedge_Total!C441 | J31: =Hedge_Total!G441 | K31: =T31+V31+X31+Z31+AB31+AD31+AF31+AH31+AJ31+AL31+AN31+AP31+AR31+AT31 | L31: =N31/$F$10 | M31: =O31/$F$10 | N31: =E31+J31 | O31: =E31+K31 | P31: =J32-2*J31+J30 | R31: =R30-1 | S31: =Hedge_Total!G24 | T31: =IF(B31>$K$10,-1*$J$10,(($K$10-B31)*$I$10)-$J$10) | U31: =Hedge_Total!G53 | V31: =IF(B31>$K$11,-1*$J$11,(($K$11-B31)*$I$11)-$J$11) | W31: =Hedge_Total!G82 | X31: =IF(B31>$K$12,-1*$J$12,(($K$12-B31)*$I$12)-$J$12) | Y31: =Hedge_Total!G111 | Z31: =IF(B31>$K$13,-1*$J$13,(($K$13-B31)*$I$13)-$J$13) | AA31: =Hedge_Total!G141 | AB31: =IF(B31>$K$14,-1*$J$14,(($K$14-B31)*$I$14)-$J$14) | AC31: =Hedge_Total!G171 | AD31: =IF(B31>$K$15,-1*$J$15,(($K$15-B31)*$I$15)-$J$15) | AE31: =Hedge_Total!G201 | AF31: =IF(B31>$K$16,-1*$J$16,(($K$16-B31)*$I$16)-$J$16) | AG31: =Hedge_Total!G231 | AH31: =IF(B31>$K$17,-1*$J$17,(($K$17-B31)*$I$17)-$J$17) | AI31: =Hedge_Total!G261 | AJ31: =IF(B31>$K$18,-1*$J$18,(($K$18-B31)*$I$18)-$J$18) | AK31: =Hedge_Total!G291 | AL31: =IF(B31>$K$19,-1*$J$19,(($K$19-B31)*$I$19)-$J$19) | AM31: =Hedge_Total!G321 | AN31: =IF(B31>$K$20,-1*$J$20,(($K$20-B31)*$I$20)-$J$20) | AO31: =Hedge_Total!G351 | AP31: =IF(B31>$K$21,-1*$J$21,(($K$21-B31)*$I$21)-$J$21) | AQ31: =Hedge_Total!G381 | AR31: =IF(B31>$K$22,-1*$J$22,(($K$22-B31)*$I$22)-$J$22) | AS31: =Hedge_Total!G411 | AT31: =IF(B31>$K$23,-1*$J$23,(($K$23-B31)*$I$23)-$J$23)
B32: =B31-1 | C32: =J32/$C$16 | D32: =K32/$C$16 | E32: =($C$10*B32)-$F$10 | F32: =(E32/$F$10) | H32: =H31-1 | I32: =Hedge_Total!C442 | J32: =Hedge_Total!G442 | K32: =T32+V32+X32+Z32+AB32+AD32+AF32+AH32+AJ32+AL32+AN32+AP32+AR32+AT32 | L32: =N32/$F$10 | M32: =O32/$F$10 | N32: =E32+J32 | O32: =E32+K32 | P32: =J33-2*J32+J31 | R32: =R31-1 | S32: =Hedge_Total!G25 | T32: =IF(B32>$K$10,-1*$J$10,(($K$10-B32)*$I$10)-$J$10) | U32: =Hedge_Total!G54 | V32: =IF(B32>$K$11,-1*$J$11,(($K$11-B32)*$I$11)-$J$11) | W32: =Hedge_Total!G83 | X32: =IF(B32>$K$12,-1*$J$12,(($K$12-B32)*$I$12)-$J$12) | Y32: =Hedge_Total!G112 | Z32: =IF(B32>$K$13,-1*$J$13,(($K$13-B32)*$I$13)-$J$13) | AA32: =Hedge_Total!G142 | AB32: =IF(B32>$K$14,-1*$J$14,(($K$14-B32)*$I$14)-$J$14) | AC32: =Hedge_Total!G172 | AD32: =IF(B32>$K$15,-1*$J$15,(($K$15-B32)*$I$15)-$J$15) | AE32: =Hedge_Total!G202 | AF32: =IF(B32>$K$16,-1*$J$16,(($K$16-B32)*$I$16)-$J$16) | AG32: =Hedge_Total!G232 | AH32: =IF(B32>$K$17,-1*$J$17,(($K$17-B32)*$I$17)-$J$17) | AI32: =Hedge_Total!G262 | AJ32: =IF(B32>$K$18,-1*$J$18,(($K$18-B32)*$I$18)-$J$18) | AK32: =Hedge_Total!G292 | AL32: =IF(B32>$K$19,-1*$J$19,(($K$19-B32)*$I$19)-$J$19) | AM32: =Hedge_Total!G322 | AN32: =IF(B32>$K$20,-1*$J$20,(($K$20-B32)*$I$20)-$J$20) | AO32: =Hedge_Total!G352 | AP32: =IF(B32>$K$21,-1*$J$21,(($K$21-B32)*$I$21)-$J$21) | AQ32: =Hedge_Total!G382 | AR32: =IF(B32>$K$22,-1*$J$22,(($K$22-B32)*$I$22)-$J$22) | AS32: =Hedge_Total!G412 | AT32: =IF(B32>$K$23,-1*$J$23,(($K$23-B32)*$I$23)-$J$23)
B33: =B32-1 | C33: =J33/$C$16 | D33: =K33/$C$16 | E33: =($C$10*B33)-$F$10 | F33: =(E33/$F$10) | H33: =H32-1 | I33: =Hedge_Total!C443 | J33: =Hedge_Total!G443 | K33: =T33+V33+X33+Z33+AB33+AD33+AF33+AH33+AJ33+AL33+AN33+AP33+AR33+AT33 | L33: =N33/$F$10 | M33: =O33/$F$10 | N33: =E33+J33 | O33: =E33+K33 | P33: =J34-2*J33+J32 | R33: =R32-1 | S33: =Hedge_Total!G26 | T33: =IF(B33>$K$10,-1*$J$10,(($K$10-B33)*$I$10)-$J$10) | U33: =Hedge_Total!G55 | V33: =IF(B33>$K$11,-1*$J$11,(($K$11-B33)*$I$11)-$J$11) | W33: =Hedge_Total!G84 | X33: =IF(B33>$K$12,-1*$J$12,(($K$12-B33)*$I$12)-$J$12) | Y33: =Hedge_Total!G113 | Z33: =IF(B33>$K$13,-1*$J$13,(($K$13-B33)*$I$13)-$J$13) | AA33: =Hedge_Total!G143 | AB33: =IF(B33>$K$14,-1*$J$14,(($K$14-B33)*$I$14)-$J$14) | AC33: =Hedge_Total!G173 | AD33: =IF(B33>$K$15,-1*$J$15,(($K$15-B33)*$I$15)-$J$15) | AE33: =Hedge_Total!G203 | AF33: =IF(B33>$K$16,-1*$J$16,(($K$16-B33)*$I$16)-$J$16) | AG33: =Hedge_Total!G233 | AH33: =IF(B33>$K$17,-1*$J$17,(($K$17-B33)*$I$17)-$J$17) | AI33: =Hedge_Total!G263 | AJ33: =IF(B33>$K$18,-1*$J$18,(($K$18-B33)*$I$18)-$J$18) | AK33: =Hedge_Total!G293 | AL33: =IF(B33>$K$19,-1*$J$19,(($K$19-B33)*$I$19)-$J$19) | AM33: =Hedge_Total!G323 | AN33: =IF(B33>$K$20,-1*$J$20,(($K$20-B33)*$I$20)-$J$20) | AO33: =Hedge_Total!G353 | AP33: =IF(B33>$K$21,-1*$J$21,(($K$21-B33)*$I$21)-$J$21) | AQ33: =Hedge_Total!G383 | AR33: =IF(B33>$K$22,-1*$J$22,(($K$22-B33)*$I$22)-$J$22) | AS33: =Hedge_Total!G413 | AT33: =IF(B33>$K$23,-1*$J$23,(($K$23-B33)*$I$23)-$J$23)
B34: =B33-1 | C34: =J34/$C$16 | D34: =K34/$C$16 | E34: =($C$10*B34)-$F$10 | F34: =(E34/$F$10) | H34: =H33-1 | I34: =Hedge_Total!C444 | J34: =Hedge_Total!G444 | K34: =T34+V34+X34+Z34+AB34+AD34+AF34+AH34+AJ34+AL34+AN34+AP34+AR34+AT34 | L34: =N34/$F$10 | M34: =O34/$F$10 | N34: =E34+J34 | O34: =E34+K34 | P34: =J35-2*J34+J33 | R34: =R33-1 | S34: =Hedge_Total!G27 | T34: =IF(B34>$K$10,-1*$J$10,(($K$10-B34)*$I$10)-$J$10) | U34: =Hedge_Total!G56 | V34: =IF(B34>$K$11,-1*$J$11,(($K$11-B34)*$I$11)-$J$11) | W34: =Hedge_Total!G85 | X34: =IF(B34>$K$12,-1*$J$12,(($K$12-B34)*$I$12)-$J$12) | Y34: =Hedge_Total!G114 | Z34: =IF(B34>$K$13,-1*$J$13,(($K$13-B34)*$I$13)-$J$13) | AA34: =Hedge_Total!G144 | AB34: =IF(B34>$K$14,-1*$J$14,(($K$14-B34)*$I$14)-$J$14) | AC34: =Hedge_Total!G174 | AD34: =IF(B34>$K$15,-1*$J$15,(($K$15-B34)*$I$15)-$J$15) | AE34: =Hedge_Total!G204 | AF34: =IF(B34>$K$16,-1*$J$16,(($K$16-B34)*$I$16)-$J$16) | AG34: =Hedge_Total!G234 | AH34: =IF(B34>$K$17,-1*$J$17,(($K$17-B34)*$I$17)-$J$17) | AI34: =Hedge_Total!G264 | AJ34: =IF(B34>$K$18,-1*$J$18,(($K$18-B34)*$I$18)-$J$18) | AK34: =Hedge_Total!G294 | AL34: =IF(B34>$K$19,-1*$J$19,(($K$19-B34)*$I$19)-$J$19) | AM34: =Hedge_Total!G324 | AN34: =IF(B34>$K$20,-1*$J$20,(($K$20-B34)*$I$20)-$J$20) | AO34: =Hedge_Total!G354 | AP34: =IF(B34>$K$21,-1*$J$21,(($K$21-B34)*$I$21)-$J$21) | AQ34: =Hedge_Total!G384 | AR34: =IF(B34>$K$22,-1*$J$22,(($K$22-B34)*$I$22)-$J$22) | AS34: =Hedge_Total!G414 | AT34: =IF(B34>$K$23,-1*$J$23,(($K$23-B34)*$I$23)-$J$23)
B35: =B34-1 | C35: =J35/$C$16 | D35: =K35/$C$16 | E35: =($C$10*B35)-$F$10 | F35: =(E35/$F$10) | H35: =H34-1 | I35: =Hedge_Total!C445 | J35: =Hedge_Total!G445 | K35: =T35+V35+X35+Z35+AB35+AD35+AF35+AH35+AJ35+AL35+AN35+AP35+AR35+AT35 | L35: =N35/$F$10 | M35: =O35/$F$10 | N35: =E35+J35 | O35: =E35+K35 | P35: =J36-2*J35+J34 | R35: =R34-1 | S35: =Hedge_Total!G28 | T35: =IF(B35>$K$10,-1*$J$10,(($K$10-B35)*$I$10)-$J$10) | U35: =Hedge_Total!G57 | V35: =IF(B35>$K$11,-1*$J$11,(($K$11-B35)*$I$11)-$J$11) | W35: =Hedge_Total!G86 | X35: =IF(B35>$K$12,-1*$J$12,(($K$12-B35)*$I$12)-$J$12) | Y35: =Hedge_Total!G115 | Z35: =IF(B35>$K$13,-1*$J$13,(($K$13-B35)*$I$13)-$J$13) | AA35: =Hedge_Total!G145 | AB35: =IF(B35>$K$14,-1*$J$14,(($K$14-B35)*$I$14)-$J$14) | AC35: =Hedge_Total!G175 | AD35: =IF(B35>$K$15,-1*$J$15,(($K$15-B35)*$I$15)-$J$15) | AE35: =Hedge_Total!G205 | AF35: =IF(B35>$K$16,-1*$J$16,(($K$16-B35)*$I$16)-$J$16) | AG35: =Hedge_Total!G235 | AH35: =IF(B35>$K$17,-1*$J$17,(($K$17-B35)*$I$17)-$J$17) | AI35: =Hedge_Total!G265 | AJ35: =IF(B35>$K$18,-1*$J$18,(($K$18-B35)*$I$18)-$J$18) | AK35: =Hedge_Total!G295 | AL35: =IF(B35>$K$19,-1*$J$19,(($K$19-B35)*$I$19)-$J$19) | AM35: =Hedge_Total!G325 | AN35: =IF(B35>$K$20,-1*$J$20,(($K$20-B35)*$I$20)-$J$20) | AO35: =Hedge_Total!G355 | AP35: =IF(B35>$K$21,-1*$J$21,(($K$21-B35)*$I$21)-$J$21) | AQ35: =Hedge_Total!G385 | AR35: =IF(B35>$K$22,-1*$J$22,(($K$22-B35)*$I$22)-$J$22) | AS35: =Hedge_Total!G415 | AT35: =IF(B35>$K$23,-1*$J$23,(($K$23-B35)*$I$23)-$J$23)
B36: =B35-1 | C36: =J36/$C$16 | D36: =K36/$C$16 | E36: =($C$10*B36)-$F$10 | F36: =(E36/$F$10) | H36: =H35-1 | I36: =Hedge_Total!C446 | J36: =Hedge_Total!G446 | K36: =T36+V36+X36+Z36+AB36+AD36+AF36+AH36+AJ36+AL36+AN36+AP36+AR36+AT36 | L36: =N36/$F$10 | M36: =O36/$F$10 | N36: =E36+J36 | O36: =E36+K36 | P36: =J37-2*J36+J35 | R36: =R35-1 | S36: =Hedge_Total!G29 | T36: =IF(B36>$K$10,-1*$J$10,(($K$10-B36)*$I$10)-$J$10) | U36: =Hedge_Total!G58 | V36: =IF(B36>$K$11,-1*$J$11,(($K$11-B36)*$I$11)-$J$11) | W36: =Hedge_Total!G87 | X36: =IF(B36>$K$12,-1*$J$12,(($K$12-B36)*$I$12)-$J$12) | Y36: =Hedge_Total!G116 | Z36: =IF(B36>$K$13,-1*$J$13,(($K$13-B36)*$I$13)-$J$13) | AA36: =Hedge_Total!G146 | AB36: =IF(B36>$K$14,-1*$J$14,(($K$14-B36)*$I$14)-$J$14) | AC36: =Hedge_Total!G176 | AD36: =IF(B36>$K$15,-1*$J$15,(($K$15-B36)*$I$15)-$J$15) | AE36: =Hedge_Total!G206 | AF36: =IF(B36>$K$16,-1*$J$16,(($K$16-B36)*$I$16)-$J$16) | AG36: =Hedge_Total!G236 | AH36: =IF(B36>$K$17,-1*$J$17,(($K$17-B36)*$I$17)-$J$17) | AI36: =Hedge_Total!G266 | AJ36: =IF(B36>$K$18,-1*$J$18,(($K$18-B36)*$I$18)-$J$18) | AK36: =Hedge_Total!G296 | AL36: =IF(B36>$K$19,-1*$J$19,(($K$19-B36)*$I$19)-$J$19) | AM36: =Hedge_Total!G326 | AN36: =IF(B36>$K$20,-1*$J$20,(($K$20-B36)*$I$20)-$J$20) | AO36: =Hedge_Total!G356 | AP36: =IF(B36>$K$21,-1*$J$21,(($K$21-B36)*$I$21)-$J$21) | AQ36: =Hedge_Total!G386 | AR36: =IF(B36>$K$22,-1*$J$22,(($K$22-B36)*$I$22)-$J$22) | AS36: =Hedge_Total!G416 | AT36: =IF(B36>$K$23,-1*$J$23,(($K$23-B36)*$I$23)-$J$23)
B37: =B36-1 | C37: =J37/$C$16 | D37: =K37/$C$16 | E37: =($C$10*B37)-$F$10 | F37: =(E37/$F$10) | H37: =H36-1 | I37: =Hedge_Total!C447 | J37: =Hedge_Total!G447 | K37: =T37+V37+X37+Z37+AB37+AD37+AF37+AH37+AJ37+AL37+AN37+AP37+AR37+AT37 | L37: =N37/$F$10 | M37: =O37/$F$10 | N37: =E37+J37 | O37: =E37+K37 | P37: =J38-2*J37+J36 | R37: =R36-1 | S37: =Hedge_Total!G30 | T37: =IF(B37>$K$10,-1*$J$10,(($K$10-B37)*$I$10)-$J$10) | U37: =Hedge_Total!G59 | V37: =IF(B37>$K$11,-1*$J$11,(($K$11-B37)*$I$11)-$J$11) | W37: =Hedge_Total!G88 | X37: =IF(B37>$K$12,-1*$J$12,(($K$12-B37)*$I$12)-$J$12) | Y37: =Hedge_Total!G117 | Z37: =IF(B37>$K$13,-1*$J$13,(($K$13-B37)*$I$13)-$J$13) | AA37: =Hedge_Total!G147 | AB37: =IF(B37>$K$14,-1*$J$14,(($K$14-B37)*$I$14)-$J$14) | AC37: =Hedge_Total!G177 | AD37: =IF(B37>$K$15,-1*$J$15,(($K$15-B37)*$I$15)-$J$15) | AE37: =Hedge_Total!G207 | AF37: =IF(B37>$K$16,-1*$J$16,(($K$16-B37)*$I$16)-$J$16) | AG37: =Hedge_Total!G237 | AH37: =IF(B37>$K$17,-1*$J$17,(($K$17-B37)*$I$17)-$J$17) | AI37: =Hedge_Total!G267 | AJ37: =IF(B37>$K$18,-1*$J$18,(($K$18-B37)*$I$18)-$J$18) | AK37: =Hedge_Total!G297 | AL37: =IF(B37>$K$19,-1*$J$19,(($K$19-B37)*$I$19)-$J$19) | AM37: =Hedge_Total!G327 | AN37: =IF(B37>$K$20,-1*$J$20,(($K$20-B37)*$I$20)-$J$20) | AO37: =Hedge_Total!G357 | AP37: =IF(B37>$K$21,-1*$J$21,(($K$21-B37)*$I$21)-$J$21) | AQ37: =Hedge_Total!G387 | AR37: =IF(B37>$K$22,-1*$J$22,(($K$22-B37)*$I$22)-$J$22) | AS37: =Hedge_Total!G417 | AT37: =IF(B37>$K$23,-1*$J$23,(($K$23-B37)*$I$23)-$J$23)
B38: =B37-1 | C38: =J38/$C$16 | D38: =K38/$C$16 | E38: =($C$10*B38)-$F$10 | F38: =(E38/$F$10) | H38: =H37-1 | I38: =Hedge_Total!C448 | J38: =Hedge_Total!G448 | K38: =T38+V38+X38+Z38+AB38+AD38+AF38+AH38+AJ38+AL38+AN38+AP38+AR38+AT38 | L38: =N38/$F$10 | M38: =O38/$F$10 | N38: =E38+J38 | O38: =E38+K38 | P38: =J39-2*J38+J37 | R38: =R37-1 | S38: =Hedge_Total!G31 | T38: =IF(B38>$K$10,-1*$J$10,(($K$10-B38)*$I$10)-$J$10) | U38: =Hedge_Total!G60 | V38: =IF(B38>$K$11,-1*$J$11,(($K$11-B38)*$I$11)-$J$11) | W38: =Hedge_Total!G89 | X38: =IF(B38>$K$12,-1*$J$12,(($K$12-B38)*$I$12)-$J$12) | Y38: =Hedge_Total!G118 | Z38: =IF(B38>$K$13,-1*$J$13,(($K$13-B38)*$I$13)-$J$13) | AA38: =Hedge_Total!G148 | AB38: =IF(B38>$K$14,-1*$J$14,(($K$14-B38)*$I$14)-$J$14) | AC38: =Hedge_Total!G178 | AD38: =IF(B38>$K$15,-1*$J$15,(($K$15-B38)*$I$15)-$J$15) | AE38: =Hedge_Total!G208 | AF38: =IF(B38>$K$16,-1*$J$16,(($K$16-B38)*$I$16)-$J$16) | AG38: =Hedge_Total!G238 | AH38: =IF(B38>$K$17,-1*$J$17,(($K$17-B38)*$I$17)-$J$17) | AI38: =Hedge_Total!G268 | AJ38: =IF(B38>$K$18,-1*$J$18,(($K$18-B38)*$I$18)-$J$18) | AK38: =Hedge_Total!G298 | AL38: =IF(B38>$K$19,-1*$J$19,(($K$19-B38)*$I$19)-$J$19) | AM38: =Hedge_Total!G328 | AN38: =IF(B38>$K$20,-1*$J$20,(($K$20-B38)*$I$20)-$J$20) | AO38: =Hedge_Total!G358 | AP38: =IF(B38>$K$21,-1*$J$21,(($K$21-B38)*$I$21)-$J$21) | AQ38: =Hedge_Total!G388 | AR38: =IF(B38>$K$22,-1*$J$22,(($K$22-B38)*$I$22)-$J$22) | AS38: =Hedge_Total!G418 | AT38: =IF(B38>$K$23,-1*$J$23,(($K$23-B38)*$I$23)-$J$23)
B39: =B38-1 | C39: =J39/$C$16 | D39: =K39/$C$16 | E39: =($C$10*B39)-$F$10 | F39: =(E39/$F$10) | H39: =H38-1 | I39: =Hedge_Total!C449 | J39: =Hedge_Total!G449 | K39: =T39+V39+X39+Z39+AB39+AD39+AF39+AH39+AJ39+AL39+AN39+AP39+AR39+AT39 | L39: =N39/$F$10 | M39: =O39/$F$10 | N39: =E39+J39 | O39: =E39+K39 | P39: =J40-2*J39+J38 | R39: =R38-1 | S39: =Hedge_Total!G32 | T39: =IF(B39>$K$10,-1*$J$10,(($K$10-B39)*$I$10)-$J$10) | U39: =Hedge_Total!G61 | V39: =IF(B39>$K$11,-1*$J$11,(($K$11-B39)*$I$11)-$J$11) | W39: =Hedge_Total!G90 | X39: =IF(B39>$K$12,-1*$J$12,(($K$12-B39)*$I$12)-$J$12) | Y39: =Hedge_Total!G119 | Z39: =IF(B39>$K$13,-1*$J$13,(($K$13-B39)*$I$13)-$J$13) | AA39: =Hedge_Total!G149 | AB39: =IF(B39>$K$14,-1*$J$14,(($K$14-B39)*$I$14)-$J$14) | AC39: =Hedge_Total!G179 | AD39: =IF(B39>$K$15,-1*$J$15,(($K$15-B39)*$I$15)-$J$15) | AE39: =Hedge_Total!G209 | AF39: =IF(B39>$K$16,-1*$J$16,(($K$16-B39)*$I$16)-$J$16) | AG39: =Hedge_Total!G239 | AH39: =IF(B39>$K$17,-1*$J$17,(($K$17-B39)*$I$17)-$J$17) | AI39: =Hedge_Total!G269 | AJ39: =IF(B39>$K$18,-1*$J$18,(($K$18-B39)*$I$18)-$J$18) | AK39: =Hedge_Total!G299 | AL39: =IF(B39>$K$19,-1*$J$19,(($K$19-B39)*$I$19)-$J$19) | AM39: =Hedge_Total!G329 | AN39: =IF(B39>$K$20,-1*$J$20,(($K$20-B39)*$I$20)-$J$20) | AO39: =Hedge_Total!G359 | AP39: =IF(B39>$K$21,-1*$J$21,(($K$21-B39)*$I$21)-$J$21) | AQ39: =Hedge_Total!G389 | AR39: =IF(B39>$K$22,-1*$J$22,(($K$22-B39)*$I$22)-$J$22) | AS39: =Hedge_Total!G419 | AT39: =IF(B39>$K$23,-1*$J$23,(($K$23-B39)*$I$23)-$J$23)
B40: =B39-1 | C40: =J40/$C$16 | D40: =K40/$C$16 | E40: =($C$10*B40)-$F$10 | F40: =(E40/$F$10) | H40: =H39-1 | I40: =Hedge_Total!C450 | J40: =Hedge_Total!G450 | K40: =T40+V40+X40+Z40+AB40+AD40+AF40+AH40+AJ40+AL40+AN40+AP40+AR40+AT40 | L40: =N40/$F$10 | M40: =O40/$F$10 | N40: =E40+J40 | O40: =E40+K40 | P40: =J41-2*J40+J39 | R40: =R39-1 | S40: =Hedge_Total!G33 | T40: =IF(B40>$K$10,-1*$J$10,(($K$10-B40)*$I$10)-$J$10) | U40: =Hedge_Total!G62 | V40: =IF(B40>$K$11,-1*$J$11,(($K$11-B40)*$I$11)-$J$11) | W40: =Hedge_Total!G91 | X40: =IF(B40>$K$12,-1*$J$12,(($K$12-B40)*$I$12)-$J$12) | Y40: =Hedge_Total!G120 | Z40: =IF(B40>$K$13,-1*$J$13,(($K$13-B40)*$I$13)-$J$13) | AA40: =Hedge_Total!G150 | AB40: =IF(B40>$K$14,-1*$J$14,(($K$14-B40)*$I$14)-$J$14) | AC40: =Hedge_Total!G180 | AD40: =IF(B40>$K$15,-1*$J$15,(($K$15-B40)*$I$15)-$J$15) | AE40: =Hedge_Total!G210 | AF40: =IF(B40>$K$16,-1*$J$16,(($K$16-B40)*$I$16)-$J$16) | AG40: =Hedge_Total!G240 | AH40: =IF(B40>$K$17,-1*$J$17,(($K$17-B40)*$I$17)-$J$17) | AI40: =Hedge_Total!G270 | AJ40: =IF(B40>$K$18,-1*$J$18,(($K$18-B40)*$I$18)-$J$18) | AK40: =Hedge_Total!G300 | AL40: =IF(B40>$K$19,-1*$J$19,(($K$19-B40)*$I$19)-$J$19) | AM40: =Hedge_Total!G330 | AN40: =IF(B40>$K$20,-1*$J$20,(($K$20-B40)*$I$20)-$J$20) | AO40: =Hedge_Total!G360 | AP40: =IF(B40>$K$21,-1*$J$21,(($K$21-B40)*$I$21)-$J$21) | AQ40: =Hedge_Total!G390 | AR40: =IF(B40>$K$22,-1*$J$22,(($K$22-B40)*$I$22)-$J$22) | AS40: =Hedge_Total!G420 | AT40: =IF(B40>$K$23,-1*$J$23,(($K$23-B40)*$I$23)-$J$23)
... B53: =B52-1 | C53: =J53/$C$16 | D53: =K53/$C$16 | E53: =($C$10*B53)-$F$10 | F53: =(E53/$F$10) | H53: =H52-1 | I53: =Hedge_Total!C463 | J53: =Hedge_Total!G463 | K53: =T53+V53+X53+Z53+AB53+AD53+AF53+AH53+AJ53+AL53+AN53+AP53+AR53+AT53 | L53: =N53/$F$10 | M53: =O53/$F$10 | N53: =E53+J53 | O53: =E53+K53 | P53: =J54-2*J53+J52 | R53: =R52-1 | S53: =Hedge_Total!G46 | T53: =IF(B53>$K$10,-1*$J$10,(($K$10-B53)*$I$10)-$J$10) | U53: =Hedge_Total!G75 | V53: =IF(B53>$K$11,-1*$J$11,(($K$11-B53)*$I$11)-$J$11) | W53: =Hedge_Total!G104 | X53: =IF(B53>$K$12,-1*$J$12,(($K$12-B53)*$I$12)-$J$12) | Y53: =Hedge_Total!G133 | Z53: =IF(B53>$K$13,-1*$J$13,(($K$13-B53)*$I$13)-$J$13) | AA53: =Hedge_Total!G163 | AB53: =IF(B53>$K$14,-1*$J$14,(($K$14-B53)*$I$14)-$J$14) | AC53: =Hedge_Total!G193 | AD53: =IF(B53>$K$15,-1*$J$15,(($K$15-B53)*$I$15)-$J$15) | AE53: =Hedge_Total!G223 | AF53: =IF(B53>$K$16,-1*$J$16,(($K$16-B53)*$I$16)-$J$16) | AG53: =Hedge_Total!G253 | AH53: =IF(B53>$K$17,-1*$J$17,(($K$17-B53)*$I$17)-$J$17) | AI53: =Hedge_Total!G283 | AJ53: =IF(B53>$K$18,-1*$J$18,(($K$18-B53)*$I$18)-$J$18) | AK53: =Hedge_Total!G313 | AL53: =IF(B53>$K$19,-1*$J$19,(($K$19-B53)*$I$19)-$J$19) | AM53: =Hedge_Total!G343 | AN53: =IF(B53>$K$20,-1*$J$20,(($K$20-B53)*$I$20)-$J$20) | AO53: =Hedge_Total!G373 | AP53: =IF(B53>$K$21,-1*$J$21,(($K$21-B53)*$I$21)-$J$21) | AQ53: =Hedge_Total!G403 | AR53: =IF(B53>$K$22,-1*$J$22,(($K$22-B53)*$I$22)-$J$22) | AS53: =Hedge_Total!G433 | AT53: =IF(B53>$K$23,-1*$J$23,(($K$23-B53)*$I$23)-$J$23)
B54: =B53-1 | C54: =J54/$C$16 | D54: =K54/$C$16 | E54: =($C$10*B54)-$F$10 | F54: =(E54/$F$10) | H54: =H53-1 | I54: =Hedge_Total!C464 | J54: =Hedge_Total!G464 | K54: =T54+V54+X54+Z54+AB54+AD54+AF54+AH54+AJ54+AL54+AN54+AP54+AR54+AT54 | L54: =N54/$F$10 | M54: =O54/$F$10 | N54: =E54+J54 | O54: =E54+K54 | R54: =R53-1 | S54: =Hedge_Total!G47 | T54: =IF(B54>$K$10,-1*$J$10,(($K$10-B54)*$I$10)-$J$10) | U54: =Hedge_Total!G76 | V54: =IF(B54>$K$11,-1*$J$11,(($K$11-B54)*$I$11)-$J$11) | W54: =Hedge_Total!G105 | X54: =IF(B54>$K$12,-1*$J$12,(($K$12-B54)*$I$12)-$J$12) | Y54: =Hedge_Total!G134 | Z54: =IF(B54>$K$13,-1*$J$13,(($K$13-B54)*$I$13)-$J$13) | AA54: =Hedge_Total!G164 | AB54: =IF(B54>$K$14,-1*$J$14,(($K$14-B54)*$I$14)-$J$14) | AC54: =Hedge_Total!G194 | AD54: =IF(B54>$K$15,-1*$J$15,(($K$15-B54)*$I$15)-$J$15) | AE54: =Hedge_Total!G224 | AF54: =IF(B54>$K$16,-1*$J$16,(($K$16-B54)*$I$16)-$J$16) | AG54: =Hedge_Total!G254 | AH54: =IF(B54>$K$17,-1*$J$17,(($K$17-B54)*$I$17)-$J$17) | AI54: =Hedge_Total!G284 | AJ54: =IF(B54>$K$18,-1*$J$18,(($K$18-B54)*$I$18)-$J$18) | AK54: =Hedge_Total!G314 | AL54: =IF(B54>$K$19,-1*$J$19,(($K$19-B54)*$I$19)-$J$19) | AM54: =Hedge_Total!G344 | AN54: =IF(B54>$K$20,-1*$J$20,(($K$20-B54)*$I$20)-$J$20) | AO54: =Hedge_Total!G374 | AP54: =IF(B54>$K$21,-1*$J$21,(($K$21-B54)*$I$21)-$J$21) | AQ54: =Hedge_Total!G404 | AR54: =IF(B54>$K$22,-1*$J$22,(($K$22-B54)*$I$22)-$J$22) | AS54: =Hedge_Total!G434 | AT54: =IF(B54>$K$23,-1*$J$23,(($K$23-B54)*$I$23)-$J$23)

Sheet Hedge_Far
A1: symbol | B1: strike | C1: delta | D1: gamma | E1: vega | F1: theta | G1: mark_price | H1: iv | I1: dte | J1: T | K1: type | L1: spot_price | M1: hedge_cost_per_day | N1: total_price | O1: position | P1: contracts | R1: Start | S1: Current
A2: =Far_laeyr!B20 | B2: =VLOOKUP(A2,OptionBoard!$A$2:$M$86,2,FALSE()) | C2: =VLOOKUP(A2,OptionBoard!$A$2:$M$86,3,0) | D2: =VLOOKUP(A2,OptionBoard!$A$2:$M$86,4,0) | E2: =VLOOKUP(A2,OptionBoard!$A$2:$M$86,5,0) | F2: =VLOOKUP(A2,OptionBoard!$A$2:$M$86,6,0) | G2: =VLOOKUP(A2,Far_laeyr!$B$9:$H$16,7,0) | H2: =VLOOKUP(A2,OptionBoard!$A$2:$M$86,8,0) | I2: =VLOOKUP(A2,OptionBoard!$A$2:$M$86,9,0) | J2: =VLOOKUP(A2,OptionBoard!$A$2:$M$86,10,0) | K2: =VLOOKUP(A2,OptionBoard!$A$2:$M$86,11,FALSE()) | L2: =VLOOKUP(A2,OptionBoard!$A$2:$M$86,12,0) | M2: =VLOOKUP(A2,OptionBoard!$A$2:$M$86,13,0) | N2: =G2*P2 | O2: buy | P2: =Far_laeyr!G20 | R2: =G2 | S2: =VLOOKUP(A2,OptionBoard!$A$2:$G$93,7,FALSE()) | U2: =R2-S2
A3: =Far_laeyr!B21 | B3: =VLOOKUP(A3,OptionBoard!$A$2:$M$86,2,FALSE()) | C3: =VLOOKUP(A3,OptionBoard!$A$2:$M$86,3,0) | D3: =VLOOKUP(A3,OptionBoard!$A$2:$M$86,4,0) | E3: =VLOOKUP(A3,OptionBoard!$A$2:$M$86,5,0) | F3: =VLOOKUP(A3,OptionBoard!$A$2:$M$86,6,0) | G3: =VLOOKUP(A3,Far_laeyr!$B$9:$H$16,7,0) | H3: =VLOOKUP(A3,OptionBoard!$A$2:$M$86,8,0) | I3: =VLOOKUP(A3,OptionBoard!$A$2:$M$86,9,0) | J3: =VLOOKUP(A3,OptionBoard!$A$2:$M$86,10,0) | K3: =VLOOKUP(A3,OptionBoard!$A$2:$M$86,11,FALSE()) | L3: =VLOOKUP(A3,OptionBoard!$A$2:$M$86,12,0) | M3: =VLOOKUP(A3,OptionBoard!$A$2:$M$86,13,0) | N3: =G3*P3 | O3: buy | P3: =Far_laeyr!G21 | R3: =G3 | S3: =VLOOKUP(A3,OptionBoard!$A$2:$G$93,7,FALSE()) | U3: =R3-S3
A4: =Far_laeyr!B22 | B4: =VLOOKUP(A4,OptionBoard!$A$2:$M$86,2,FALSE()) | C4: =VLOOKUP(A4,OptionBoard!$A$2:$M$86,3,0) | D4: =VLOOKUP(A4,OptionBoard!$A$2:$M$86,4,0) | E4: =VLOOKUP(A4,OptionBoard!$A$2:$M$86,5,0) | F4: =VLOOKUP(A4,OptionBoard!$A$2:$M$86,6,0) | G4: =VLOOKUP(A4,Far_laeyr!$B$9:$H$16,7,0) | H4: =VLOOKUP(A4,OptionBoard!$A$2:$M$86,8,0) | I4: =VLOOKUP(A4,OptionBoard!$A$2:$M$86,9,0) | J4: =VLOOKUP(A4,OptionBoard!$A$2:$M$86,10,0) | K4: =VLOOKUP(A4,OptionBoard!$A$2:$M$86,11,FALSE()) | L4: =VLOOKUP(A4,OptionBoard!$A$2:$M$86,12,0) | M4: =VLOOKUP(A4,OptionBoard!$A$2:$M$86,13,0) | N4: =G4*P4 | O4: buy | P4: =Far_laeyr!G22 | R4: 1.4 | S4: =VLOOKUP(A4,OptionBoard!$A$2:$G$93,7,FALSE()) | U4: =R4-S4
A5: =Far_laeyr!B23 | B5: =VLOOKUP(A5,OptionBoard!$A$2:$M$86,2,FALSE()) | C5: =VLOOKUP(A5,OptionBoard!$A$2:$M$86,3,0) | D5: =VLOOKUP(A5,OptionBoard!$A$2:$M$86,4,0) | E5: =VLOOKUP(A5,OptionBoard!$A$2:$M$86,5,0) | F5: =VLOOKUP(A5,OptionBoard!$A$2:$M$86,6,0) | G5: =VLOOKUP(A5,Far_laeyr!$B$9:$H$16,7,0) | H5: =VLOOKUP(A5,OptionBoard!$A$2:$M$86,8,0) | I5: =VLOOKUP(A5,OptionBoard!$A$2:$M$86,9,0) | J5: =VLOOKUP(A5,OptionBoard!$A$2:$M$86,10,0) | K5: =VLOOKUP(A5,OptionBoard!$A$2:$M$86,11,FALSE()) | L5: =VLOOKUP(A5,OptionBoard!$A$2:$M$86,12,0) | M5: =VLOOKUP(A5,OptionBoard!$A$2:$M$86,13,0) | N5: =G5*P5 | O5: buy | P5: =Far_laeyr!G23 | R5: =G5 | S5: =VLOOKUP(A5,OptionBoard!$A$2:$G$93,7,FALSE()) | U5: =R5-S5
A6: =Far_laeyr!B24 | B6: =VLOOKUP(A6,OptionBoard!$A$2:$M$86,2,FALSE()) | C6: =VLOOKUP(A6,OptionBoard!$A$2:$M$86,3,0) | D6: =VLOOKUP(A6,OptionBoard!$A$2:$M$86,4,0) | E6: =VLOOKUP(A6,OptionBoard!$A$2:$M$86,5,0) | F6: =VLOOKUP(A6,OptionBoard!$A$2:$M$86,6,0) | G6: =VLOOKUP(A6,Far_laeyr!$B$9:$H$16,7,0) | H6: =VLOOKUP(A6,OptionBoard!$A$2:$M$86,8,0) | I6: =VLOOKUP(A6,OptionBoard!$A$2:$M$86,9,0) | J6: =VLOOKUP(A6,OptionBoard!$A$2:$M$86,10,0) | K6: =VLOOKUP(A6,OptionBoard!$A$2:$M$86,11,FALSE()) | L6: =VLOOKUP(A6,OptionBoard!$A$2:$M$86,12,0) | M6: =VLOOKUP(A6,OptionBoard!$A$2:$M$86,13,0) | N6: =G6*P6 | O6: buy | P6: =Far_laeyr!G24 | R6: =G6 | S6: =VLOOKUP(A6,OptionBoard!$A$2:$G$93,7,FALSE()) | U6: =R6-S6
A7: =Far_laeyr!B25 | B7: =VLOOKUP(A7,OptionBoard!$A$2:$M$86,2,FALSE()) | C7: =VLOOKUP(A7,OptionBoard!$A$2:$M$86,3,0) | D7: =VLOOKUP(A7,OptionBoard!$A$2:$M$86,4,0) | E7: =VLOOKUP(A7,OptionBoard!$A$2:$M$86,5,0) | F7: =VLOOKUP(A7,OptionBoard!$A$2:$M$86,6,0) | G7: =VLOOKUP(A7,Far_laeyr!$B$9:$H$16,7,0) | H7: =VLOOKUP(A7,OptionBoard!$A$2:$M$86,8,0) | I7: =VLOOKUP(A7,OptionBoard!$A$2:$M$86,9,0) | J7: =VLOOKUP(A7,OptionBoard!$A$2:$M$86,10,0) | K7: =VLOOKUP(A7,OptionBoard!$A$2:$M$86,11,FALSE()) | L7: =VLOOKUP(A7,OptionBoard!$A$2:$M$86,12,0) | M7: =VLOOKUP(A7,OptionBoard!$A$2:$M$86,13,0) | N7: =G7*P7 | O7: buy | P7: =Far_laeyr!G25 | R7: =G7 | S7: =VLOOKUP(A7,OptionBoard!$A$2:$G$93,7,FALSE()) | U7: =R7-S7
A8: =Far_laeyr!B26 | B8: =VLOOKUP(A8,OptionBoard!$A$2:$M$86,2,FALSE()) | C8: =VLOOKUP(A8,OptionBoard!$A$2:$M$86,3,0) | D8: =VLOOKUP(A8,OptionBoard!$A$2:$M$86,4,0) | E8: =VLOOKUP(A8,OptionBoard!$A$2:$M$86,5,0) | F8: =VLOOKUP(A8,OptionBoard!$A$2:$M$86,6,0) | G8: =VLOOKUP(A8,Far_laeyr!$B$9:$H$16,7,0) | H8: =VLOOKUP(A8,OptionBoard!$A$2:$M$86,8,0) | I8: =VLOOKUP(A8,OptionBoard!$A$2:$M$86,9,0) | J8: =VLOOKUP(A8,OptionBoard!$A$2:$M$86,10,0) | K8: =VLOOKUP(A8,OptionBoard!$A$2:$M$86,11,FALSE()) | L8: =VLOOKUP(A8,OptionBoard!$A$2:$M$86,12,0) | M8: =VLOOKUP(A8,OptionBoard!$A$2:$M$86,13,0) | N8: =G8*P8 | O8: buy | P8: =Far_laeyr!G26 | S8: =VLOOKUP(A8,OptionBoard!$A$2:$G$93,7,FALSE()) | U8: =R8-S8
A9: =Far_laeyr!B27 | B9: =VLOOKUP(A9,OptionBoard!$A$2:$M$86,2,FALSE()) | C9: =VLOOKUP(A9,OptionBoard!$A$2:$M$86,3,0) | D9: =VLOOKUP(A9,OptionBoard!$A$2:$M$86,4,0) | E9: =VLOOKUP(A9,OptionBoard!$A$2:$M$86,5,0) | F9: =VLOOKUP(A9,OptionBoard!$A$2:$M$86,6,0) | G9: =VLOOKUP(A9,Far_laeyr!$B$9:$H$16,7,0) | H9: =VLOOKUP(A9,OptionBoard!$A$2:$M$86,8,0) | I9: =VLOOKUP(A9,OptionBoard!$A$2:$M$86,9,0) | J9: =VLOOKUP(A9,OptionBoard!$A$2:$M$86,10,0) | K9: =VLOOKUP(A9,OptionBoard!$A$2:$M$86,11,FALSE()) | L9: =VLOOKUP(A9,OptionBoard!$A$2:$M$86,12,0) | M9: =VLOOKUP(A9,OptionBoard!$A$2:$M$86,13,0) | N9: =G9*P9 | O9: buy | P9: =Far_laeyr!G27 | S9: =VLOOKUP(A9,OptionBoard!$A$2:$G$93,7,FALSE()) | U9: =R9-S9
A10: =Far_laeyr!B28 | B10: =VLOOKUP(A10,OptionBoard!$A$2:$M$86,2,FALSE()) | C10: =VLOOKUP(A10,OptionBoard!$A$2:$M$86,3,0) | D10: =VLOOKUP(A10,OptionBoard!$A$2:$M$86,4,0) | E10: =VLOOKUP(A10,OptionBoard!$A$2:$M$86,5,0) | F10: =VLOOKUP(A10,OptionBoard!$A$2:$M$86,6,0) | G10: =VLOOKUP(A10,Far_laeyr!$B$9:$H$16,7,0) | H10: =VLOOKUP(A10,OptionBoard!$A$2:$M$86,8,0) | I10: =VLOOKUP(A10,OptionBoard!$A$2:$M$86,9,0) | J10: =VLOOKUP(A10,OptionBoard!$A$2:$M$86,10,0) | K10: =VLOOKUP(A10,OptionBoard!$A$2:$M$86,11,FALSE()) | L10: =VLOOKUP(A10,OptionBoard!$A$2:$M$86,12,0) | M10: =VLOOKUP(A10,OptionBoard!$A$2:$M$86,13,0) | N10: =G10*P10 | O10: buy | P10: =Far_laeyr!G28 | S10: =VLOOKUP(A10,OptionBoard!$A$2:$G$93,7,FALSE()) | U10: =R10-S10
A11: =Far_laeyr!B29 | B11: =VLOOKUP(A11,OptionBoard!$A$2:$M$86,2,FALSE()) | C11: =VLOOKUP(A11,OptionBoard!$A$2:$M$86,3,0) | D11: =VLOOKUP(A11,OptionBoard!$A$2:$M$86,4,0) | E11: =VLOOKUP(A11,OptionBoard!$A$2:$M$86,5,0) | F11: =VLOOKUP(A11,OptionBoard!$A$2:$M$86,6,0) | G11: =VLOOKUP(A11,Far_laeyr!$B$9:$H$16,7,0) | H11: =VLOOKUP(A11,OptionBoard!$A$2:$M$86,8,0) | I11: =VLOOKUP(A11,OptionBoard!$A$2:$M$86,9,0) | J11: =VLOOKUP(A11,OptionBoard!$A$2:$M$86,10,0) | K11: =VLOOKUP(A11,OptionBoard!$A$2:$M$86,11,FALSE()) | L11: =VLOOKUP(A11,OptionBoard!$A$2:$M$86,12,0) | M11: =VLOOKUP(A11,OptionBoard!$A$2:$M$86,13,0) | N11: =G11*P11 | O11: buy | P11: =Far_laeyr!G29 | S11: =VLOOKUP(A11,OptionBoard!$A$2:$G$93,7,FALSE()) | U11: =R11-S11
A14: Now_Greeks | C14: =(IF($O$2="buy",1,-1) * C2 * P2)+(IF($O$3="buy",1,-1) * C3 * P3)+(IF($O$4="buy",1,-1) * C4 * P4)+(IF($O$5="buy",1,-1) * C5 * P5)+(IF($O$6="buy",1,-1) * C6 * P6)+(IF($O$7="buy",1,-1) * C7 * P7)+(IF($O$8="buy",1,-1) * C8 * P8)+(IF($O$9="buy",1,-1) * C9 * P9)+(IF($O$10="buy",1,-1) * C10 * P10)+(IF($O$11="buy",1,-1) * C11 * P11) | D14: =(IF($O$2="buy",1,-1) * D2 * P2)+(IF($O$3="buy",1,-1) * D3 * P3)+(IF($O$4="buy",1,-1) * D4 * P4)+(IF($O$5="buy",1,-1) * D5 * P5)+(IF($O$6="buy",1,-1) * D6 * P6)+(IF($O$7="buy",1,-1) * D7 * P7)+(IF($O$8="buy",1,-1) * D8 * P8)+(IF($O$9="buy",1,-1) * D9 * P9)+(IF($O$10="buy",1,-1) * D10 * P10)+(IF($O$11="buy",1,-1) * D11 * P11) | E14: =(IF($O$2="buy",1,-1) * E2 * P2)+(IF($O$3="buy",1,-1) * E3 * P3)+(IF($O$4="buy",1,-1) * E4 * P4)+(IF($O$5="buy",1,-1) * E5 * P5)+(IF($O$6="buy",1,-1) * E6 * P6)+(IF($O$7="buy",1,-1) * E7 * P7)+(IF($O$8="buy",1,-1) * E8 * P8)+(IF($O$9="buy",1,-1) * E9 * P9)+(IF($O$10="buy",1,-1) * E10 * P10)+(IF($O$11="buy",1,-1) * E11 * P11) | F14: =(IF($O$2="buy",1,-1) * F2 * P2)+(IF($O$3="buy",1,-1) * F3 * P3)+(IF($O$4="buy",1,-1) * F4 * P4)+(IF($O$5="buy",1,-1) * F5 * P5)+(IF($O$6="buy",1,-1) * F6 * P6)+(IF($O$7="buy",1,-1) * F7 * P7)+(IF($O$8="buy",1,-1) * F8 * P8)+(IF($O$9="buy",1,-1) * F9 * P9)+(IF($O$10="buy",1,-1) * F10 * P10)+(IF($O$11="buy",1,-1) * F11 * P11) | G14: =(IF($O$2="buy",1,-1) * G2 * P2)+(IF($O$3="buy",1,-1) * G3 * P3)+(IF($O$4="buy",1,-1) * G4 * P4)+(IF($O$5="buy",1,-1) * G5 * P5)+(IF($O$6="buy",1,-1) * G6 * P6)+(IF($O$7="buy",1,-1) * G7 * P7)+(IF($O$8="buy",1,-1) * G8 * P8)+(IF($O$9="buy",1,-1) * G9 * P9)+(IF($O$10="buy",1,-1) * G10 * P10)+(IF($O$11="buy",1,-1) * G11 * P11) | M14: =M2*P2+M3*P3+M5*P5+M4*P4+M6*P6+M7*P7+M8*P8+M9*P9+M10*P10 | S14: =F14/C14
A16: =A2 | C16: delta | D16: gamma | E16: vega | F16: theta | G16: mark_price | I16: d1 | J16: d2
B17: =Portfolio!B28 | C17: =IF($O$2="sell",-1,1) * IF($K$2="call", NORMDIST(I17,0,1,1), NORMDIST(I17,0,1,1)-1 ) * $P$2 | D17: =IF($O$2="sell",-1,1) * NORMDIST(I17,0,1,0)/(B17*$H$2*SQRT($J$2)) * $P$2 | E17: =IF($O$2="sell",-1,1) * (B17*NORMDIST(I17,0,1,0)*SQRT($J$2)/365) * $P$2 | F17: =IF($O$2="sell",-1,1) * (-(B17*NORMDIST(I17,0,1,0)*$H$2)/(2*SQRT($J$2))/365) *$P$2 | G17: =IF($O$2="buy",1,-1)*( IF($K$2="call",B17*NORMDIST(I17,0,1,1) - $B$2*NORMDIST(J17,0,1,1),$B$2*NORMDIST(-J17,0,1,1) - B17*NORMDIST(-I17,0,1,1) ) - $G$2) * $P$2 | I17: =(LN(B17/$B$2)+($H$2^2/2)*($J$2))/($H$2*SQRT($J$2)) | J17: =I17 - $H$2*SQRT($J$2)
B18: =Portfolio!B29 | C18: =IF($O$2="sell",-1,1) * IF($K$2="call", NORMDIST(I18,0,1,1), NORMDIST(I18,0,1,1)-1 ) * $P$2 | D18: =IF($O$2="sell",-1,1) * NORMDIST(I18,0,1,0)/(B18*$H$2*SQRT($J$2)) * $P$2 | E18: =IF($O$2="sell",-1,1) * (B18*NORMDIST(I18,0,1,0)*SQRT($J$2)/365) * $P$2 | F18: =IF($O$2="sell",-1,1) * (-(B18*NORMDIST(I18,0,1,0)*$H$2)/(2*SQRT($J$2))/365) *$P$2 | G18: =IF($O$2="buy",1,-1)*( IF($K$2="call",B18*NORMDIST(I18,0,1,1) - $B$2*NORMDIST(J18,0,1,1),$B$2*NORMDIST(-J18,0,1,1) - B18*NORMDIST(-I18,0,1,1) ) - $G$2) * $P$2 | I18: =(LN(B18/$B$2)+($H$2^2/2)*($J$2))/($H$2*SQRT($J$2)) | J18: =I18 - $H$2*SQRT($J$2)
B19: =Portfolio!B30 | C19: =IF($O$2="sell",-1,1) * IF($K$2="call", NORMDIST(I19,0,1,1), NORMDIST(I19,0,1,1)-1 ) * $P$2 | D19: =IF($O$2="sell",-1,1) * NORMDIST(I19,0,1,0)/(B19*$H$2*SQRT($J$2)) * $P$2 | E19: =IF($O$2="sell",-1,1) * (B19*NORMDIST(I19,0,1,0)*SQRT($J$2)/365) * $P$2 | F19: =IF($O$2="sell",-1,1) * (-(B19*NORMDIST(I19,0,1,0)*$H$2)/(2*SQRT($J$2))/365) *$P$2 | G19: =IF($O$2="buy",1,-1)*( IF($K$2="call",B19*NORMDIST(I19,0,1,1) - $B$2*NORMDIST(J19,0,1,1),$B$2*NORMDIST(-J19,0,1,1) - B19*NORMDIST(-I19,0,1,1) ) - $G$2) * $P$2 | I19: =(LN(B19/$B$2)+($H$2^2/2)*($J$2))/($H$2*SQRT($J$2)) | J19: =I19 - $H$2*SQRT($J$2)
B20: =Portfolio!B31 | C20: =IF($O$2="sell",-1,1) * IF($K$2="call", NORMDIST(I20,0,1,1), NORMDIST(I20,0,1,1)-1 ) * $P$2 | D20: =IF($O$2="sell",-1,1) * NORMDIST(I20,0,1,0)/(B20*$H$2*SQRT($J$2)) * $P$2 | E20: =IF($O$2="sell",-1,1) * (B20*NORMDIST(I20,0,1,0)*SQRT($J$2)/365) * $P$2 | F20: =IF($O$2="sell",-1,1) * (-(B20*NORMDIST(I20,0,1,0)*$H$2)/(2*SQRT($J$2))/365) *$P$2 | G20: =IF($O$2="buy",1,-1)*( IF($K$2="call",B20*NORMDIST(I20,0,1,1) - $B$2*NORMDIST(J20,0,1,1),$B$2*NORMDIST(-J20,0,1,1) - B20*NORMDIST(-I20,0,1,1) ) - $G$2) * $P$2 | I20: =(LN(B20/$B$2)+($H$2^2/2)*($J$2))/($H$2*SQRT($J$2)) | J20: =I20 - $H$2*SQRT($J$2)
B21: =Portfolio!B32 | C21: =IF($O$2="sell",-1,1) * IF($K$2="call", NORMDIST(I21,0,1,1), NORMDIST(I21,0,1,1)-1 ) * $P$2 | D21: =IF($O$2="sell",-1,1) * NORMDIST(I21,0,1,0)/(B21*$H$2*SQRT($J$2)) * $P$2 | E21: =IF($O$2="sell",-1,1) * (B21*NORMDIST(I21,0,1,0)*SQRT($J$2)/365) * $P$2 | F21: =IF($O$2="sell",-1,1) * (-(B21*NORMDIST(I21,0,1,0)*$H$2)/(2*SQRT($J$2))/365) *$P$2 | G21: =IF($O$2="buy",1,-1)*( IF($K$2="call",B21*NORMDIST(I21,0,1,1) - $B$2*NORMDIST(J21,0,1,1),$B$2*NORMDIST(-J21,0,1,1) - B21*NORMDIST(-I21,0,1,1) ) - $G$2) * $P$2 | I21: =(LN(B21/$B$2)+($H$2^2/2)*($J$2))/($H$2*SQRT($J$2)) | J21: =I21 - $H$2*SQRT($J$2)
B22: =Portfolio!B33 | C22: =IF($O$2="sell",-1,1) * IF($K$2="call", NORMDIST(I22,0,1,1), NORMDIST(I22,0,1,1)-1 ) * $P$2 | D22: =IF($O$2="sell",-1,1) * NORMDIST(I22,0,1,0)/(B22*$H$2*SQRT($J$2)) * $P$2 | E22: =IF($O$2="sell",-1,1) * (B22*NORMDIST(I22,0,1,0)*SQRT($J$2)/365) * $P$2 | F22: =IF($O$2="sell",-1,1) * (-(B22*NORMDIST(I22,0,1,0)*$H$2)/(2*SQRT($J$2))/365) *$P$2 | G22: =IF($O$2="buy",1,-1)*( IF($K$2="call",B22*NORMDIST(I22,0,1,1) - $B$2*NORMDIST(J22,0,1,1),$B$2*NORMDIST(-J22,0,1,1) - B22*NORMDIST(-I22,0,1,1) ) - $G$2) * $P$2 | I22: =(LN(B22/$B$2)+($H$2^2/2)*($J$2))/($H$2*SQRT($J$2)) | J22: =I22 - $H$2*SQRT($J$2)
B23: =Portfolio!B34 | C23: =IF($O$2="sell",-1,1) * IF($K$2="call", NORMDIST(I23,0,1,1), NORMDIST(I23,0,1,1)-1 ) * $P$2 | D23: =IF($O$2="sell",-1,1) * NORMDIST(I23,0,1,0)/(B23*$H$2*SQRT($J$2)) * $P$2 | E23: =IF($O$2="sell",-1,1) * (B23*NORMDIST(I23,0,1,0)*SQRT($J$2)/365) * $P$2 | F23: =IF($O$2="sell",-1,1) * (-(B23*NORMDIST(I23,0,1,0)*$H$2)/(2*SQRT($J$2))/365) *$P$2 | G23: =IF($O$2="buy",1,-1)*( IF($K$2="call",B23*NORMDIST(I23,0,1,1) - $B$2*NORMDIST(J23,0,1,1),$B$2*NORMDIST(-J23,0,1,1) - B23*NORMDIST(-I23,0,1,1) ) - $G$2) * $P$2 | I23: =(LN(B23/$B$2)+($H$2^2/2)*($J$2))/($H$2*SQRT($J$2)) | J23: =I23 - $H$2*SQRT($J$2)
B24: =Portfolio!B35 | C24: =IF($O$2="sell",-1,1) * IF($K$2="call", NORMDIST(I24,0,1,1), NORMDIST(I24,0,1,1)-1 ) * $P$2 | D24: =IF($O$2="sell",-1,1) * NORMDIST(I24,0,1,0)/(B24*$H$2*SQRT($J$2)) * $P$2 | E24: =IF($O$2="sell",-1,1) * (B24*NORMDIST(I24,0,1,0)*SQRT($J$2)/365) * $P$2 | F24: =IF($O$2="sell",-1,1) * (-(B24*NORMDIST(I24,0,1,0)*$H$2)/(2*SQRT($J$2))/365) *$P$2 | G24: =IF($O$2="buy",1,-1)*( IF($K$2="call",B24*NORMDIST(I24,0,1,1) - $B$2*NORMDIST(J24,0,1,1),$B$2*NORMDIST(-J24,0,1,1) - B24*NORMDIST(-I24,0,1,1) ) - $G$2) * $P$2 | I24: =(LN(B24/$B$2)+($H$2^2/2)*($J$2))/($H$2*SQRT($J$2)) | J24: =I24 - $H$2*SQRT($J$2)
B25: =Portfolio!B36 | C25: =IF($O$2="sell",-1,1) * IF($K$2="call", NORMDIST(I25,0,1,1), NORMDIST(I25,0,1,1)-1 ) * $P$2 | D25: =IF($O$2="sell",-1,1) * NORMDIST(I25,0,1,0)/(B25*$H$2*SQRT($J$2)) * $P$2 | E25: =IF($O$2="sell",-1,1) * (B25*NORMDIST(I25,0,1,0)*SQRT($J$2)/365) * $P$2 | F25: =IF($O$2="sell",-1,1) * (-(B25*NORMDIST(I25,0,1,0)*$H$2)/(2*SQRT($J$2))/365) *$P$2 | G25: =IF($O$2="buy",1,-1)*( IF($K$2="call",B25*NORMDIST(I25,0,1,1) - $B$2*NORMDIST(J25,0,1,1),$B$2*NORMDIST(-J25,0,1,1) - B25*NORMDIST(-I25,0,1,1) ) - $G$2) * $P$2 | I25: =(LN(B25/$B$2)+($H$2^2/2)*($J$2))/($H$2*SQRT($J$2)) | J25: =I25 - $H$2*SQRT($J$2)
B26: =Portfolio!B37 | C26: =IF($O$2="sell",-1,1) * IF($K$2="call", NORMDIST(I26,0,1,1), NORMDIST(I26,0,1,1)-1 ) * $P$2 | D26: =IF($O$2="sell",-1,1) * NORMDIST(I26,0,1,0)/(B26*$H$2*SQRT($J$2)) * $P$2 | E26: =IF($O$2="sell",-1,1) * (B26*NORMDIST(I26,0,1,0)*SQRT($J$2)/365) * $P$2 | F26: =IF($O$2="sell",-1,1) * (-(B26*NORMDIST(I26,0,1,0)*$H$2)/(2*SQRT($J$2))/365) *$P$2 | G26: =IF($O$2="buy",1,-1)*( IF($K$2="call",B26*NORMDIST(I26,0,1,1) - $B$2*NORMDIST(J26,0,1,1),$B$2*NORMDIST(-J26,0,1,1) - B26*NORMDIST(-I26,0,1,1) ) - $G$2) * $P$2 | I26: =(LN(B26/$B$2)+($H$2^2/2)*($J$2))/($H$2*SQRT($J$2)) | J26: =I26 - $H$2*SQRT($J$2)
B27: =Portfolio!B38 | C27: =IF($O$2="sell",-1,1) * IF($K$2="call", NORMDIST(I27,0,1,1), NORMDIST(I27,0,1,1)-1 ) * $P$2 | D27: =IF($O$2="sell",-1,1) * NORMDIST(I27,0,1,0)/(B27*$H$2*SQRT($J$2)) * $P$2 | E27: =IF($O$2="sell",-1,1) * (B27*NORMDIST(I27,0,1,0)*SQRT($J$2)/365) * $P$2 | F27: =IF($O$2="sell",-1,1) * (-(B27*NORMDIST(I27,0,1,0)*$H$2)/(2*SQRT($J$2))/365) *$P$2 | G27: =IF($O$2="buy",1,-1)*( IF($K$2="call",B27*NORMDIST(I27,0,1,1) - $B$2*NORMDIST(J27,0,1,1),$B$2*NORMDIST(-J27,0,1,1) - B27*NORMDIST(-I27,0,1,1) ) - $G$2) * $P$2 | I27: =(LN(B27/$B$2)+($H$2^2/2)*($J$2))/($H$2*SQRT($J$2)) | J27: =I27 - $H$2*SQRT($J$2)
B28: =Portfolio!B39 | C28: =IF($O$2="sell",-1,1) * IF($K$2="call", NORMDIST(I28,0,1,1), NORMDIST(I28,0,1,1)-1 ) * $P$2 | D28: =IF($O$2="sell",-1,1) * NORMDIST(I28,0,1,0)/(B28*$H$2*SQRT($J$2)) * $P$2 | E28: =IF($O$2="sell",-1,1) * (B28*NORMDIST(I28,0,1,0)*SQRT($J$2)/365) * $P$2 | F28: =IF($O$2="sell",-1,1) * (-(B28*NORMDIST(I28,0,1,0)*$H$2)/(2*SQRT($J$2))/365) *$P$2 | G28: =IF($O$2="buy",1,-1)*( IF($K$2="call",B28*NORMDIST(I28,0,1,1) - $B$2*NORMDIST(J28,0,1,1),$B$2*NORMDIST(-J28,0,1,1) - B28*NORMDIST(-I28,0,1,1) ) - $G$2) * $P$2 | I28: =(LN(B28/$B$2)+($H$2^2/2)*($J$2))/($H$2*SQRT($J$2)) | J28: =I28 - $H$2*SQRT($J$2)
... B43: =Portfolio!B54 | C43: =IF($O$2="sell",-1,1) * IF($K$2="call", NORMDIST(I43,0,1,1), NORMDIST(I43,0,1,1)-1 ) * $P$2 | D43: =IF($O$2="sell",-1,1) * NORMDIST(I43,0,1,0)/(B43*$H$2*SQRT($J$2)) * $P$2 | E43: =IF($O$2="sell",-1,1) * (B43*NORMDIST(I43,0,1,0)*SQRT($J$2)/365) * $P$2 | F43: =IF($O$2="sell",-1,1) * (-(B43*NORMDIST(I43,0,1,0)*$H$2)/(2*SQRT($J$2))/365) *$P$2 | G43: =IF($O$2="buy",1,-1)*( IF($K$2="call",B43*NORMDIST(I43,0,1,1) - $B$2*NORMDIST(J43,0,1,1),$B$2*NORMDIST(-J43,0,1,1) - B43*NORMDIST(-I43,0,1,1) ) - $G$2) * $P$2 | I43: =(LN(B43/$B$2)+($H$2^2/2)*($J$2))/($H$2*SQRT($J$2)) | J43: =I43 - $H$2*SQRT($J$2)
A45: =A3 | C45: delta | D45: gamma | E45: vega | F45: theta | G45: mark_price | I45: d1 | J45: d2
B46: =B17 | C46: =IF($O$3="sell",-1,1) * IF($K$3="call", NORMDIST(I46,0,1,1), NORMDIST(I46,0,1,1)-1 ) * $P$3 | D46: =IF($O$3="sell",-1,1) * NORMDIST(I46,0,1,0)/(B46*$H$3*SQRT($J$3)) * $P$3 | E46: =IF($O$3="sell",-1,1) * (B46*NORMDIST(I46,0,1,0)*SQRT($J$3)/365) * $P$3 | F46: =IF($O$3="sell",-1,1) * (-(B46*NORMDIST(I46,0,1,0)*$H$3)/(2*SQRT($J$3))/365) *$P$3 | G46: =IF($O$3="buy",1,-1)*( IF($K$3="call",B46*NORMDIST(I46,0,1,1) - $B$3*NORMDIST(J46,0,1,1),$B$3*NORMDIST(-J46,0,1,1) - B46*NORMDIST(-I46,0,1,1) ) - $G$3) * $P$3 | I46: =(LN(B46/$B$3)+($H$3^2/2)*($J$3))/($H$3*SQRT($J$3)) | J46: =I46 - $H$3*SQRT($J$3)
B47: =B18 | C47: =IF($O$3="sell",-1,1) * IF($K$3="call", NORMDIST(I47,0,1,1), NORMDIST(I47,0,1,1)-1 ) * $P$3 | D47: =IF($O$3="sell",-1,1) * NORMDIST(I47,0,1,0)/(B47*$H$3*SQRT($J$3)) * $P$3 | E47: =IF($O$3="sell",-1,1) * (B47*NORMDIST(I47,0,1,0)*SQRT($J$3)/365) * $P$3 | F47: =IF($O$3="sell",-1,1) * (-(B47*NORMDIST(I47,0,1,0)*$H$3)/(2*SQRT($J$3))/365) *$P$3 | G47: =IF($O$3="buy",1,-1)*( IF($K$3="call",B47*NORMDIST(I47,0,1,1) - $B$3*NORMDIST(J47,0,1,1),$B$3*NORMDIST(-J47,0,1,1) - B47*NORMDIST(-I47,0,1,1) ) - $G$3) * $P$3 | I47: =(LN(B47/$B$3)+($H$3^2/2)*($J$3))/($H$3*SQRT($J$3)) | J47: =I47 - $H$3*SQRT($J$3)
B48: =B19 | C48: =IF($O$3="sell",-1,1) * IF($K$3="call", NORMDIST(I48,0,1,1), NORMDIST(I48,0,1,1)-1 ) * $P$3 | D48: =IF($O$3="sell",-1,1) * NORMDIST(I48,0,1,0)/(B48*$H$3*SQRT($J$3)) * $P$3 | E48: =IF($O$3="sell",-1,1) * (B48*NORMDIST(I48,0,1,0)*SQRT($J$3)/365) * $P$3 | F48: =IF($O$3="sell",-1,1) * (-(B48*NORMDIST(I48,0,1,0)*$H$3)/(2*SQRT($J$3))/365) *$P$3 | G48: =IF($O$3="buy",1,-1)*( IF($K$3="call",B48*NORMDIST(I48,0,1,1) - $B$3*NORMDIST(J48,0,1,1),$B$3*NORMDIST(-J48,0,1,1) - B48*NORMDIST(-I48,0,1,1) ) - $G$3) * $P$3 | I48: =(LN(B48/$B$3)+($H$3^2/2)*($J$3))/($H$3*SQRT($J$3)) | J48: =I48 - $H$3*SQRT($J$3)
B49: =B20 | C49: =IF($O$3="sell",-1,1) * IF($K$3="call", NORMDIST(I49,0,1,1), NORMDIST(I49,0,1,1)-1 ) * $P$3 | D49: =IF($O$3="sell",-1,1) * NORMDIST(I49,0,1,0)/(B49*$H$3*SQRT($J$3)) * $P$3 | E49: =IF($O$3="sell",-1,1) * (B49*NORMDIST(I49,0,1,0)*SQRT($J$3)/365) * $P$3 | F49: =IF($O$3="sell",-1,1) * (-(B49*NORMDIST(I49,0,1,0)*$H$3)/(2*SQRT($J$3))/365) *$P$3 | G49: =IF($O$3="buy",1,-1)*( IF($K$3="call",B49*NORMDIST(I49,0,1,1) - $B$3*NORMDIST(J49,0,1,1),$B$3*NORMDIST(-J49,0,1,1) - B49*NORMDIST(-I49,0,1,1) ) - $G$3) * $P$3 | I49: =(LN(B49/$B$3)+($H$3^2/2)*($J$3))/($H$3*SQRT($J$3)) | J49: =I49 - $H$3*SQRT($J$3)
B50: =B21 | C50: =IF($O$3="sell",-1,1) * IF($K$3="call", NORMDIST(I50,0,1,1), NORMDIST(I50,0,1,1)-1 ) * $P$3 | D50: =IF($O$3="sell",-1,1) * NORMDIST(I50,0,1,0)/(B50*$H$3*SQRT($J$3)) * $P$3 | E50: =IF($O$3="sell",-1,1) * (B50*NORMDIST(I50,0,1,0)*SQRT($J$3)/365) * $P$3 | F50: =IF($O$3="sell",-1,1) * (-(B50*NORMDIST(I50,0,1,0)*$H$3)/(2*SQRT($J$3))/365) *$P$3 | G50: =IF($O$3="buy",1,-1)*( IF($K$3="call",B50*NORMDIST(I50,0,1,1) - $B$3*NORMDIST(J50,0,1,1),$B$3*NORMDIST(-J50,0,1,1) - B50*NORMDIST(-I50,0,1,1) ) - $G$3) * $P$3 | I50: =(LN(B50/$B$3)+($H$3^2/2)*($J$3))/($H$3*SQRT($J$3)) | J50: =I50 - $H$3*SQRT($J$3)
B51: =B22 | C51: =IF($O$3="sell",-1,1) * IF($K$3="call", NORMDIST(I51,0,1,1), NORMDIST(I51,0,1,1)-1 ) * $P$3 | D51: =IF($O$3="sell",-1,1) * NORMDIST(I51,0,1,0)/(B51*$H$3*SQRT($J$3)) * $P$3 | E51: =IF($O$3="sell",-1,1) * (B51*NORMDIST(I51,0,1,0)*SQRT($J$3)/365) * $P$3 | F51: =IF($O$3="sell",-1,1) * (-(B51*NORMDIST(I51,0,1,0)*$H$3)/(2*SQRT($J$3))/365) *$P$3 | G51: =IF($O$3="buy",1,-1)*( IF($K$3="call",B51*NORMDIST(I51,0,1,1) - $B$3*NORMDIST(J51,0,1,1),$B$3*NORMDIST(-J51,0,1,1) - B51*NORMDIST(-I51,0,1,1) ) - $G$3) * $P$3 | I51: =(LN(B51/$B$3)+($H$3^2/2)*($J$3))/($H$3*SQRT($J$3)) | J51: =I51 - $H$3*SQRT($J$3)
B52: =B23 | C52: =IF($O$3="sell",-1,1) * IF($K$3="call", NORMDIST(I52,0,1,1), NORMDIST(I52,0,1,1)-1 ) * $P$3 | D52: =IF($O$3="sell",-1,1) * NORMDIST(I52,0,1,0)/(B52*$H$3*SQRT($J$3)) * $P$3 | E52: =IF($O$3="sell",-1,1) * (B52*NORMDIST(I52,0,1,0)*SQRT($J$3)/365) * $P$3 | F52: =IF($O$3="sell",-1,1) * (-(B52*NORMDIST(I52,0,1,0)*$H$3)/(2*SQRT($J$3))/365) *$P$3 | G52: =IF($O$3="buy",1,-1)*( IF($K$3="call",B52*NORMDIST(I52,0,1,1) - $B$3*NORMDIST(J52,0,1,1),$B$3*NORMDIST(-J52,0,1,1) - B52*NORMDIST(-I52,0,1,1) ) - $G$3) * $P$3 | I52: =(LN(B52/$B$3)+($H$3^2/2)*($J$3))/($H$3*SQRT($J$3)) | J52: =I52 - $H$3*SQRT($J$3)
B53: =B24 | C53: =IF($O$3="sell",-1,1) * IF($K$3="call", NORMDIST(I53,0,1,1), NORMDIST(I53,0,1,1)-1 ) * $P$3 | D53: =IF($O$3="sell",-1,1) * NORMDIST(I53,0,1,0)/(B53*$H$3*SQRT($J$3)) * $P$3 | E53: =IF($O$3="sell",-1,1) * (B53*NORMDIST(I53,0,1,0)*SQRT($J$3)/365) * $P$3 | F53: =IF($O$3="sell",-1,1) * (-(B53*NORMDIST(I53,0,1,0)*$H$3)/(2*SQRT($J$3))/365) *$P$3 | G53: =IF($O$3="buy",1,-1)*( IF($K$3="call",B53*NORMDIST(I53,0,1,1) - $B$3*NORMDIST(J53,0,1,1),$B$3*NORMDIST(-J53,0,1,1) - B53*NORMDIST(-I53,0,1,1) ) - $G$3) * $P$3 | I53: =(LN(B53/$B$3)+($H$3^2/2)*($J$3))/($H$3*SQRT($J$3)) | J53: =I53 - $H$3*SQRT($J$3)
B54: =B25 | C54: =IF($O$3="sell",-1,1) * IF($K$3="call", NORMDIST(I54,0,1,1), NORMDIST(I54,0,1,1)-1 ) * $P$3 | D54: =IF($O$3="sell",-1,1) * NORMDIST(I54,0,1,0)/(B54*$H$3*SQRT($J$3)) * $P$3 | E54: =IF($O$3="sell",-1,1) * (B54*NORMDIST(I54,0,1,0)*SQRT($J$3)/365) * $P$3 | F54: =IF($O$3="sell",-1,1) * (-(B54*NORMDIST(I54,0,1,0)*$H$3)/(2*SQRT($J$3))/365) *$P$3 | G54: =IF($O$3="buy",1,-1)*( IF($K$3="call",B54*NORMDIST(I54,0,1,1) - $B$3*NORMDIST(J54,0,1,1),$B$3*NORMDIST(-J54,0,1,1) - B54*NORMDIST(-I54,0,1,1) ) - $G$3) * $P$3 | I54: =(LN(B54/$B$3)+($H$3^2/2)*($J$3))/($H$3*SQRT($J$3)) | J54: =I54 - $H$3*SQRT($J$3)
B55: =B26 | C55: =IF($O$3="sell",-1,1) * IF($K$3="call", NORMDIST(I55,0,1,1), NORMDIST(I55,0,1,1)-1 ) * $P$3 | D55: =IF($O$3="sell",-1,1) * NORMDIST(I55,0,1,0)/(B55*$H$3*SQRT($J$3)) * $P$3 | E55: =IF($O$3="sell",-1,1) * (B55*NORMDIST(I55,0,1,0)*SQRT($J$3)/365) * $P$3 | F55: =IF($O$3="sell",-1,1) * (-(B55*NORMDIST(I55,0,1,0)*$H$3)/(2*SQRT($J$3))/365) *$P$3 | G55: =IF($O$3="buy",1,-1)*( IF($K$3="call",B55*NORMDIST(I55,0,1,1) - $B$3*NORMDIST(J55,0,1,1),$B$3*NORMDIST(-J55,0,1,1) - B55*NORMDIST(-I55,0,1,1) ) - $G$3) * $P$3 | I55: =(LN(B55/$B$3)+($H$3^2/2)*($J$3))/($H$3*SQRT($J$3)) | J55: =I55 - $H$3*SQRT($J$3)
B56: =B27 | C56: =IF($O$3="sell",-1,1) * IF($K$3="call", NORMDIST(I56,0,1,1), NORMDIST(I56,0,1,1)-1 ) * $P$3 | D56: =IF($O$3="sell",-1,1) * NORMDIST(I56,0,1,0)/(B56*$H$3*SQRT($J$3)) * $P$3 | E56: =IF($O$3="sell",-1,1) * (B56*NORMDIST(I56,0,1,0)*SQRT($J$3)/365) * $P$3 | F56: =IF($O$3="sell",-1,1) * (-(B56*NORMDIST(I56,0,1,0)*$H$3)/(2*SQRT($J$3))/365) *$P$3 | G56: =IF($O$3="buy",1,-1)*( IF($K$3="call",B56*NORMDIST(I56,0,1,1) - $B$3*NORMDIST(J56,0,1,1),$B$3*NORMDIST(-J56,0,1,1) - B56*NORMDIST(-I56,0,1,1) ) - $G$3) * $P$3 | I56: =(LN(B56/$B$3)+($H$3^2/2)*($J$3))/($H$3*SQRT($J$3)) | J56: =I56 - $H$3*SQRT($J$3)
B57: =B28 | C57: =IF($O$3="sell",-1,1) * IF($K$3="call", NORMDIST(I57,0,1,1), NORMDIST(I57,0,1,1)-1 ) * $P$3 | D57: =IF($O$3="sell",-1,1) * NORMDIST(I57,0,1,0)/(B57*$H$3*SQRT($J$3)) * $P$3 | E57: =IF($O$3="sell",-1,1) * (B57*NORMDIST(I57,0,1,0)*SQRT($J$3)/365) * $P$3 | F57: =IF($O$3="sell",-1,1) * (-(B57*NORMDIST(I57,0,1,0)*$H$3)/(2*SQRT($J$3))/365) *$P$3 | G57: =IF($O$3="buy",1,-1)*( IF($K$3="call",B57*NORMDIST(I57,0,1,1) - $B$3*NORMDIST(J57,0,1,1),$B$3*NORMDIST(-J57,0,1,1) - B57*NORMDIST(-I57,0,1,1) ) - $G$3) * $P$3 | I57: =(LN(B57/$B$3)+($H$3^2/2)*($J$3))/($H$3*SQRT($J$3)) | J57: =I57 - $H$3*SQRT($J$3)
... B72: =B43 | C72: =IF($O$3="sell",-1,1) * IF($K$3="call", NORMDIST(I72,0,1,1), NORMDIST(I72,0,1,1)-1 ) * $P$3 | D72: =IF($O$3="sell",-1,1) * NORMDIST(I72,0,1,0)/(B72*$H$3*SQRT($J$3)) * $P$3 | E72: =IF($O$3="sell",-1,1) * (B72*NORMDIST(I72,0,1,0)*SQRT($J$3)/365) * $P$3 | F72: =IF($O$3="sell",-1,1) * (-(B72*NORMDIST(I72,0,1,0)*$H$3)/(2*SQRT($J$3))/365) *$P$3 | G72: =IF($O$3="buy",1,-1)*( IF($K$3="call",B72*NORMDIST(I72,0,1,1) - $B$3*NORMDIST(J72,0,1,1),$B$3*NORMDIST(-J72,0,1,1) - B72*NORMDIST(-I72,0,1,1) ) - $G$3) * $P$3 | I72: =(LN(B72/$B$3)+($H$3^2/2)*($J$3))/($H$3*SQRT($J$3)) | J72: =I72 - $H$3*SQRT($J$3)
C74: delta | D74: gamma | E74: vega | F74: theta | G74: mark_price | I74: d1 | J74: d2
A75: =A4 | B75: =B46 | C75: =IF($O$4="sell",-1,1) * IF($K$4="call", NORMDIST(I75,0,1,1), NORMDIST(I75,0,1,1)-1 ) * $P$4 | D75: =IF($O$4="sell",-1,1) * NORMDIST(I75,0,1,0)/(B75*$H$4*SQRT($J$4)) * $P$4 | E75: =IF($O$4="sell",-1,1) * (B75*NORMDIST(I75,0,1,0)*SQRT($J$4)/365) * $P$4 | F75: =IF($O$4="sell",-1,1) * (-(B75*NORMDIST(I75,0,1,0)*$H$4)/(2*SQRT($J$4))/365) *$P$4 | G75: =IF($O$4="buy",1,-1)*( IF($K$4="call",B75*NORMDIST(I75,0,1,1) - $B$4*NORMDIST(J75,0,1,1),$B$4*NORMDIST(-J75,0,1,1) - B75*NORMDIST(-I75,0,1,1) ) - $G$4) * $P$4 | I75: =(LN(B75/$B$4)+($H$4^2/2)*($J$4))/($H$4*SQRT($J$4)) | J75: =I75 - $H$4*SQRT($J$4)
B76: =B47 | C76: =IF($O$4="sell",-1,1) * IF($K$4="call", NORMDIST(I76,0,1,1), NORMDIST(I76,0,1,1)-1 ) * $P$4 | D76: =IF($O$4="sell",-1,1) * NORMDIST(I76,0,1,0)/(B76*$H$4*SQRT($J$4)) * $P$4 | E76: =IF($O$4="sell",-1,1) * (B76*NORMDIST(I76,0,1,0)*SQRT($J$4)/365) * $P$4 | F76: =IF($O$4="sell",-1,1) * (-(B76*NORMDIST(I76,0,1,0)*$H$4)/(2*SQRT($J$4))/365) *$P$4 | G76: =IF($O$4="buy",1,-1)*( IF($K$4="call",B76*NORMDIST(I76,0,1,1) - $B$4*NORMDIST(J76,0,1,1),$B$4*NORMDIST(-J76,0,1,1) - B76*NORMDIST(-I76,0,1,1) ) - $G$4) * $P$4 | I76: =(LN(B76/$B$4)+($H$4^2/2)*($J$4))/($H$4*SQRT($J$4)) | J76: =I76 - $H$4*SQRT($J$4)
B77: =B48 | C77: =IF($O$4="sell",-1,1) * IF($K$4="call", NORMDIST(I77,0,1,1), NORMDIST(I77,0,1,1)-1 ) * $P$4 | D77: =IF($O$4="sell",-1,1) * NORMDIST(I77,0,1,0)/(B77*$H$4*SQRT($J$4)) * $P$4 | E77: =IF($O$4="sell",-1,1) * (B77*NORMDIST(I77,0,1,0)*SQRT($J$4)/365) * $P$4 | F77: =IF($O$4="sell",-1,1) * (-(B77*NORMDIST(I77,0,1,0)*$H$4)/(2*SQRT($J$4))/365) *$P$4 | G77: =IF($O$4="buy",1,-1)*( IF($K$4="call",B77*NORMDIST(I77,0,1,1) - $B$4*NORMDIST(J77,0,1,1),$B$4*NORMDIST(-J77,0,1,1) - B77*NORMDIST(-I77,0,1,1) ) - $G$4) * $P$4 | I77: =(LN(B77/$B$4)+($H$4^2/2)*($J$4))/($H$4*SQRT($J$4)) | J77: =I77 - $H$4*SQRT($J$4)
B78: =B49 | C78: =IF($O$4="sell",-1,1) * IF($K$4="call", NORMDIST(I78,0,1,1), NORMDIST(I78,0,1,1)-1 ) * $P$4 | D78: =IF($O$4="sell",-1,1) * NORMDIST(I78,0,1,0)/(B78*$H$4*SQRT($J$4)) * $P$4 | E78: =IF($O$4="sell",-1,1) * (B78*NORMDIST(I78,0,1,0)*SQRT($J$4)/365) * $P$4 | F78: =IF($O$4="sell",-1,1) * (-(B78*NORMDIST(I78,0,1,0)*$H$4)/(2*SQRT($J$4))/365) *$P$4 | G78: =IF($O$4="buy",1,-1)*( IF($K$4="call",B78*NORMDIST(I78,0,1,1) - $B$4*NORMDIST(J78,0,1,1),$B$4*NORMDIST(-J78,0,1,1) - B78*NORMDIST(-I78,0,1,1) ) - $G$4) * $P$4 | I78: =(LN(B78/$B$4)+($H$4^2/2)*($J$4))/($H$4*SQRT($J$4)) | J78: =I78 - $H$4*SQRT($J$4)
B79: =B50 | C79: =IF($O$4="sell",-1,1) * IF($K$4="call", NORMDIST(I79,0,1,1), NORMDIST(I79,0,1,1)-1 ) * $P$4 | D79: =IF($O$4="sell",-1,1) * NORMDIST(I79,0,1,0)/(B79*$H$4*SQRT($J$4)) * $P$4 | E79: =IF($O$4="sell",-1,1) * (B79*NORMDIST(I79,0,1,0)*SQRT($J$4)/365) * $P$4 | F79: =IF($O$4="sell",-1,1) * (-(B79*NORMDIST(I79,0,1,0)*$H$4)/(2*SQRT($J$4))/365) *$P$4 | G79: =IF($O$4="buy",1,-1)*( IF($K$4="call",B79*NORMDIST(I79,0,1,1) - $B$4*NORMDIST(J79,0,1,1),$B$4*NORMDIST(-J79,0,1,1) - B79*NORMDIST(-I79,0,1,1) ) - $G$4) * $P$4 | I79: =(LN(B79/$B$4)+($H$4^2/2)*($J$4))/($H$4*SQRT($J$4)) | J79: =I79 - $H$4*SQRT($J$4)
B80: =B51 | C80: =IF($O$4="sell",-1,1) * IF($K$4="call", NORMDIST(I80,0,1,1), NORMDIST(I80,0,1,1)-1 ) * $P$4 | D80: =IF($O$4="sell",-1,1) * NORMDIST(I80,0,1,0)/(B80*$H$4*SQRT($J$4)) * $P$4 | E80: =IF($O$4="sell",-1,1) * (B80*NORMDIST(I80,0,1,0)*SQRT($J$4)/365) * $P$4 | F80: =IF($O$4="sell",-1,1) * (-(B80*NORMDIST(I80,0,1,0)*$H$4)/(2*SQRT($J$4))/365) *$P$4 | G80: =IF($O$4="buy",1,-1)*( IF($K$4="call",B80*NORMDIST(I80,0,1,1) - $B$4*NORMDIST(J80,0,1,1),$B$4*NORMDIST(-J80,0,1,1) - B80*NORMDIST(-I80,0,1,1) ) - $G$4) * $P$4 | I80: =(LN(B80/$B$4)+($H$4^2/2)*($J$4))/($H$4*SQRT($J$4)) | J80: =I80 - $H$4*SQRT($J$4)
B81: =B52 | C81: =IF($O$4="sell",-1,1) * IF($K$4="call", NORMDIST(I81,0,1,1), NORMDIST(I81,0,1,1)-1 ) * $P$4 | D81: =IF($O$4="sell",-1,1) * NORMDIST(I81,0,1,0)/(B81*$H$4*SQRT($J$4)) * $P$4 | E81: =IF($O$4="sell",-1,1) * (B81*NORMDIST(I81,0,1,0)*SQRT($J$4)/365) * $P$4 | F81: =IF($O$4="sell",-1,1) * (-(B81*NORMDIST(I81,0,1,0)*$H$4)/(2*SQRT($J$4))/365) *$P$4 | G81: =IF($O$4="buy",1,-1)*( IF($K$4="call",B81*NORMDIST(I81,0,1,1) - $B$4*NORMDIST(J81,0,1,1),$B$4*NORMDIST(-J81,0,1,1) - B81*NORMDIST(-I81,0,1,1) ) - $G$4) * $P$4 | I81: =(LN(B81/$B$4)+($H$4^2/2)*($J$4))/($H$4*SQRT($J$4)) | J81: =I81 - $H$4*SQRT($J$4)
B82: =B53 | C82: =IF($O$4="sell",-1,1) * IF($K$4="call", NORMDIST(I82,0,1,1), NORMDIST(I82,0,1,1)-1 ) * $P$4 | D82: =IF($O$4="sell",-1,1) * NORMDIST(I82,0,1,0)/(B82*$H$4*SQRT($J$4)) * $P$4 | E82: =IF($O$4="sell",-1,1) * (B82*NORMDIST(I82,0,1,0)*SQRT($J$4)/365) * $P$4 | F82: =IF($O$4="sell",-1,1) * (-(B82*NORMDIST(I82,0,1,0)*$H$4)/(2*SQRT($J$4))/365) *$P$4 | G82: =IF($O$4="buy",1,-1)*( IF($K$4="call",B82*NORMDIST(I82,0,1,1) - $B$4*NORMDIST(J82,0,1,1),$B$4*NORMDIST(-J82,0,1,1) - B82*NORMDIST(-I82,0,1,1) ) - $G$4) * $P$4 | I82: =(LN(B82/$B$4)+($H$4^2/2)*($J$4))/($H$4*SQRT($J$4)) | J82: =I82 - $H$4*SQRT($J$4)
B83: =B54 | C83: =IF($O$4="sell",-1,1) * IF($K$4="call", NORMDIST(I83,0,1,1), NORMDIST(I83,0,1,1)-1 ) * $P$4 | D83: =IF($O$4="sell",-1,1) * NORMDIST(I83,0,1,0)/(B83*$H$4*SQRT($J$4)) * $P$4 | E83: =IF($O$4="sell",-1,1) * (B83*NORMDIST(I83,0,1,0)*SQRT($J$4)/365) * $P$4 | F83: =IF($O$4="sell",-1,1) * (-(B83*NORMDIST(I83,0,1,0)*$H$4)/(2*SQRT($J$4))/365) *$P$4 | G83: =IF($O$4="buy",1,-1)*( IF($K$4="call",B83*NORMDIST(I83,0,1,1) - $B$4*NORMDIST(J83,0,1,1),$B$4*NORMDIST(-J83,0,1,1) - B83*NORMDIST(-I83,0,1,1) ) - $G$4) * $P$4 | I83: =(LN(B83/$B$4)+($H$4^2/2)*($J$4))/($H$4*SQRT($J$4)) | J83: =I83 - $H$4*SQRT($J$4)
B84: =B55 | C84: =IF($O$4="sell",-1,1) * IF($K$4="call", NORMDIST(I84,0,1,1), NORMDIST(I84,0,1,1)-1 ) * $P$4 | D84: =IF($O$4="sell",-1,1) * NORMDIST(I84,0,1,0)/(B84*$H$4*SQRT($J$4)) * $P$4 | E84: =IF($O$4="sell",-1,1) * (B84*NORMDIST(I84,0,1,0)*SQRT($J$4)/365) * $P$4 | F84: =IF($O$4="sell",-1,1) * (-(B84*NORMDIST(I84,0,1,0)*$H$4)/(2*SQRT($J$4))/365) *$P$4 | G84: =IF($O$4="buy",1,-1)*( IF($K$4="call",B84*NORMDIST(I84,0,1,1) - $B$4*NORMDIST(J84,0,1,1),$B$4*NORMDIST(-J84,0,1,1) - B84*NORMDIST(-I84,0,1,1) ) - $G$4) * $P$4 | I84: =(LN(B84/$B$4)+($H$4^2/2)*($J$4))/($H$4*SQRT($J$4)) | J84: =I84 - $H$4*SQRT($J$4)
B85: =B56 | C85: =IF($O$4="sell",-1,1) * IF($K$4="call", NORMDIST(I85,0,1,1), NORMDIST(I85,0,1,1)-1 ) * $P$4 | D85: =IF($O$4="sell",-1,1) * NORMDIST(I85,0,1,0)/(B85*$H$4*SQRT($J$4)) * $P$4 | E85: =IF($O$4="sell",-1,1) * (B85*NORMDIST(I85,0,1,0)*SQRT($J$4)/365) * $P$4 | F85: =IF($O$4="sell",-1,1) * (-(B85*NORMDIST(I85,0,1,0)*$H$4)/(2*SQRT($J$4))/365) *$P$4 | G85: =IF($O$4="buy",1,-1)*( IF($K$4="call",B85*NORMDIST(I85,0,1,1) - $B$4*NORMDIST(J85,0,1,1),$B$4*NORMDIST(-J85,0,1,1) - B85*NORMDIST(-I85,0,1,1) ) - $G$4) * $P$4 | I85: =(LN(B85/$B$4)+($H$4^2/2)*($J$4))/($H$4*SQRT($J$4)) | J85: =I85 - $H$4*SQRT($J$4)
B86: =B57 | C86: =IF($O$4="sell",-1,1) * IF($K$4="call", NORMDIST(I86,0,1,1), NORMDIST(I86,0,1,1)-1 ) * $P$4 | D86: =IF($O$4="sell",-1,1) * NORMDIST(I86,0,1,0)/(B86*$H$4*SQRT($J$4)) * $P$4 | E86: =IF($O$4="sell",-1,1) * (B86*NORMDIST(I86,0,1,0)*SQRT($J$4)/365) * $P$4 | F86: =IF($O$4="sell",-1,1) * (-(B86*NORMDIST(I86,0,1,0)*$H$4)/(2*SQRT($J$4))/365) *$P$4 | G86: =IF($O$4="buy",1,-1)*( IF($K$4="call",B86*NORMDIST(I86,0,1,1) - $B$4*NORMDIST(J86,0,1,1),$B$4*NORMDIST(-J86,0,1,1) - B86*NORMDIST(-I86,0,1,1) ) - $G$4) * $P$4 | I86: =(LN(B86/$B$4)+($H$4^2/2)*($J$4))/($H$4*SQRT($J$4)) | J86: =I86 - $H$4*SQRT($J$4)
B87: =B58 | C87: =IF($O$4="sell",-1,1) * IF($K$4="call", NORMDIST(I87,0,1,1), NORMDIST(I87,0,1,1)-1 ) * $P$4 | D87: =IF($O$4="sell",-1,1) * NORMDIST(I87,0,1,0)/(B87*$H$4*SQRT($J$4)) * $P$4 | E87: =IF($O$4="sell",-1,1) * (B87*NORMDIST(I87,0,1,0)*SQRT($J$4)/365) * $P$4 | F87: =IF($O$4="sell",-1,1) * (-(B87*NORMDIST(I87,0,1,0)*$H$4)/(2*SQRT($J$4))/365) *$P$4 | G87: =IF($O$4="buy",1,-1)*( IF($K$4="call",B87*NORMDIST(I87,0,1,1) - $B$4*NORMDIST(J87,0,1,1),$B$4*NORMDIST(-J87,0,1,1) - B87*NORMDIST(-I87,0,1,1) ) - $G$4) * $P$4 | I87: =(LN(B87/$B$4)+($H$4^2/2)*($J$4))/($H$4*SQRT($J$4)) | J87: =I87 - $H$4*SQRT($J$4)
... B101: =B72 | C101: =IF($O$4="sell",-1,1) * IF($K$4="call", NORMDIST(I101,0,1,1), NORMDIST(I101,0,1,1)-1 ) * $P$4 | D101: =IF($O$4="sell",-1,1) * NORMDIST(I101,0,1,0)/(B101*$H$4*SQRT($J$4)) * $P$4 | E101: =IF($O$4="sell",-1,1) * (B101*NORMDIST(I101,0,1,0)*SQRT($J$4)/365) * $P$4 | F101: =IF($O$4="sell",-1,1) * (-(B101*NORMDIST(I101,0,1,0)*$H$4)/(2*SQRT($J$4))/365) *$P$4 | G101: =IF($O$4="buy",1,-1)*( IF($K$4="call",B101*NORMDIST(I101,0,1,1) - $B$4*NORMDIST(J101,0,1,1),$B$4*NORMDIST(-J101,0,1,1) - B101*NORMDIST(-I101,0,1,1) ) - $G$4) * $P$4 | I101: =(LN(B101/$B$4)+($H$4^2/2)*($J$4))/($H$4*SQRT($J$4)) | J101: =I101 - $H$4*SQRT($J$4)
C103: delta | D103: gamma | E103: vega | F103: theta | G103: mark_price | I103: d1 | J103: d2
A104: =A5 | B104: =B75 | C104: =IF($O$5="sell",-1,1) * IF($K$5="call", NORMDIST(I104,0,1,1), NORMDIST(I104,0,1,1)-1 ) * $P$5 | D104: =IF($O$5="sell",-1,1) * NORMDIST(I104,0,1,0)/(B104*$H$5*SQRT($J$5)) * $P$5 | E104: =IF($O$5="sell",-1,1) * (B104*NORMDIST(I104,0,1,0)*SQRT($J$5)/365) * $P$5 | F104: =IF($O$5="sell",-1,1) * (-(B104*NORMDIST(I104,0,1,0)*$H$5)/(2*SQRT($J$5))/365) *$P$5 | G104: =IF($O$5="buy",1,-1)*( IF($K$5="call",B104*NORMDIST(I104,0,1,1) - $B$5*NORMDIST(J104,0,1,1),$B$5*NORMDIST(-J104,0,1,1) - B104*NORMDIST(-I104,0,1,1) ) - $G$5) * $P$5 | I104: =(LN(B104/$B$5)+($H$5^2/2)*($J$5))/($H$5*SQRT($J$5)) | J104: =I104 - $H$5*SQRT($J$5)
B105: =B76 | C105: =IF($O$5="sell",-1,1) * IF($K$5="call", NORMDIST(I105,0,1,1), NORMDIST(I105,0,1,1)-1 ) * $P$5 | D105: =IF($O$5="sell",-1,1) * NORMDIST(I105,0,1,0)/(B105*$H$5*SQRT($J$5)) * $P$5 | E105: =IF($O$5="sell",-1,1) * (B105*NORMDIST(I105,0,1,0)*SQRT($J$5)/365) * $P$5 | F105: =IF($O$5="sell",-1,1) * (-(B105*NORMDIST(I105,0,1,0)*$H$5)/(2*SQRT($J$5))/365) *$P$5 | G105: =IF($O$5="buy",1,-1)*( IF($K$5="call",B105*NORMDIST(I105,0,1,1) - $B$5*NORMDIST(J105,0,1,1),$B$5*NORMDIST(-J105,0,1,1) - B105*NORMDIST(-I105,0,1,1) ) - $G$5) * $P$5 | I105: =(LN(B105/$B$5)+($H$5^2/2)*($J$5))/($H$5*SQRT($J$5)) | J105: =I105 - $H$5*SQRT($J$5)
B106: =B77 | C106: =IF($O$5="sell",-1,1) * IF($K$5="call", NORMDIST(I106,0,1,1), NORMDIST(I106,0,1,1)-1 ) * $P$5 | D106: =IF($O$5="sell",-1,1) * NORMDIST(I106,0,1,0)/(B106*$H$5*SQRT($J$5)) * $P$5 | E106: =IF($O$5="sell",-1,1) * (B106*NORMDIST(I106,0,1,0)*SQRT($J$5)/365) * $P$5 | F106: =IF($O$5="sell",-1,1) * (-(B106*NORMDIST(I106,0,1,0)*$H$5)/(2*SQRT($J$5))/365) *$P$5 | G106: =IF($O$5="buy",1,-1)*( IF($K$5="call",B106*NORMDIST(I106,0,1,1) - $B$5*NORMDIST(J106,0,1,1),$B$5*NORMDIST(-J106,0,1,1) - B106*NORMDIST(-I106,0,1,1) ) - $G$5) * $P$5 | I106: =(LN(B106/$B$5)+($H$5^2/2)*($J$5))/($H$5*SQRT($J$5)) | J106: =I106 - $H$5*SQRT($J$5)
B107: =B78 | C107: =IF($O$5="sell",-1,1) * IF($K$5="call", NORMDIST(I107,0,1,1), NORMDIST(I107,0,1,1)-1 ) * $P$5 | D107: =IF($O$5="sell",-1,1) * NORMDIST(I107,0,1,0)/(B107*$H$5*SQRT($J$5)) * $P$5 | E107: =IF($O$5="sell",-1,1) * (B107*NORMDIST(I107,0,1,0)*SQRT($J$5)/365) * $P$5 | F107: =IF($O$5="sell",-1,1) * (-(B107*NORMDIST(I107,0,1,0)*$H$5)/(2*SQRT($J$5))/365) *$P$5 | G107: =IF($O$5="buy",1,-1)*( IF($K$5="call",B107*NORMDIST(I107,0,1,1) - $B$5*NORMDIST(J107,0,1,1),$B$5*NORMDIST(-J107,0,1,1) - B107*NORMDIST(-I107,0,1,1) ) - $G$5) * $P$5 | I107: =(LN(B107/$B$5)+($H$5^2/2)*($J$5))/($H$5*SQRT($J$5)) | J107: =I107 - $H$5*SQRT($J$5)
B108: =B79 | C108: =IF($O$5="sell",-1,1) * IF($K$5="call", NORMDIST(I108,0,1,1), NORMDIST(I108,0,1,1)-1 ) * $P$5 | D108: =IF($O$5="sell",-1,1) * NORMDIST(I108,0,1,0)/(B108*$H$5*SQRT($J$5)) * $P$5 | E108: =IF($O$5="sell",-1,1) * (B108*NORMDIST(I108,0,1,0)*SQRT($J$5)/365) * $P$5 | F108: =IF($O$5="sell",-1,1) * (-(B108*NORMDIST(I108,0,1,0)*$H$5)/(2*SQRT($J$5))/365) *$P$5 | G108: =IF($O$5="buy",1,-1)*( IF($K$5="call",B108*NORMDIST(I108,0,1,1) - $B$5*NORMDIST(J108,0,1,1),$B$5*NORMDIST(-J108,0,1,1) - B108*NORMDIST(-I108,0,1,1) ) - $G$5) * $P$5 | I108: =(LN(B108/$B$5)+($H$5^2/2)*($J$5))/($H$5*SQRT($J$5)) | J108: =I108 - $H$5*SQRT($J$5)
B109: =B80 | C109: =IF($O$5="sell",-1,1) * IF($K$5="call", NORMDIST(I109,0,1,1), NORMDIST(I109,0,1,1)-1 ) * $P$5 | D109: =IF($O$5="sell",-1,1) * NORMDIST(I109,0,1,0)/(B109*$H$5*SQRT($J$5)) * $P$5 | E109: =IF($O$5="sell",-1,1) * (B109*NORMDIST(I109,0,1,0)*SQRT($J$5)/365) * $P$5 | F109: =IF($O$5="sell",-1,1) * (-(B109*NORMDIST(I109,0,1,0)*$H$5)/(2*SQRT($J$5))/365) *$P$5 | G109: =IF($O$5="buy",1,-1)*( IF($K$5="call",B109*NORMDIST(I109,0,1,1) - $B$5*NORMDIST(J109,0,1,1),$B$5*NORMDIST(-J109,0,1,1) - B109*NORMDIST(-I109,0,1,1) ) - $G$5) * $P$5 | I109: =(LN(B109/$B$5)+($H$5^2/2)*($J$5))/($H$5*SQRT($J$5)) | J109: =I109 - $H$5*SQRT($J$5)
B110: =B81 | C110: =IF($O$5="sell",-1,1) * IF($K$5="call", NORMDIST(I110,0,1,1), NORMDIST(I110,0,1,1)-1 ) * $P$5 | D110: =IF($O$5="sell",-1,1) * NORMDIST(I110,0,1,0)/(B110*$H$5*SQRT($J$5)) * $P$5 | E110: =IF($O$5="sell",-1,1) * (B110*NORMDIST(I110,0,1,0)*SQRT($J$5)/365) * $P$5 | F110: =IF($O$5="sell",-1,1) * (-(B110*NORMDIST(I110,0,1,0)*$H$5)/(2*SQRT($J$5))/365) *$P$5 | G110: =IF($O$5="buy",1,-1)*( IF($K$5="call",B110*NORMDIST(I110,0,1,1) - $B$5*NORMDIST(J110,0,1,1),$B$5*NORMDIST(-J110,0,1,1) - B110*NORMDIST(-I110,0,1,1) ) - $G$5) * $P$5 | I110: =(LN(B110/$B$5)+($H$5^2/2)*($J$5))/($H$5*SQRT($J$5)) | J110: =I110 - $H$5*SQRT($J$5)
B111: =B82 | C111: =IF($O$5="sell",-1,1) * IF($K$5="call", NORMDIST(I111,0,1,1), NORMDIST(I111,0,1,1)-1 ) * $P$5 | D111: =IF($O$5="sell",-1,1) * NORMDIST(I111,0,1,0)/(B111*$H$5*SQRT($J$5)) * $P$5 | E111: =IF($O$5="sell",-1,1) * (B111*NORMDIST(I111,0,1,0)*SQRT($J$5)/365) * $P$5 | F111: =IF($O$5="sell",-1,1) * (-(B111*NORMDIST(I111,0,1,0)*$H$5)/(2*SQRT($J$5))/365) *$P$5 | G111: =IF($O$5="buy",1,-1)*( IF($K$5="call",B111*NORMDIST(I111,0,1,1) - $B$5*NORMDIST(J111,0,1,1),$B$5*NORMDIST(-J111,0,1,1) - B111*NORMDIST(-I111,0,1,1) ) - $G$5) * $P$5 | I111: =(LN(B111/$B$5)+($H$5^2/2)*($J$5))/($H$5*SQRT($J$5)) | J111: =I111 - $H$5*SQRT($J$5)
B112: =B83 | C112: =IF($O$5="sell",-1,1) * IF($K$5="call", NORMDIST(I112,0,1,1), NORMDIST(I112,0,1,1)-1 ) * $P$5 | D112: =IF($O$5="sell",-1,1) * NORMDIST(I112,0,1,0)/(B112*$H$5*SQRT($J$5)) * $P$5 | E112: =IF($O$5="sell",-1,1) * (B112*NORMDIST(I112,0,1,0)*SQRT($J$5)/365) * $P$5 | F112: =IF($O$5="sell",-1,1) * (-(B112*NORMDIST(I112,0,1,0)*$H$5)/(2*SQRT($J$5))/365) *$P$5 | G112: =IF($O$5="buy",1,-1)*( IF($K$5="call",B112*NORMDIST(I112,0,1,1) - $B$5*NORMDIST(J112,0,1,1),$B$5*NORMDIST(-J112,0,1,1) - B112*NORMDIST(-I112,0,1,1) ) - $G$5) * $P$5 | I112: =(LN(B112/$B$5)+($H$5^2/2)*($J$5))/($H$5*SQRT($J$5)) | J112: =I112 - $H$5*SQRT($J$5)
B113: =B84 | C113: =IF($O$5="sell",-1,1) * IF($K$5="call", NORMDIST(I113,0,1,1), NORMDIST(I113,0,1,1)-1 ) * $P$5 | D113: =IF($O$5="sell",-1,1) * NORMDIST(I113,0,1,0)/(B113*$H$5*SQRT($J$5)) * $P$5 | E113: =IF($O$5="sell",-1,1) * (B113*NORMDIST(I113,0,1,0)*SQRT($J$5)/365) * $P$5 | F113: =IF($O$5="sell",-1,1) * (-(B113*NORMDIST(I113,0,1,0)*$H$5)/(2*SQRT($J$5))/365) *$P$5 | G113: =IF($O$5="buy",1,-1)*( IF($K$5="call",B113*NORMDIST(I113,0,1,1) - $B$5*NORMDIST(J113,0,1,1),$B$5*NORMDIST(-J113,0,1,1) - B113*NORMDIST(-I113,0,1,1) ) - $G$5) * $P$5 | I113: =(LN(B113/$B$5)+($H$5^2/2)*($J$5))/($H$5*SQRT($J$5)) | J113: =I113 - $H$5*SQRT($J$5)
B114: =B85 | C114: =IF($O$5="sell",-1,1) * IF($K$5="call", NORMDIST(I114,0,1,1), NORMDIST(I114,0,1,1)-1 ) * $P$5 | D114: =IF($O$5="sell",-1,1) * NORMDIST(I114,0,1,0)/(B114*$H$5*SQRT($J$5)) * $P$5 | E114: =IF($O$5="sell",-1,1) * (B114*NORMDIST(I114,0,1,0)*SQRT($J$5)/365) * $P$5 | F114: =IF($O$5="sell",-1,1) * (-(B114*NORMDIST(I114,0,1,0)*$H$5)/(2*SQRT($J$5))/365) *$P$5 | G114: =IF($O$5="buy",1,-1)*( IF($K$5="call",B114*NORMDIST(I114,0,1,1) - $B$5*NORMDIST(J114,0,1,1),$B$5*NORMDIST(-J114,0,1,1) - B114*NORMDIST(-I114,0,1,1) ) - $G$5) * $P$5 | I114: =(LN(B114/$B$5)+($H$5^2/2)*($J$5))/($H$5*SQRT($J$5)) | J114: =I114 - $H$5*SQRT($J$5)
B115: =B86 | C115: =IF($O$5="sell",-1,1) * IF($K$5="call", NORMDIST(I115,0,1,1), NORMDIST(I115,0,1,1)-1 ) * $P$5 | D115: =IF($O$5="sell",-1,1) * NORMDIST(I115,0,1,0)/(B115*$H$5*SQRT($J$5)) * $P$5 | E115: =IF($O$5="sell",-1,1) * (B115*NORMDIST(I115,0,1,0)*SQRT($J$5)/365) * $P$5 | F115: =IF($O$5="sell",-1,1) * (-(B115*NORMDIST(I115,0,1,0)*$H$5)/(2*SQRT($J$5))/365) *$P$5 | G115: =IF($O$5="buy",1,-1)*( IF($K$5="call",B115*NORMDIST(I115,0,1,1) - $B$5*NORMDIST(J115,0,1,1),$B$5*NORMDIST(-J115,0,1,1) - B115*NORMDIST(-I115,0,1,1) ) - $G$5) * $P$5 | I115: =(LN(B115/$B$5)+($H$5^2/2)*($J$5))/($H$5*SQRT($J$5)) | J115: =I115 - $H$5*SQRT($J$5)
B116: =B87 | C116: =IF($O$5="sell",-1,1) * IF($K$5="call", NORMDIST(I116,0,1,1), NORMDIST(I116,0,1,1)-1 ) * $P$5 | D116: =IF($O$5="sell",-1,1) * NORMDIST(I116,0,1,0)/(B116*$H$5*SQRT($J$5)) * $P$5 | E116: =IF($O$5="sell",-1,1) * (B116*NORMDIST(I116,0,1,0)*SQRT($J$5)/365) * $P$5 | F116: =IF($O$5="sell",-1,1) * (-(B116*NORMDIST(I116,0,1,0)*$H$5)/(2*SQRT($J$5))/365) *$P$5 | G116: =IF($O$5="buy",1,-1)*( IF($K$5="call",B116*NORMDIST(I116,0,1,1) - $B$5*NORMDIST(J116,0,1,1),$B$5*NORMDIST(-J116,0,1,1) - B116*NORMDIST(-I116,0,1,1) ) - $G$5) * $P$5 | I116: =(LN(B116/$B$5)+($H$5^2/2)*($J$5))/($H$5*SQRT($J$5)) | J116: =I116 - $H$5*SQRT($J$5)
... B130: =B101 | C130: =IF($O$5="sell",-1,1) * IF($K$5="call", NORMDIST(I130,0,1,1), NORMDIST(I130,0,1,1)-1 ) * $P$5 | D130: =IF($O$5="sell",-1,1) * NORMDIST(I130,0,1,0)/(B130*$H$5*SQRT($J$5)) * $P$5 | E130: =IF($O$5="sell",-1,1) * (B130*NORMDIST(I130,0,1,0)*SQRT($J$5)/365) * $P$5 | F130: =IF($O$5="sell",-1,1) * (-(B130*NORMDIST(I130,0,1,0)*$H$5)/(2*SQRT($J$5))/365) *$P$5 | G130: =IF($O$5="buy",1,-1)*( IF($K$5="call",B130*NORMDIST(I130,0,1,1) - $B$5*NORMDIST(J130,0,1,1),$B$5*NORMDIST(-J130,0,1,1) - B130*NORMDIST(-I130,0,1,1) ) - $G$5) * $P$5 | I130: =(LN(B130/$B$5)+($H$5^2/2)*($J$5))/($H$5*SQRT($J$5)) | J130: =I130 - $H$5*SQRT($J$5)
C133: delta | D133: gamma | E133: vega | F133: theta | G133: mark_price | I133: d1 | J133: d2
A134: =A6 | B134: =B104 | C134: =IF($O$6="sell",-1,1) * IF($K$6="call", NORMDIST(I134,0,1,1), NORMDIST(I134,0,1,1)-1 ) * $P$6 | D134: =IF($O$6="sell",-1,1) * NORMDIST(I134,0,1,0)/(B134*$H$6*SQRT($J$6)) * $P$6 | E134: =IF($O$6="sell",-1,1) * (B134*NORMDIST(I134,0,1,0)*SQRT($J$6)/365) * $P$6 | F134: =IF($O$6="sell",-1,1) * (-(B134*NORMDIST(I134,0,1,0)*$H$6)/(2*SQRT($J$6))/365) *$P$6 | G134: =IF($O$6="buy",1,-1)*( IF($K$6="call",B134*NORMDIST(I134,0,1,1) - $B$6*NORMDIST(J134,0,1,1),$B$6*NORMDIST(-J134,0,1,1) - B134*NORMDIST(-I134,0,1,1) ) - $G$6) * $P$6 | I134: =(LN(B134/$B$6)+($H$6^2/2)*($J$6))/($H$6*SQRT($J$6)) | J134: =I134 - $H$6*SQRT($J$6)
B135: =B105 | C135: =IF($O$6="sell",-1,1) * IF($K$6="call", NORMDIST(I135,0,1,1), NORMDIST(I135,0,1,1)-1 ) * $P$6 | D135: =IF($O$6="sell",-1,1) * NORMDIST(I135,0,1,0)/(B135*$H$6*SQRT($J$6)) * $P$6 | E135: =IF($O$6="sell",-1,1) * (B135*NORMDIST(I135,0,1,0)*SQRT($J$6)/365) * $P$6 | F135: =IF($O$6="sell",-1,1) * (-(B135*NORMDIST(I135,0,1,0)*$H$6)/(2*SQRT($J$6))/365) *$P$6 | G135: =IF($O$6="buy",1,-1)*( IF($K$6="call",B135*NORMDIST(I135,0,1,1) - $B$6*NORMDIST(J135,0,1,1),$B$6*NORMDIST(-J135,0,1,1) - B135*NORMDIST(-I135,0,1,1) ) - $G$6) * $P$6 | I135: =(LN(B135/$B$6)+($H$6^2/2)*($J$6))/($H$6*SQRT($J$6)) | J135: =I135 - $H$6*SQRT($J$6)
B136: =B106 | C136: =IF($O$6="sell",-1,1) * IF($K$6="call", NORMDIST(I136,0,1,1), NORMDIST(I136,0,1,1)-1 ) * $P$6 | D136: =IF($O$6="sell",-1,1) * NORMDIST(I136,0,1,0)/(B136*$H$6*SQRT($J$6)) * $P$6 | E136: =IF($O$6="sell",-1,1) * (B136*NORMDIST(I136,0,1,0)*SQRT($J$6)/365) * $P$6 | F136: =IF($O$6="sell",-1,1) * (-(B136*NORMDIST(I136,0,1,0)*$H$6)/(2*SQRT($J$6))/365) *$P$6 | G136: =IF($O$6="buy",1,-1)*( IF($K$6="call",B136*NORMDIST(I136,0,1,1) - $B$6*NORMDIST(J136,0,1,1),$B$6*NORMDIST(-J136,0,1,1) - B136*NORMDIST(-I136,0,1,1) ) - $G$6) * $P$6 | I136: =(LN(B136/$B$6)+($H$6^2/2)*($J$6))/($H$6*SQRT($J$6)) | J136: =I136 - $H$6*SQRT($J$6)
B137: =B107 | C137: =IF($O$6="sell",-1,1) * IF($K$6="call", NORMDIST(I137,0,1,1), NORMDIST(I137,0,1,1)-1 ) * $P$6 | D137: =IF($O$6="sell",-1,1) * NORMDIST(I137,0,1,0)/(B137*$H$6*SQRT($J$6)) * $P$6 | E137: =IF($O$6="sell",-1,1) * (B137*NORMDIST(I137,0,1,0)*SQRT($J$6)/365) * $P$6 | F137: =IF($O$6="sell",-1,1) * (-(B137*NORMDIST(I137,0,1,0)*$H$6)/(2*SQRT($J$6))/365) *$P$6 | G137: =IF($O$6="buy",1,-1)*( IF($K$6="call",B137*NORMDIST(I137,0,1,1) - $B$6*NORMDIST(J137,0,1,1),$B$6*NORMDIST(-J137,0,1,1) - B137*NORMDIST(-I137,0,1,1) ) - $G$6) * $P$6 | I137: =(LN(B137/$B$6)+($H$6^2/2)*($J$6))/($H$6*SQRT($J$6)) | J137: =I137 - $H$6*SQRT($J$6)
B138: =B108 | C138: =IF($O$6="sell",-1,1) * IF($K$6="call", NORMDIST(I138,0,1,1), NORMDIST(I138,0,1,1)-1 ) * $P$6 | D138: =IF($O$6="sell",-1,1) * NORMDIST(I138,0,1,0)/(B138*$H$6*SQRT($J$6)) * $P$6 | E138: =IF($O$6="sell",-1,1) * (B138*NORMDIST(I138,0,1,0)*SQRT($J$6)/365) * $P$6 | F138: =IF($O$6="sell",-1,1) * (-(B138*NORMDIST(I138,0,1,0)*$H$6)/(2*SQRT($J$6))/365) *$P$6 | G138: =IF($O$6="buy",1,-1)*( IF($K$6="call",B138*NORMDIST(I138,0,1,1) - $B$6*NORMDIST(J138,0,1,1),$B$6*NORMDIST(-J138,0,1,1) - B138*NORMDIST(-I138,0,1,1) ) - $G$6) * $P$6 | I138: =(LN(B138/$B$6)+($H$6^2/2)*($J$6))/($H$6*SQRT($J$6)) | J138: =I138 - $H$6*SQRT($J$6)
B139: =B109 | C139: =IF($O$6="sell",-1,1) * IF($K$6="call", NORMDIST(I139,0,1,1), NORMDIST(I139,0,1,1)-1 ) * $P$6 | D139: =IF($O$6="sell",-1,1) * NORMDIST(I139,0,1,0)/(B139*$H$6*SQRT($J$6)) * $P$6 | E139: =IF($O$6="sell",-1,1) * (B139*NORMDIST(I139,0,1,0)*SQRT($J$6)/365) * $P$6 | F139: =IF($O$6="sell",-1,1) * (-(B139*NORMDIST(I139,0,1,0)*$H$6)/(2*SQRT($J$6))/365) *$P$6 | G139: =IF($O$6="buy",1,-1)*( IF($K$6="call",B139*NORMDIST(I139,0,1,1) - $B$6*NORMDIST(J139,0,1,1),$B$6*NORMDIST(-J139,0,1,1) - B139*NORMDIST(-I139,0,1,1) ) - $G$6) * $P$6 | I139: =(LN(B139/$B$6)+($H$6^2/2)*($J$6))/($H$6*SQRT($J$6)) | J139: =I139 - $H$6*SQRT($J$6)
B140: =B110 | C140: =IF($O$6="sell",-1,1) * IF($K$6="call", NORMDIST(I140,0,1,1), NORMDIST(I140,0,1,1)-1 ) * $P$6 | D140: =IF($O$6="sell",-1,1) * NORMDIST(I140,0,1,0)/(B140*$H$6*SQRT($J$6)) * $P$6 | E140: =IF($O$6="sell",-1,1) * (B140*NORMDIST(I140,0,1,0)*SQRT($J$6)/365) * $P$6 | F140: =IF($O$6="sell",-1,1) * (-(B140*NORMDIST(I140,0,1,0)*$H$6)/(2*SQRT($J$6))/365) *$P$6 | G140: =IF($O$6="buy",1,-1)*( IF($K$6="call",B140*NORMDIST(I140,0,1,1) - $B$6*NORMDIST(J140,0,1,1),$B$6*NORMDIST(-J140,0,1,1) - B140*NORMDIST(-I140,0,1,1) ) - $G$6) * $P$6 | I140: =(LN(B140/$B$6)+($H$6^2/2)*($J$6))/($H$6*SQRT($J$6)) | J140: =I140 - $H$6*SQRT($J$6)
B141: =B111 | C141: =IF($O$6="sell",-1,1) * IF($K$6="call", NORMDIST(I141,0,1,1), NORMDIST(I141,0,1,1)-1 ) * $P$6 | D141: =IF($O$6="sell",-1,1) * NORMDIST(I141,0,1,0)/(B141*$H$6*SQRT($J$6)) * $P$6 | E141: =IF($O$6="sell",-1,1) * (B141*NORMDIST(I141,0,1,0)*SQRT($J$6)/365) * $P$6 | F141: =IF($O$6="sell",-1,1) * (-(B141*NORMDIST(I141,0,1,0)*$H$6)/(2*SQRT($J$6))/365) *$P$6 | G141: =IF($O$6="buy",1,-1)*( IF($K$6="call",B141*NORMDIST(I141,0,1,1) - $B$6*NORMDIST(J141,0,1,1),$B$6*NORMDIST(-J141,0,1,1) - B141*NORMDIST(-I141,0,1,1) ) - $G$6) * $P$6 | I141: =(LN(B141/$B$6)+($H$6^2/2)*($J$6))/($H$6*SQRT($J$6)) | J141: =I141 - $H$6*SQRT($J$6)
B142: =B112 | C142: =IF($O$6="sell",-1,1) * IF($K$6="call", NORMDIST(I142,0,1,1), NORMDIST(I142,0,1,1)-1 ) * $P$6 | D142: =IF($O$6="sell",-1,1) * NORMDIST(I142,0,1,0)/(B142*$H$6*SQRT($J$6)) * $P$6 | E142: =IF($O$6="sell",-1,1) * (B142*NORMDIST(I142,0,1,0)*SQRT($J$6)/365) * $P$6 | F142: =IF($O$6="sell",-1,1) * (-(B142*NORMDIST(I142,0,1,0)*$H$6)/(2*SQRT($J$6))/365) *$P$6 | G142: =IF($O$6="buy",1,-1)*( IF($K$6="call",B142*NORMDIST(I142,0,1,1) - $B$6*NORMDIST(J142,0,1,1),$B$6*NORMDIST(-J142,0,1,1) - B142*NORMDIST(-I142,0,1,1) ) - $G$6) * $P$6 | I142: =(LN(B142/$B$6)+($H$6^2/2)*($J$6))/($H$6*SQRT($J$6)) | J142: =I142 - $H$6*SQRT($J$6)
B143: =B113 | C143: =IF($O$6="sell",-1,1) * IF($K$6="call", NORMDIST(I143,0,1,1), NORMDIST(I143,0,1,1)-1 ) * $P$6 | D143: =IF($O$6="sell",-1,1) * NORMDIST(I143,0,1,0)/(B143*$H$6*SQRT($J$6)) * $P$6 | E143: =IF($O$6="sell",-1,1) * (B143*NORMDIST(I143,0,1,0)*SQRT($J$6)/365) * $P$6 | F143: =IF($O$6="sell",-1,1) * (-(B143*NORMDIST(I143,0,1,0)*$H$6)/(2*SQRT($J$6))/365) *$P$6 | G143: =IF($O$6="buy",1,-1)*( IF($K$6="call",B143*NORMDIST(I143,0,1,1) - $B$6*NORMDIST(J143,0,1,1),$B$6*NORMDIST(-J143,0,1,1) - B143*NORMDIST(-I143,0,1,1) ) - $G$6) * $P$6 | I143: =(LN(B143/$B$6)+($H$6^2/2)*($J$6))/($H$6*SQRT($J$6)) | J143: =I143 - $H$6*SQRT($J$6)
B144: =B114 | C144: =IF($O$6="sell",-1,1) * IF($K$6="call", NORMDIST(I144,0,1,1), NORMDIST(I144,0,1,1)-1 ) * $P$6 | D144: =IF($O$6="sell",-1,1) * NORMDIST(I144,0,1,0)/(B144*$H$6*SQRT($J$6)) * $P$6 | E144: =IF($O$6="sell",-1,1) * (B144*NORMDIST(I144,0,1,0)*SQRT($J$6)/365) * $P$6 | F144: =IF($O$6="sell",-1,1) * (-(B144*NORMDIST(I144,0,1,0)*$H$6)/(2*SQRT($J$6))/365) *$P$6 | G144: =IF($O$6="buy",1,-1)*( IF($K$6="call",B144*NORMDIST(I144,0,1,1) - $B$6*NORMDIST(J144,0,1,1),$B$6*NORMDIST(-J144,0,1,1) - B144*NORMDIST(-I144,0,1,1) ) - $G$6) * $P$6 | I144: =(LN(B144/$B$6)+($H$6^2/2)*($J$6))/($H$6*SQRT($J$6)) | J144: =I144 - $H$6*SQRT($J$6)
B145: =B115 | C145: =IF($O$6="sell",-1,1) * IF($K$6="call", NORMDIST(I145,0,1,1), NORMDIST(I145,0,1,1)-1 ) * $P$6 | D145: =IF($O$6="sell",-1,1) * NORMDIST(I145,0,1,0)/(B145*$H$6*SQRT($J$6)) * $P$6 | E145: =IF($O$6="sell",-1,1) * (B145*NORMDIST(I145,0,1,0)*SQRT($J$6)/365) * $P$6 | F145: =IF($O$6="sell",-1,1) * (-(B145*NORMDIST(I145,0,1,0)*$H$6)/(2*SQRT($J$6))/365) *$P$6 | G145: =IF($O$6="buy",1,-1)*( IF($K$6="call",B145*NORMDIST(I145,0,1,1) - $B$6*NORMDIST(J145,0,1,1),$B$6*NORMDIST(-J145,0,1,1) - B145*NORMDIST(-I145,0,1,1) ) - $G$6) * $P$6 | I145: =(LN(B145/$B$6)+($H$6^2/2)*($J$6))/($H$6*SQRT($J$6)) | J145: =I145 - $H$6*SQRT($J$6)
B146: =B116 | C146: =IF($O$6="sell",-1,1) * IF($K$6="call", NORMDIST(I146,0,1,1), NORMDIST(I146,0,1,1)-1 ) * $P$6 | D146: =IF($O$6="sell",-1,1) * NORMDIST(I146,0,1,0)/(B146*$H$6*SQRT($J$6)) * $P$6 | E146: =IF($O$6="sell",-1,1) * (B146*NORMDIST(I146,0,1,0)*SQRT($J$6)/365) * $P$6 | F146: =IF($O$6="sell",-1,1) * (-(B146*NORMDIST(I146,0,1,0)*$H$6)/(2*SQRT($J$6))/365) *$P$6 | G146: =IF($O$6="buy",1,-1)*( IF($K$6="call",B146*NORMDIST(I146,0,1,1) - $B$6*NORMDIST(J146,0,1,1),$B$6*NORMDIST(-J146,0,1,1) - B146*NORMDIST(-I146,0,1,1) ) - $G$6) * $P$6 | I146: =(LN(B146/$B$6)+($H$6^2/2)*($J$6))/($H$6*SQRT($J$6)) | J146: =I146 - $H$6*SQRT($J$6)
... B160: =B130 | C160: =IF($O$6="sell",-1,1) * IF($K$6="call", NORMDIST(I160,0,1,1), NORMDIST(I160,0,1,1)-1 ) * $P$6 | D160: =IF($O$6="sell",-1,1) * NORMDIST(I160,0,1,0)/(B160*$H$6*SQRT($J$6)) * $P$6 | E160: =IF($O$6="sell",-1,1) * (B160*NORMDIST(I160,0,1,0)*SQRT($J$6)/365) * $P$6 | F160: =IF($O$6="sell",-1,1) * (-(B160*NORMDIST(I160,0,1,0)*$H$6)/(2*SQRT($J$6))/365) *$P$6 | G160: =IF($O$6="buy",1,-1)*( IF($K$6="call",B160*NORMDIST(I160,0,1,1) - $B$6*NORMDIST(J160,0,1,1),$B$6*NORMDIST(-J160,0,1,1) - B160*NORMDIST(-I160,0,1,1) ) - $G$6) * $P$6 | I160: =(LN(B160/$B$6)+($H$6^2/2)*($J$6))/($H$6*SQRT($J$6)) | J160: =I160 - $H$6*SQRT($J$6)
C163: delta | D163: gamma | E163: vega | F163: theta | G163: mark_price | I163: d1 | J163: d2
A164: =A7 | B164: =B134 | C164: =IF($O$7="sell",-1,1) * IF($K$7="call", NORMDIST(I164,0,1,1), NORMDIST(I164,0,1,1)-1 ) * $P$7 | D164: =IF($O$7="sell",-1,1) * NORMDIST(I164,0,1,0)/(B164*$H$7*SQRT($J$7)) * $P$7 | E164: =IF($O$7="sell",-1,1) * (B164*NORMDIST(I164,0,1,0)*SQRT($J$7)/365) * $P$7 | F164: =IF($O$7="sell",-1,1) * (-(B164*NORMDIST(I164,0,1,0)*$H$7)/(2*SQRT($J$7))/365) *$P$7 | G164: =IF($O$7="buy",1,-1)*( IF($K$7="call",B164*NORMDIST(I164,0,1,1) - $B$7*NORMDIST(J164,0,1,1),$B$7*NORMDIST(-J164,0,1,1) - B164*NORMDIST(-I164,0,1,1) ) - $G$7) * $P$7 | I164: =(LN(B164/$B$7)+($H$7^2/2)*($J$7))/($H$7*SQRT($J$7)) | J164: =I164 - $H$7*SQRT($J$7)
B165: =B135 | C165: =IF($O$7="sell",-1,1) * IF($K$7="call", NORMDIST(I165,0,1,1), NORMDIST(I165,0,1,1)-1 ) * $P$7 | D165: =IF($O$7="sell",-1,1) * NORMDIST(I165,0,1,0)/(B165*$H$7*SQRT($J$7)) * $P$7 | E165: =IF($O$7="sell",-1,1) * (B165*NORMDIST(I165,0,1,0)*SQRT($J$7)/365) * $P$7 | F165: =IF($O$7="sell",-1,1) * (-(B165*NORMDIST(I165,0,1,0)*$H$7)/(2*SQRT($J$7))/365) *$P$7 | G165: =IF($O$7="buy",1,-1)*( IF($K$7="call",B165*NORMDIST(I165,0,1,1) - $B$7*NORMDIST(J165,0,1,1),$B$7*NORMDIST(-J165,0,1,1) - B165*NORMDIST(-I165,0,1,1) ) - $G$7) * $P$7 | I165: =(LN(B165/$B$7)+($H$7^2/2)*($J$7))/($H$7*SQRT($J$7)) | J165: =I165 - $H$7*SQRT($J$7)
B166: =B136 | C166: =IF($O$7="sell",-1,1) * IF($K$7="call", NORMDIST(I166,0,1,1), NORMDIST(I166,0,1,1)-1 ) * $P$7 | D166: =IF($O$7="sell",-1,1) * NORMDIST(I166,0,1,0)/(B166*$H$7*SQRT($J$7)) * $P$7 | E166: =IF($O$7="sell",-1,1) * (B166*NORMDIST(I166,0,1,0)*SQRT($J$7)/365) * $P$7 | F166: =IF($O$7="sell",-1,1) * (-(B166*NORMDIST(I166,0,1,0)*$H$7)/(2*SQRT($J$7))/365) *$P$7 | G166: =IF($O$7="buy",1,-1)*( IF($K$7="call",B166*NORMDIST(I166,0,1,1) - $B$7*NORMDIST(J166,0,1,1),$B$7*NORMDIST(-J166,0,1,1) - B166*NORMDIST(-I166,0,1,1) ) - $G$7) * $P$7 | I166: =(LN(B166/$B$7)+($H$7^2/2)*($J$7))/($H$7*SQRT($J$7)) | J166: =I166 - $H$7*SQRT($J$7)
B167: =B137 | C167: =IF($O$7="sell",-1,1) * IF($K$7="call", NORMDIST(I167,0,1,1), NORMDIST(I167,0,1,1)-1 ) * $P$7 | D167: =IF($O$7="sell",-1,1) * NORMDIST(I167,0,1,0)/(B167*$H$7*SQRT($J$7)) * $P$7 | E167: =IF($O$7="sell",-1,1) * (B167*NORMDIST(I167,0,1,0)*SQRT($J$7)/365) * $P$7 | F167: =IF($O$7="sell",-1,1) * (-(B167*NORMDIST(I167,0,1,0)*$H$7)/(2*SQRT($J$7))/365) *$P$7 | G167: =IF($O$7="buy",1,-1)*( IF($K$7="call",B167*NORMDIST(I167,0,1,1) - $B$7*NORMDIST(J167,0,1,1),$B$7*NORMDIST(-J167,0,1,1) - B167*NORMDIST(-I167,0,1,1) ) - $G$7) * $P$7 | I167: =(LN(B167/$B$7)+($H$7^2/2)*($J$7))/($H$7*SQRT($J$7)) | J167: =I167 - $H$7*SQRT($J$7)
B168: =B138 | C168: =IF($O$7="sell",-1,1) * IF($K$7="call", NORMDIST(I168,0,1,1), NORMDIST(I168,0,1,1)-1 ) * $P$7 | D168: =IF($O$7="sell",-1,1) * NORMDIST(I168,0,1,0)/(B168*$H$7*SQRT($J$7)) * $P$7 | E168: =IF($O$7="sell",-1,1) * (B168*NORMDIST(I168,0,1,0)*SQRT($J$7)/365) * $P$7 | F168: =IF($O$7="sell",-1,1) * (-(B168*NORMDIST(I168,0,1,0)*$H$7)/(2*SQRT($J$7))/365) *$P$7 | G168: =IF($O$7="buy",1,-1)*( IF($K$7="call",B168*NORMDIST(I168,0,1,1) - $B$7*NORMDIST(J168,0,1,1),$B$7*NORMDIST(-J168,0,1,1) - B168*NORMDIST(-I168,0,1,1) ) - $G$7) * $P$7 | I168: =(LN(B168/$B$7)+($H$7^2/2)*($J$7))/($H$7*SQRT($J$7)) | J168: =I168 - $H$7*SQRT($J$7)
B169: =B139 | C169: =IF($O$7="sell",-1,1) * IF($K$7="call", NORMDIST(I169,0,1,1), NORMDIST(I169,0,1,1)-1 ) * $P$7 | D169: =IF($O$7="sell",-1,1) * NORMDIST(I169,0,1,0)/(B169*$H$7*SQRT($J$7)) * $P$7 | E169: =IF($O$7="sell",-1,1) * (B169*NORMDIST(I169,0,1,0)*SQRT($J$7)/365) * $P$7 | F169: =IF($O$7="sell",-1,1) * (-(B169*NORMDIST(I169,0,1,0)*$H$7)/(2*SQRT($J$7))/365) *$P$7 | G169: =IF($O$7="buy",1,-1)*( IF($K$7="call",B169*NORMDIST(I169,0,1,1) - $B$7*NORMDIST(J169,0,1,1),$B$7*NORMDIST(-J169,0,1,1) - B169*NORMDIST(-I169,0,1,1) ) - $G$7) * $P$7 | I169: =(LN(B169/$B$7)+($H$7^2/2)*($J$7))/($H$7*SQRT($J$7)) | J169: =I169 - $H$7*SQRT($J$7)
B170: =B140 | C170: =IF($O$7="sell",-1,1) * IF($K$7="call", NORMDIST(I170,0,1,1), NORMDIST(I170,0,1,1)-1 ) * $P$7 | D170: =IF($O$7="sell",-1,1) * NORMDIST(I170,0,1,0)/(B170*$H$7*SQRT($J$7)) * $P$7 | E170: =IF($O$7="sell",-1,1) * (B170*NORMDIST(I170,0,1,0)*SQRT($J$7)/365) * $P$7 | F170: =IF($O$7="sell",-1,1) * (-(B170*NORMDIST(I170,0,1,0)*$H$7)/(2*SQRT($J$7))/365) *$P$7 | G170: =IF($O$7="buy",1,-1)*( IF($K$7="call",B170*NORMDIST(I170,0,1,1) - $B$7*NORMDIST(J170,0,1,1),$B$7*NORMDIST(-J170,0,1,1) - B170*NORMDIST(-I170,0,1,1) ) - $G$7) * $P$7 | I170: =(LN(B170/$B$7)+($H$7^2/2)*($J$7))/($H$7*SQRT($J$7)) | J170: =I170 - $H$7*SQRT($J$7)
B171: =B141 | C171: =IF($O$7="sell",-1,1) * IF($K$7="call", NORMDIST(I171,0,1,1), NORMDIST(I171,0,1,1)-1 ) * $P$7 | D171: =IF($O$7="sell",-1,1) * NORMDIST(I171,0,1,0)/(B171*$H$7*SQRT($J$7)) * $P$7 | E171: =IF($O$7="sell",-1,1) * (B171*NORMDIST(I171,0,1,0)*SQRT($J$7)/365) * $P$7 | F171: =IF($O$7="sell",-1,1) * (-(B171*NORMDIST(I171,0,1,0)*$H$7)/(2*SQRT($J$7))/365) *$P$7 | G171: =IF($O$7="buy",1,-1)*( IF($K$7="call",B171*NORMDIST(I171,0,1,1) - $B$7*NORMDIST(J171,0,1,1),$B$7*NORMDIST(-J171,0,1,1) - B171*NORMDIST(-I171,0,1,1) ) - $G$7) * $P$7 | I171: =(LN(B171/$B$7)+($H$7^2/2)*($J$7))/($H$7*SQRT($J$7)) | J171: =I171 - $H$7*SQRT($J$7)
B172: =B142 | C172: =IF($O$7="sell",-1,1) * IF($K$7="call", NORMDIST(I172,0,1,1), NORMDIST(I172,0,1,1)-1 ) * $P$7 | D172: =IF($O$7="sell",-1,1) * NORMDIST(I172,0,1,0)/(B172*$H$7*SQRT($J$7)) * $P$7 | E172: =IF($O$7="sell",-1,1) * (B172*NORMDIST(I172,0,1,0)*SQRT($J$7)/365) * $P$7 | F172: =IF($O$7="sell",-1,1) * (-(B172*NORMDIST(I172,0,1,0)*$H$7)/(2*SQRT($J$7))/365) *$P$7 | G172: =IF($O$7="buy",1,-1)*( IF($K$7="call",B172*NORMDIST(I172,0,1,1) - $B$7*NORMDIST(J172,0,1,1),$B$7*NORMDIST(-J172,0,1,1) - B172*NORMDIST(-I172,0,1,1) ) - $G$7) * $P$7 | I172: =(LN(B172/$B$7)+($H$7^2/2)*($J$7))/($H$7*SQRT($J$7)) | J172: =I172 - $H$7*SQRT($J$7)
B173: =B143 | C173: =IF($O$7="sell",-1,1) * IF($K$7="call", NORMDIST(I173,0,1,1), NORMDIST(I173,0,1,1)-1 ) * $P$7 | D173: =IF($O$7="sell",-1,1) * NORMDIST(I173,0,1,0)/(B173*$H$7*SQRT($J$7)) * $P$7 | E173: =IF($O$7="sell",-1,1) * (B173*NORMDIST(I173,0,1,0)*SQRT($J$7)/365) * $P$7 | F173: =IF($O$7="sell",-1,1) * (-(B173*NORMDIST(I173,0,1,0)*$H$7)/(2*SQRT($J$7))/365) *$P$7 | G173: =IF($O$7="buy",1,-1)*( IF($K$7="call",B173*NORMDIST(I173,0,1,1) - $B$7*NORMDIST(J173,0,1,1),$B$7*NORMDIST(-J173,0,1,1) - B173*NORMDIST(-I173,0,1,1) ) - $G$7) * $P$7 | I173: =(LN(B173/$B$7)+($H$7^2/2)*($J$7))/($H$7*SQRT($J$7)) | J173: =I173 - $H$7*SQRT($J$7)
B174: =B144 | C174: =IF($O$7="sell",-1,1) * IF($K$7="call", NORMDIST(I174,0,1,1), NORMDIST(I174,0,1,1)-1 ) * $P$7 | D174: =IF($O$7="sell",-1,1) * NORMDIST(I174,0,1,0)/(B174*$H$7*SQRT($J$7)) * $P$7 | E174: =IF($O$7="sell",-1,1) * (B174*NORMDIST(I174,0,1,0)*SQRT($J$7)/365) * $P$7 | F174: =IF($O$7="sell",-1,1) * (-(B174*NORMDIST(I174,0,1,0)*$H$7)/(2*SQRT($J$7))/365) *$P$7 | G174: =IF($O$7="buy",1,-1)*( IF($K$7="call",B174*NORMDIST(I174,0,1,1) - $B$7*NORMDIST(J174,0,1,1),$B$7*NORMDIST(-J174,0,1,1) - B174*NORMDIST(-I174,0,1,1) ) - $G$7) * $P$7 | I174: =(LN(B174/$B$7)+($H$7^2/2)*($J$7))/($H$7*SQRT($J$7)) | J174: =I174 - $H$7*SQRT($J$7)
B175: =B145 | C175: =IF($O$7="sell",-1,1) * IF($K$7="call", NORMDIST(I175,0,1,1), NORMDIST(I175,0,1,1)-1 ) * $P$7 | D175: =IF($O$7="sell",-1,1) * NORMDIST(I175,0,1,0)/(B175*$H$7*SQRT($J$7)) * $P$7 | E175: =IF($O$7="sell",-1,1) * (B175*NORMDIST(I175,0,1,0)*SQRT($J$7)/365) * $P$7 | F175: =IF($O$7="sell",-1,1) * (-(B175*NORMDIST(I175,0,1,0)*$H$7)/(2*SQRT($J$7))/365) *$P$7 | G175: =IF($O$7="buy",1,-1)*( IF($K$7="call",B175*NORMDIST(I175,0,1,1) - $B$7*NORMDIST(J175,0,1,1),$B$7*NORMDIST(-J175,0,1,1) - B175*NORMDIST(-I175,0,1,1) ) - $G$7) * $P$7 | I175: =(LN(B175/$B$7)+($H$7^2/2)*($J$7))/($H$7*SQRT($J$7)) | J175: =I175 - $H$7*SQRT($J$7)
B176: =B146 | C176: =IF($O$7="sell",-1,1) * IF($K$7="call", NORMDIST(I176,0,1,1), NORMDIST(I176,0,1,1)-1 ) * $P$7 | D176: =IF($O$7="sell",-1,1) * NORMDIST(I176,0,1,0)/(B176*$H$7*SQRT($J$7)) * $P$7 | E176: =IF($O$7="sell",-1,1) * (B176*NORMDIST(I176,0,1,0)*SQRT($J$7)/365) * $P$7 | F176: =IF($O$7="sell",-1,1) * (-(B176*NORMDIST(I176,0,1,0)*$H$7)/(2*SQRT($J$7))/365) *$P$7 | G176: =IF($O$7="buy",1,-1)*( IF($K$7="call",B176*NORMDIST(I176,0,1,1) - $B$7*NORMDIST(J176,0,1,1),$B$7*NORMDIST(-J176,0,1,1) - B176*NORMDIST(-I176,0,1,1) ) - $G$7) * $P$7 | I176: =(LN(B176/$B$7)+($H$7^2/2)*($J$7))/($H$7*SQRT($J$7)) | J176: =I176 - $H$7*SQRT($J$7)
... B190: =B160 | C190: =IF($O$7="sell",-1,1) * IF($K$7="call", NORMDIST(I190,0,1,1), NORMDIST(I190,0,1,1)-1 ) * $P$7 | D190: =IF($O$7="sell",-1,1) * NORMDIST(I190,0,1,0)/(B190*$H$7*SQRT($J$7)) * $P$7 | E190: =IF($O$7="sell",-1,1) * (B190*NORMDIST(I190,0,1,0)*SQRT($J$7)/365) * $P$7 | F190: =IF($O$7="sell",-1,1) * (-(B190*NORMDIST(I190,0,1,0)*$H$7)/(2*SQRT($J$7))/365) *$P$7 | G190: =IF($O$7="buy",1,-1)*( IF($K$7="call",B190*NORMDIST(I190,0,1,1) - $B$7*NORMDIST(J190,0,1,1),$B$7*NORMDIST(-J190,0,1,1) - B190*NORMDIST(-I190,0,1,1) ) - $G$7) * $P$7 | I190: =(LN(B190/$B$7)+($H$7^2/2)*($J$7))/($H$7*SQRT($J$7)) | J190: =I190 - $H$7*SQRT($J$7)
...

Sheet Far_laeyr
C1: Кол | D1: Цена | E1: Стоимость | G1: Ближний слой | H1: 5-10 | I1: 0 | J1: 0.05 | N1: 42 | O1: 21 | P1: 14 | Q1: total | R1: cost | S1: % cost
B2: Sol | C2: =Portfolio!C10 | D2: =Portfolio!D10 | E2: =Portfolio!F10 | G2: Средний слой | H2: 10-20 | I2: 0.05 | J2: 0.15 | M2: 70 | N2: =G21 | P2: =G24 | Q2: =SUM(N2:P2) | R2: =H21+H24 | S2: =R2/$R$5
G3: Дальный слой | H3: 20-40 | I3: 0.16 | J3: выше | M3: 65 | Q3: =SUM(N3:P3) | S3: =R3/$R$5
B4: Лимит | C4: =Portfolio!D15 | D4: =Portfolio!E15 | M4: 60 | N4: =G20 | O4: =G22 | P4: =G23 | Q4: =SUM(N4:P4) | R4: =H20+H22+H23 | S4: =R4/$R$5
B5: база | C5: =C4*0.7 | D5: =R2+R3 | E5: =C5-D5 | F5: delta | G5: =C2*0.8 | H5: =C2*1.12 | Q5: =SUM(Q2:Q4) | R5: =SUM(R2:R4)
B6: усиление | C6: =C4*0.3 | D6: =R4 | E6: =C6-D6
B8: symbol | C8: strike | D8: delta | E8: DTE | F8: % price | G8: %priceCur | H8: priceCur
A9: 1 | B9: SOL-26JUN26-60-P-USDT | C9: =VLOOKUP(B9,OptionBoard!$A$2:$M$79,2,0) | D9: =VLOOKUP(B9,OptionBoard!$A$2:$M$79,3,0) | E9: =VLOOKUP(B9,OptionBoard!$A$2:$M$79,9,0) | F9: =($D$2-C9)/$D$2 | G9: =(Portfolio!$C$4-C9)/Portfolio!$C$4 | H9: 0.45
A10: 2 | B10: SOL-26JUN26-70-P-USDT | C10: =VLOOKUP(B10,OptionBoard!$A$2:$M$79,2,0) | D10: =VLOOKUP(B10,OptionBoard!$A$2:$M$79,3,0) | E10: =VLOOKUP(B10,OptionBoard!$A$2:$M$79,9,0) | F10: =($D$2-C10)/$D$2 | G10: =(Portfolio!$C$4-C10)/Portfolio!$C$4 | H10: 1
A11: 3 | B11: SOL-26JUN26-74-P-USDT | C11: =VLOOKUP(B11,OptionBoard!$A$2:$M$79,2,0) | D11: =VLOOKUP(B11,OptionBoard!$A$2:$M$79,3,0) | E11: =VLOOKUP(B11,OptionBoard!$A$2:$M$79,9,0) | F11: =($D$2-C11)/$D$2 | G11: =(Portfolio!$C$4-C11)/Portfolio!$C$4
A12: 4 | B12: SOL-26JUN26-74-P-USDT | C12: =VLOOKUP(B12,OptionBoard!$A$2:$M$79,2,0) | D12: =VLOOKUP(B12,OptionBoard!$A$2:$M$79,3,0) | E12: =VLOOKUP(B12,OptionBoard!$A$2:$M$79,9,0) | F12: =($D$2-C12)/$D$2 | G12: =(Portfolio!$C$4-C12)/Portfolio!$C$4
A13: 5 | B13: SOL-26JUN26-74-P-USDT | C13: =VLOOKUP(B13,OptionBoard!$A$2:$M$79,2,0) | D13: =VLOOKUP(B13,OptionBoard!$A$2:$M$79,3,0) | E13: =VLOOKUP(B13,OptionBoard!$A$2:$M$79,9,0) | F13: =($D$2-C13)/$D$2 | G13: =(Portfolio!$C$4-C13)/Portfolio!$C$4
A14: 6 | B14: SOL-26JUN26-74-P-USDT | C14: =VLOOKUP(B14,OptionBoard!$A$2:$M$79,2,0) | D14: =VLOOKUP(B14,OptionBoard!$A$2:$M$79,3,0) | E14: =VLOOKUP(B14,OptionBoard!$A$2:$M$79,9,0) | F14: =($D$2-C14)/$D$2 | G14: =(Portfolio!$C$4-C14)/Portfolio!$C$4
A15: 7 | B15: SOL-26JUN26-74-P-USDT | C15: =VLOOKUP(B15,OptionBoard!$A$2:$M$79,2,0) | D15: =VLOOKUP(B15,OptionBoard!$A$2:$M$79,3,0) | E15: =VLOOKUP(B15,OptionBoard!$A$2:$M$79,9,0) | F15: =($D$2-C15)/$D$2 | G15: =(Portfolio!$C$4-C15)/Portfolio!$C$4
B16: SOL-29MAY26-85-P-USDT
P18: =P26/C2
B19: symbol | C19: strike | D19: delta | E19: DTE | F19: priceCur | G19: кол | H19: cost | I19: % cost | M19: Strike | N19: Effi_Pnl | O19: Effi_Intr | P19: Delta | Q19: Pnl | R19: Intrin | S19: Acclerat
B20: =B9 | C20: =C9 | D20: =D9 | E20: =E9 | F20: =H9 | G20: 5 | H20: =F20*G20 | I20: =H20/$H$30 | M20: 70 | N20: =VLOOKUP(M20,$B$73:$C$99,2,0) | O20: =VLOOKUP(M20,$B$73:$D$99,3,0) | P20: =VLOOKUP(M20,$M$73:$P$99,2,0) | Q20: =VLOOKUP(M20,$M$73:$P$99,3,0) | R20: =VLOOKUP(M20,$M$73:$P$99,4,0)
B21: =B10 | C21: =C10 | D21: =D10 | E21: =E10 | F21: =H10 | G21: 8 | H21: =F21*G21 | I21: =H21/$H$30 | M21: 66 | N21: =VLOOKUP(M21,$B$73:$C$99,2,0) | O21: =VLOOKUP(M21,$B$73:$D$99,3,0) | P21: =VLOOKUP(M21,$M$73:$P$99,2,0) | Q21: =VLOOKUP(M21,$M$73:$P$99,3,0) | R21: =VLOOKUP(M21,$M$73:$P$99,4,0) | S21: =Q21-Q20
B22: =B11 | C22: =C11 | D22: =D11 | E22: =E11 | F22: =H11 | H22: =F22*G22 | I22: =H22/$H$30 | M22: 65 | N22: =VLOOKUP(M22,$B$73:$C$99,2,0) | O22: =VLOOKUP(M22,$B$73:$D$99,3,0) | P22: =VLOOKUP(M22,$M$73:$P$99,2,0) | Q22: =VLOOKUP(M22,$M$73:$P$99,3,0) | R22: =VLOOKUP(M22,$M$73:$P$99,4,0) | S22: =Q22-Q21
B23: =B12 | C23: =C12 | D23: =D12 | E23: =E12 | F23: =H12 | H23: =F23*G23 | I23: =H23/$H$30 | M23: 64 | N23: =VLOOKUP(M23,$B$73:$C$99,2,0) | O23: =VLOOKUP(M23,$B$73:$D$99,3,0) | P23: =VLOOKUP(M23,$M$73:$P$99,2,0) | Q23: =VLOOKUP(M23,$M$73:$P$99,3,0) | R23: =VLOOKUP(M23,$M$73:$P$99,4,0) | S23: =Q23-Q22
B24: =B13 | C24: =C13 | D24: =D13 | E24: =E13 | F24: =H13 | H24: =F24*G24 | I24: =H24/$H$30 | M24: 63 | N24: =VLOOKUP(M24,$B$73:$C$99,2,0) | O24: =VLOOKUP(M24,$B$73:$D$99,3,0) | P24: =VLOOKUP(M24,$M$73:$P$99,2,0) | Q24: =VLOOKUP(M24,$M$73:$P$99,3,0) | R24: =VLOOKUP(M24,$M$73:$P$99,4,0) | S24: =Q24-Q23
B25: =B14 | C25: =C14 | D25: =D14 | E25: =E14 | F25: =H14 | H25: =F25*G25 | I25: =H25/$H$30 | M25: 62 | N25: =VLOOKUP(M25,$B$73:$C$99,2,0) | O25: =VLOOKUP(M25,$B$73:$D$99,3,0) | P25: =VLOOKUP(M25,$M$73:$P$99,2,0) | Q25: =VLOOKUP(M25,$M$73:$P$99,3,0) | R25: =VLOOKUP(M25,$M$73:$P$99,4,0) | S25: =Q25-Q24
B26: =B15 | C26: =C15 | D26: =D15 | E26: =E15 | F26: =H15 | H26: =F26*G26 | I26: =H26/$H$30 | M26: 61 | N26: =VLOOKUP(M26,$B$73:$C$99,2,0) | O26: =VLOOKUP(M26,$B$73:$D$99,3,0) | P26: =VLOOKUP(M26,$M$73:$P$99,2,0) | Q26: =VLOOKUP(M26,$M$73:$P$99,3,0) | R26: =VLOOKUP(M26,$M$73:$P$99,4,0) | S26: =Q26-Q25
B27: SOL-26JUN26-60-P-USDT | C27: =Hedge_Far!B9 | D27: =Hedge_Far!C9 | E27: =Hedge_Far!I9 | H27: =Hedge_Far!N9 | I27: =H27/$H$30 | M27: 60 | N27: =VLOOKUP(M27,$B$73:$C$99,2,0) | O27: =VLOOKUP(M27,$B$73:$D$99,3,0) | P27: =VLOOKUP(M27,$M$73:$P$99,2,0) | Q27: =VLOOKUP(M27,$M$73:$P$99,3,0) | R27: =VLOOKUP(M27,$M$73:$P$99,4,0) | S27: =Q27-Q26
B28: SOL-26JUN26-70-P-USDT | C28: =Hedge_Far!B10 | D28: =Hedge_Far!C10 | E28: =Hedge_Far!I10 | H28: =Hedge_Far!N10 | I28: =H28/$H$30 | M28: 59 | N28: =VLOOKUP(M28,$B$73:$C$99,2,0) | O28: =VLOOKUP(M28,$B$73:$D$99,3,0) | P28: =VLOOKUP(M28,$M$73:$P$99,2,0) | Q28: =VLOOKUP(M28,$M$73:$P$99,3,0) | R28: =VLOOKUP(M28,$M$73:$P$99,4,0) | S28: =Q28-Q27
B29: SOL-26JUN26-74-P-USDT | C29: =Hedge_Far!B11 | D29: =Hedge_Far!C11 | E29: =Hedge_Far!I11 | H29: =Hedge_Far!N11 | I29: =H29/$H$30 | M29: 58 | N29: =VLOOKUP(M29,$B$73:$C$99,2,0) | O29: =VLOOKUP(M29,$B$73:$D$99,3,0) | P29: =VLOOKUP(M29,$M$73:$P$99,2,0) | Q29: =VLOOKUP(M29,$M$73:$P$99,3,0) | R29: =VLOOKUP(M29,$M$73:$P$99,4,0) | S29: =Q29-Q28
H30: =SUM(H20:H29) | N30: =AVERAGE(N20,N21,N22,N27) | O30: =AVERAGE(O20,O21,O22,O27) | Q30: =AVERAGE(Q20,Q21,Q26)
B32: symbol | C32: strike | D32: delta | E32: DTE | F32: priceCur | G32: кол | H32: cost | I32: % cost | M32: Strike | N32: Effi_Pnl | O32: Effi_Intr | P32: Delta | Q32: Pnl | R32: Intrin | S32: Acclerat
M33: 70
M34: 66
M35: 65
M36: 64
M37: 63
M38: 62
M39: 61
M40: 60
M41: 59
M42: 58 | V42: =Q30-R57 | W42: =V42/V43
V43: =H30-I56
B45: symbol | C45: strike | D45: delta | E45: DTE | F45: priceCur | G45: кол | H45: cost | I45: % cost | M45: Strike | N45: Effi_Pnl | O45: Effi_Intr | P45: Delta | Q45: Pnl | R45: Intrin | S45: Acclerat
B58: symbol | C58: strike | D58: delta | E58: DTE | F58: price | G58: кол | H58: cost | I58: % cost | M58: Strike | N58: Effi_Pnl | O58: Effi_Intr | P58: Delta | Q58: Pnl | R58: Intrin | S58: Acclerat | V58: 46 | W58: 18 | X58: 11 | Y58: total | Z58: cost | AA58: % cost
B59: SOL-29MAY26-60-P-USDT | C59: 60 | D59: -0.10159583 | E59: 46 | F59: 1.26 | G59: 7 | H59: =F59*G59 | I59: 0.19200849 | M59: 70 | N59: 1.3826841 | O59: -1 | P59: -7.4905809 | Q59: 39.102307 | R59: -28.28 | U59: 70 | V59: 2 | W59: 2 | X59: 5 | Y59: 9 | Z59: 15.4 | AA59: 0.54455446
B60: SOL-29MAY26-70-P-USDT | C60: 70 | D60: -0.22409187 | E60: 46 | F60: 3.55 | G60: 2 | H60: 7.1 | I60: 0.25106082 | M60: 65 | N60: 3.0364158 | O60: 0.59123055 | P60: -11.316422 | Q60: 85.869839 | R60: 16.72 | S60: 46.767532 | U60: 65 | X60: 5 | Y60: 5 | Z60: 4.2 | AA60: 0.14851485
B61: SOL-1MAY26-60-P-USDT | C61: 60 | D61: -0.03792071 | E61: 18 | F61: 0.43 | G61: 1 | H61: 0.43 | I61: 0.015205092 | M61: 64 | N61: 3.4510148 | O61: 1.0862801 | P61: -12.134433 | Q61: 97.594698 | R61: 30.72 | S61: 11.724858 | U61: 60 | V61: 3 | W61: 1 | X61: 6 | Y61: 10 | Z61: 8.68 | AA61: 0.30693069
B62: SOL-1MAY26-70-P-USDT | C62: 70 | D62: -0.13970333 | E62: 18 | F62: 1.06 | G62: 3 | H62: 2 | I62: 0.070721358 | M62: 63 | N62: 3.8946218 | O62: 1.5813296 | P62: -12.956034 | Q62: 110.1399 | R62: 44.72 | S62: 12.545205 | Y62: 24 | Z62: 28.28
B63: SOL-24APR26-60-P-USDT | C63: 60 | D63: -0.03169814 | E63: 11 | F63: 0.47 | G63: 6 | H63: 2.82 | I63: 0.099717115 | M63: 62 | N63: 4.3672485 | O63: 2.0763791 | P63: -13.774699 | Q63: 123.50579 | R63: 58.72 | S63: 13.365884
B64: SOL-24APR26-65-P-USDT | C64: 65 | D64: -0.05661972 | E64: 11 | F64: 0.84 | G64: 5 | H64: 4.2 | I64: 0.14851485 | M64: 61 | N64: 4.868676 | O64: 2.5714286 | P64: -14.583937 | Q64: 137.68616 | R64: 72.72 | S64: 14.18037
B65: SOL-24APR26-70-P-USDT | C65: 70 | D65: -0.10544421 | E65: 11 | F65: 1.26 | G65: 5 | H65: 6.3 | I65: 0.22277228 | M65: 60 | N65: 5.3984589 | O65: 3.0664781 | P65: -15.377461 | Q65: 152.66842 | R65: 86.72 | S65: 14.982262
M66: 59 | N66: 5.9559357 | O66: 3.9151344 | P66: -16.14935 | Q66: 168.43386 | R66: 110.72 | S66: 15.765443
M67: 58 | N67: 6.5402438 | O67: 4.7637907 | P67: -16.894183 | Q67: 184.95809 | R67: 134.72 | S67: 16.524232
M68: 57 | N68: 7.1503394 | O68: 5.612447 | P68: -17.607152 | Q68: 202.2116 | R68: 158.72 | S68: 17.253505
H69: 28.28 | N69: 3.4565126 | O69: 1.1481612 | Q69: 92.546855
B71: Activ | M71: Total Options | X71: =B20 | Z71: =B21 | AB71: =B22 | AD71: =B23 | AF71: =B24 | AH71: =B25 | AJ71: =B26 | AL71: =B27 | AN71: =B28 | AP71: =B29
B72: Price | C72: Efficien Pnl | D72: Efficien Intr | E72: Pnl | F72: %loss | M72: Price | N72: Delta | O72: Pnl | P72: Intrin | Q72: Pnl %loss | R72: Int %loss | S72: Pnl_loss | T72: Intrin_Loss | W72: Price | X72: Pnl | Y72: Intrin | Z72: Pnl | AA72: Intrin | AB72: Pnl | AC72: Intrin | AD72: Pnl | AE72: Intrin | AF72: Pnl | AG72: Intrin | AH72: Pnl | AI72: Intrin | AJ72: Pnl | AK72: Intrin | AL72: Pnl | AM72: Intrin | AN72: Pnl | AO72: Intrin | AP72: Pnl | AQ72: Intrin
B73: =ROUND(Portfolio!D10,0) | C73: =O73/$H$30 | D73: =P73/$H$30 | E73: =($C$2*B73)-$E$2 | F73: =(E73/$E$2) | M73: =B73 | N73: =Hedge_Far!C314 | O73: =Hedge_Far!G314 | P73: =Y73+AA73+AC73+AE73+AG73+AI73+AK73+AM73+AO73+AQ73 | Q73: =S73/$E$2 | R73: =T73/$E$2 | S73: =E73+O73 | T73: =E73+P73 | W73: =B73 | X73: =Hedge_Far!G17 | Y73: =IF(B73>$C$20,-1*$H$20,(($C$20-B73)*$G$20)-$H$20) | Z73: =Hedge_Far!G46 | AA73: =IF(B73>$C$21,-1*$H$21,(($C$21-B73)*$G$21)-$H$21) | AB73: =Hedge_Far!G75 | AC73: =IF(B73>$C$22,-1*$H$22,(($C$22-B73)*$G$22)-$H$22) | AD73: =Hedge_Far!G104 | AE73: =IF(B73>$C$23,-1*$H$23,(($C$23-B73)*$G$23)-$H$23) | AF73: =Hedge_Far!G134 | AG73: =IF(B73>$C$24,-1*$H$24,(($C$24-B73)*$G$24)-$H$24) | AH73: =Hedge_Far!G164 | AI73: =IF(B73>$C$25,-1*$H$25,(($C$25-B73)*$G$25)-$H$25) | AJ73: =Hedge_Far!G194 | AK73: =IF(B73>$C$26,-1*$H$26,(($C$26-B73)*$G$26)-$H$26) | AL73: =Hedge_Far!G224 | AM73: =IF(B73>$C$27,-1*$H$27,(($C$27-B73)*$G$27)-$H$27) | AN73: =Hedge_Far!G254 | AO73: =IF(B73>$C$28,-1*$H$28,(($C$28-B73)*$G$28)-$H$28) | AP73: =Hedge_Far!G284 | AQ73: =IF(B73>$C$29,-1*$H$29,(($C$29-B73)*$G$29)-$H$29)
B74: =B73-1 | C74: =O74/$H$30 | D74: =P74/$H$30 | E74: =($C$2*B74)-$E$2 | F74: =(E74/$E$2) | M74: =M73-1 | N74: =Hedge_Far!C315 | O74: =Hedge_Far!G315 | P74: =Y74+AA74+AC74+AE74+AG74+AI74+AK74+AM74+AO74+AQ74 | Q74: =S74/$E$2 | R74: =T74/$E$2 | S74: =E74+O74 | T74: =E74+P74 | U74: =O75-2*O74+O73 | W74: =W73-1 | X74: =Hedge_Far!G18 | Y74: =IF(B74>$C$20,-1*$H$20,(($C$20-B74)*$G$20)-$H$20) | Z74: =Hedge_Far!G47 | AA74: =IF(B74>$C$21,-1*$H$21,(($C$21-B74)*$G$21)-$H$21) | AB74: =Hedge_Far!G76 | AC74: =IF(B74>$C$22,-1*$H$22,(($C$22-B74)*$G$22)-$H$22) | AD74: =Hedge_Far!G105 | AE74: =IF(B74>$C$23,-1*$H$23,(($C$23-B74)*$G$23)-$H$23) | AF74: =Hedge_Far!G135 | AG74: =IF(B74>$C$24,-1*$H$24,(($C$24-B74)*$G$24)-$H$24) | AH74: =Hedge_Far!G165 | AI74: =IF(B74>$C$25,-1*$H$25,(($C$25-B74)*$G$25)-$H$25) | AJ74: =Hedge_Far!G195 | AK74: =IF(B74>$C$26,-1*$H$26,(($C$26-B74)*$G$26)-$H$26) | AL74: =Hedge_Far!G225 | AM74: =IF(B74>$C$27,-1*$H$27,(($C$27-B74)*$G$27)-$H$27) | AN74: =Hedge_Far!G255 | AO74: =IF(B74>$C$28,-1*$H$28,(($C$28-B74)*$G$28)-$H$28) | AP74: =Hedge_Far!G285 | AQ74: =IF(B74>$C$29,-1*$H$29,(($C$29-B74)*$G$29)-$H$29)
B75: =B74-1 | C75: =O75/$H$30 | D75: =P75/$H$30 | E75: =($C$2*B75)-$E$2 | F75: =(E75/$E$2) | M75: =M74-1 | N75: =Hedge_Far!C316 | O75: =Hedge_Far!G316 | P75: =Y75+AA75+AC75+AE75+AG75+AI75+AK75+AM75+AO75+AQ75 | Q75: =S75/$E$2 | R75: =T75/$E$2 | S75: =E75+O75 | T75: =E75+P75 | U75: =O76-2*O75+O74 | W75: =W74-1 | X75: =Hedge_Far!G19 | Y75: =IF(B75>$C$20,-1*$H$20,(($C$20-B75)*$G$20)-$H$20) | Z75: =Hedge_Far!G48 | AA75: =IF(B75>$C$21,-1*$H$21,(($C$21-B75)*$G$21)-$H$21) | AB75: =Hedge_Far!G77 | AC75: =IF(B75>$C$22,-1*$H$22,(($C$22-B75)*$G$22)-$H$22) | AD75: =Hedge_Far!G106 | AE75: =IF(B75>$C$23,-1*$H$23,(($C$23-B75)*$G$23)-$H$23) | AF75: =Hedge_Far!G136 | AG75: =IF(B75>$C$24,-1*$H$24,(($C$24-B75)*$G$24)-$H$24) | AH75: =Hedge_Far!G166 | AI75: =IF(B75>$C$25,-1*$H$25,(($C$25-B75)*$G$25)-$H$25) | AJ75: =Hedge_Far!G196 | AK75: =IF(B75>$C$26,-1*$H$26,(($C$26-B75)*$G$26)-$H$26) | AL75: =Hedge_Far!G226 | AM75: =IF(B75>$C$27,-1*$H$27,(($C$27-B75)*$G$27)-$H$27) | AN75: =Hedge_Far!G256 | AO75: =IF(B75>$C$28,-1*$H$28,(($C$28-B75)*$G$28)-$H$28) | AP75: =Hedge_Far!G286 | AQ75: =IF(B75>$C$29,-1*$H$29,(($C$29-B75)*$G$29)-$H$29)
B76: =B75-1 | C76: =O76/$H$30 | D76: =P76/$H$30 | E76: =($C$2*B76)-$E$2 | F76: =(E76/$E$2) | M76: =M75-1 | N76: =Hedge_Far!C317 | O76: =Hedge_Far!G317 | P76: =Y76+AA76+AC76+AE76+AG76+AI76+AK76+AM76+AO76+AQ76 | Q76: =S76/$E$2 | R76: =T76/$E$2 | S76: =E76+O76 | T76: =E76+P76 | U76: =O77-2*O76+O75 | W76: =W75-1 | X76: =Hedge_Far!G20 | Y76: =IF(B76>$C$20,-1*$H$20,(($C$20-B76)*$G$20)-$H$20) | Z76: =Hedge_Far!G49 | AA76: =IF(B76>$C$21,-1*$H$21,(($C$21-B76)*$G$21)-$H$21) | AB76: =Hedge_Far!G78 | AC76: =IF(B76>$C$22,-1*$H$22,(($C$22-B76)*$G$22)-$H$22) | AD76: =Hedge_Far!G107 | AE76: =IF(B76>$C$23,-1*$H$23,(($C$23-B76)*$G$23)-$H$23) | AF76: =Hedge_Far!G137 | AG76: =IF(B76>$C$24,-1*$H$24,(($C$24-B76)*$G$24)-$H$24) | AH76: =Hedge_Far!G167 | AI76: =IF(B76>$C$25,-1*$H$25,(($C$25-B76)*$G$25)-$H$25) | AJ76: =Hedge_Far!G197 | AK76: =IF(B76>$C$26,-1*$H$26,(($C$26-B76)*$G$26)-$H$26) | AL76: =Hedge_Far!G227 | AM76: =IF(B76>$C$27,-1*$H$27,(($C$27-B76)*$G$27)-$H$27) | AN76: =Hedge_Far!G257 | AO76: =IF(B76>$C$28,-1*$H$28,(($C$28-B76)*$G$28)-$H$28) | AP76: =Hedge_Far!G287 | AQ76: =IF(B76>$C$29,-1*$H$29,(($C$29-B76)*$G$29)-$H$29)
B77: =B76-1 | C77: =O77/$H$30 | D77: =P77/$H$30 | E77: =($C$2*B77)-$E$2 | F77: =(E77/$E$2) | M77: =M76-1 | N77: =Hedge_Far!C318 | O77: =Hedge_Far!G318 | P77: =Y77+AA77+AC77+AE77+AG77+AI77+AK77+AM77+AO77+AQ77 | Q77: =S77/$E$2 | R77: =T77/$E$2 | S77: =E77+O77 | T77: =E77+P77 | U77: =O78-2*O77+O76 | W77: =W76-1 | X77: =Hedge_Far!G21 | Y77: =IF(B77>$C$20,-1*$H$20,(($C$20-B77)*$G$20)-$H$20) | Z77: =Hedge_Far!G50 | AA77: =IF(B77>$C$21,-1*$H$21,(($C$21-B77)*$G$21)-$H$21) | AB77: =Hedge_Far!G79 | AC77: =IF(B77>$C$22,-1*$H$22,(($C$22-B77)*$G$22)-$H$22) | AD77: =Hedge_Far!G108 | AE77: =IF(B77>$C$23,-1*$H$23,(($C$23-B77)*$G$23)-$H$23) | AF77: =Hedge_Far!G138 | AG77: =IF(B77>$C$24,-1*$H$24,(($C$24-B77)*$G$24)-$H$24) | AH77: =Hedge_Far!G168 | AI77: =IF(B77>$C$25,-1*$H$25,(($C$25-B77)*$G$25)-$H$25) | AJ77: =Hedge_Far!G198 | AK77: =IF(B77>$C$26,-1*$H$26,(($C$26-B77)*$G$26)-$H$26) | AL77: =Hedge_Far!G228 | AM77: =IF(B77>$C$27,-1*$H$27,(($C$27-B77)*$G$27)-$H$27) | AN77: =Hedge_Far!G258 | AO77: =IF(B77>$C$28,-1*$H$28,(($C$28-B77)*$G$28)-$H$28) | AP77: =Hedge_Far!G288 | AQ77: =IF(B77>$C$29,-1*$H$29,(($C$29-B77)*$G$29)-$H$29)
B78: =B77-1 | C78: =O78/$H$30 | D78: =P78/$H$30 | E78: =($C$2*B78)-$E$2 | F78: =(E78/$E$2) | M78: =M77-1 | N78: =Hedge_Far!C319 | O78: =Hedge_Far!G319 | P78: =Y78+AA78+AC78+AE78+AG78+AI78+AK78+AM78+AO78+AQ78 | Q78: =S78/$E$2 | R78: =T78/$E$2 | S78: =E78+O78 | T78: =E78+P78 | U78: =O79-2*O78+O77 | W78: =W77-1 | X78: =Hedge_Far!G22 | Y78: =IF(B78>$C$20,-1*$H$20,(($C$20-B78)*$G$20)-$H$20) | Z78: =Hedge_Far!G51 | AA78: =IF(B78>$C$21,-1*$H$21,(($C$21-B78)*$G$21)-$H$21) | AB78: =Hedge_Far!G80 | AC78: =IF(B78>$C$22,-1*$H$22,(($C$22-B78)*$G$22)-$H$22) | AD78: =Hedge_Far!G109 | AE78: =IF(B78>$C$23,-1*$H$23,(($C$23-B78)*$G$23)-$H$23) | AF78: =Hedge_Far!G139 | AG78: =IF(B78>$C$24,-1*$H$24,(($C$24-B78)*$G$24)-$H$24) | AH78: =Hedge_Far!G169 | AI78: =IF(B78>$C$25,-1*$H$25,(($C$25-B78)*$G$25)-$H$25) | AJ78: =Hedge_Far!G199 | AK78: =IF(B78>$C$26,-1*$H$26,(($C$26-B78)*$G$26)-$H$26) | AL78: =Hedge_Far!G229 | AM78: =IF(B78>$C$27,-1*$H$27,(($C$27-B78)*$G$27)-$H$27) | AN78: =Hedge_Far!G259 | AO78: =IF(B78>$C$28,-1*$H$28,(($C$28-B78)*$G$28)-$H$28) | AP78: =Hedge_Far!G289 | AQ78: =IF(B78>$C$29,-1*$H$29,(($C$29-B78)*$G$29)-$H$29)
B79: =B78-1 | C79: =O79/$H$30 | D79: =P79/$H$30 | E79: =($C$2*B79)-$E$2 | F79: =(E79/$E$2) | M79: =M78-1 | N79: =Hedge_Far!C320 | O79: =Hedge_Far!G320 | P79: =Y79+AA79+AC79+AE79+AG79+AI79+AK79+AM79+AO79+AQ79 | Q79: =S79/$E$2 | R79: =T79/$E$2 | S79: =E79+O79 | T79: =E79+P79 | U79: =O80-2*O79+O78 | W79: =W78-1 | X79: =Hedge_Far!G23 | Y79: =IF(B79>$C$20,-1*$H$20,(($C$20-B79)*$G$20)-$H$20) | Z79: =Hedge_Far!G52 | AA79: =IF(B79>$C$21,-1*$H$21,(($C$21-B79)*$G$21)-$H$21) | AB79: =Hedge_Far!G81 | AC79: =IF(B79>$C$22,-1*$H$22,(($C$22-B79)*$G$22)-$H$22) | AD79: =Hedge_Far!G110 | AE79: =IF(B79>$C$23,-1*$H$23,(($C$23-B79)*$G$23)-$H$23) | AF79: =Hedge_Far!G140 | AG79: =IF(B79>$C$24,-1*$H$24,(($C$24-B79)*$G$24)-$H$24) | AH79: =Hedge_Far!G170 | AI79: =IF(B79>$C$25,-1*$H$25,(($C$25-B79)*$G$25)-$H$25) | AJ79: =Hedge_Far!G200 | AK79: =IF(B79>$C$26,-1*$H$26,(($C$26-B79)*$G$26)-$H$26) | AL79: =Hedge_Far!G230 | AM79: =IF(B79>$C$27,-1*$H$27,(($C$27-B79)*$G$27)-$H$27) | AN79: =Hedge_Far!G260 | AO79: =IF(B79>$C$28,-1*$H$28,(($C$28-B79)*$G$28)-$H$28) | AP79: =Hedge_Far!G290 | AQ79: =IF(B79>$C$29,-1*$H$29,(($C$29-B79)*$G$29)-$H$29)
B80: =B79-1 | C80: =O80/$H$30 | D80: =P80/$H$30 | E80: =($C$2*B80)-$E$2 | F80: =(E80/$E$2) | M80: =M79-1 | N80: =Hedge_Far!C321 | O80: =Hedge_Far!G321 | P80: =Y80+AA80+AC80+AE80+AG80+AI80+AK80+AM80+AO80+AQ80 | Q80: =S80/$E$2 | R80: =T80/$E$2 | S80: =E80+O80 | T80: =E80+P80 | U80: =O81-2*O80+O79 | W80: =W79-1 | X80: =Hedge_Far!G24 | Y80: =IF(B80>$C$20,-1*$H$20,(($C$20-B80)*$G$20)-$H$20) | Z80: =Hedge_Far!G53 | AA80: =IF(B80>$C$21,-1*$H$21,(($C$21-B80)*$G$21)-$H$21) | AB80: =Hedge_Far!G82 | AC80: =IF(B80>$C$22,-1*$H$22,(($C$22-B80)*$G$22)-$H$22) | AD80: =Hedge_Far!G111 | AE80: =IF(B80>$C$23,-1*$H$23,(($C$23-B80)*$G$23)-$H$23) | AF80: =Hedge_Far!G141 | AG80: =IF(B80>$C$24,-1*$H$24,(($C$24-B80)*$G$24)-$H$24) | AH80: =Hedge_Far!G171 | AI80: =IF(B80>$C$25,-1*$H$25,(($C$25-B80)*$G$25)-$H$25) | AJ80: =Hedge_Far!G201 | AK80: =IF(B80>$C$26,-1*$H$26,(($C$26-B80)*$G$26)-$H$26) | AL80: =Hedge_Far!G231 | AM80: =IF(B80>$C$27,-1*$H$27,(($C$27-B80)*$G$27)-$H$27) | AN80: =Hedge_Far!G261 | AO80: =IF(B80>$C$28,-1*$H$28,(($C$28-B80)*$G$28)-$H$28) | AP80: =Hedge_Far!G291 | AQ80: =IF(B80>$C$29,-1*$H$29,(($C$29-B80)*$G$29)-$H$29)
B81: =B80-1 | C81: =O81/$H$30 | D81: =P81/$H$30 | E81: =($C$2*B81)-$E$2 | F81: =(E81/$E$2) | M81: =M80-1 | N81: =Hedge_Far!C322 | O81: =Hedge_Far!G322 | P81: =Y81+AA81+AC81+AE81+AG81+AI81+AK81+AM81+AO81+AQ81 | Q81: =S81/$E$2 | R81: =T81/$E$2 | S81: =E81+O81 | T81: =E81+P81 | U81: =O82-2*O81+O80 | W81: =W80-1 | X81: =Hedge_Far!G25 | Y81: =IF(B81>$C$20,-1*$H$20,(($C$20-B81)*$G$20)-$H$20) | Z81: =Hedge_Far!G54 | AA81: =IF(B81>$C$21,-1*$H$21,(($C$21-B81)*$G$21)-$H$21) | AB81: =Hedge_Far!G83 | AC81: =IF(B81>$C$22,-1*$H$22,(($C$22-B81)*$G$22)-$H$22) | AD81: =Hedge_Far!G112 | AE81: =IF(B81>$C$23,-1*$H$23,(($C$23-B81)*$G$23)-$H$23) | AF81: =Hedge_Far!G142 | AG81: =IF(B81>$C$24,-1*$H$24,(($C$24-B81)*$G$24)-$H$24) | AH81: =Hedge_Far!G172 | AI81: =IF(B81>$C$25,-1*$H$25,(($C$25-B81)*$G$25)-$H$25) | AJ81: =Hedge_Far!G202 | AK81: =IF(B81>$C$26,-1*$H$26,(($C$26-B81)*$G$26)-$H$26) | AL81: =Hedge_Far!G232 | AM81: =IF(B81>$C$27,-1*$H$27,(($C$27-B81)*$G$27)-$H$27) | AN81: =Hedge_Far!G262 | AO81: =IF(B81>$C$28,-1*$H$28,(($C$28-B81)*$G$28)-$H$28) | AP81: =Hedge_Far!G292 | AQ81: =IF(B81>$C$29,-1*$H$29,(($C$29-B81)*$G$29)-$H$29)
B82: =B81-1 | C82: =O82/$H$30 | D82: =P82/$H$30 | E82: =($C$2*B82)-$E$2 | F82: =(E82/$E$2) | M82: =M81-1 | N82: =Hedge_Far!C323 | O82: =Hedge_Far!G323 | P82: =Y82+AA82+AC82+AE82+AG82+AI82+AK82+AM82+AO82+AQ82 | Q82: =S82/$E$2 | R82: =T82/$E$2 | S82: =E82+O82 | T82: =E82+P82 | U82: =O83-2*O82+O81 | W82: =W81-1 | X82: =Hedge_Far!G26 | Y82: =IF(B82>$C$20,-1*$H$20,(($C$20-B82)*$G$20)-$H$20) | Z82: =Hedge_Far!G55 | AA82: =IF(B82>$C$21,-1*$H$21,(($C$21-B82)*$G$21)-$H$21) | AB82: =Hedge_Far!G84 | AC82: =IF(B82>$C$22,-1*$H$22,(($C$22-B82)*$G$22)-$H$22) | AD82: =Hedge_Far!G113 | AE82: =IF(B82>$C$23,-1*$H$23,(($C$23-B82)*$G$23)-$H$23) | AF82: =Hedge_Far!G143 | AG82: =IF(B82>$C$24,-1*$H$24,(($C$24-B82)*$G$24)-$H$24) | AH82: =Hedge_Far!G173 | AI82: =IF(B82>$C$25,-1*$H$25,(($C$25-B82)*$G$25)-$H$25) | AJ82: =Hedge_Far!G203 | AK82: =IF(B82>$C$26,-1*$H$26,(($C$26-B82)*$G$26)-$H$26) | AL82: =Hedge_Far!G233 | AM82: =IF(B82>$C$27,-1*$H$27,(($C$27-B82)*$G$27)-$H$27) | AN82: =Hedge_Far!G263 | AO82: =IF(B82>$C$28,-1*$H$28,(($C$28-B82)*$G$28)-$H$28) | AP82: =Hedge_Far!G293 | AQ82: =IF(B82>$C$29,-1*$H$29,(($C$29-B82)*$G$29)-$H$29)
B83: =B82-1 | C83: =O83/$H$30 | D83: =P83/$H$30 | E83: =($C$2*B83)-$E$2 | F83: =(E83/$E$2) | M83: =M82-1 | N83: =Hedge_Far!C324 | O83: =Hedge_Far!G324 | P83: =Y83+AA83+AC83+AE83+AG83+AI83+AK83+AM83+AO83+AQ83 | Q83: =S83/$E$2 | R83: =T83/$E$2 | S83: =E83+O83 | T83: =E83+P83 | U83: =O84-2*O83+O82 | W83: =W82-1 | X83: =Hedge_Far!G27 | Y83: =IF(B83>$C$20,-1*$H$20,(($C$20-B83)*$G$20)-$H$20) | Z83: =Hedge_Far!G56 | AA83: =IF(B83>$C$21,-1*$H$21,(($C$21-B83)*$G$21)-$H$21) | AB83: =Hedge_Far!G85 | AC83: =IF(B83>$C$22,-1*$H$22,(($C$22-B83)*$G$22)-$H$22) | AD83: =Hedge_Far!G114 | AE83: =IF(B83>$C$23,-1*$H$23,(($C$23-B83)*$G$23)-$H$23) | AF83: =Hedge_Far!G144 | AG83: =IF(B83>$C$24,-1*$H$24,(($C$24-B83)*$G$24)-$H$24) | AH83: =Hedge_Far!G174 | AI83: =IF(B83>$C$25,-1*$H$25,(($C$25-B83)*$G$25)-$H$25) | AJ83: =Hedge_Far!G204 | AK83: =IF(B83>$C$26,-1*$H$26,(($C$26-B83)*$G$26)-$H$26) | AL83: =Hedge_Far!G234 | AM83: =IF(B83>$C$27,-1*$H$27,(($C$27-B83)*$G$27)-$H$27) | AN83: =Hedge_Far!G264 | AO83: =IF(B83>$C$28,-1*$H$28,(($C$28-B83)*$G$28)-$H$28) | AP83: =Hedge_Far!G294 | AQ83: =IF(B83>$C$29,-1*$H$29,(($C$29-B83)*$G$29)-$H$29)
B84: =B83-1 | C84: =O84/$H$30 | D84: =P84/$H$30 | E84: =($C$2*B84)-$E$2 | F84: =(E84/$E$2) | M84: =M83-1 | N84: =Hedge_Far!C325 | O84: =Hedge_Far!G325 | P84: =Y84+AA84+AC84+AE84+AG84+AI84+AK84+AM84+AO84+AQ84 | Q84: =S84/$E$2 | R84: =T84/$E$2 | S84: =E84+O84 | T84: =E84+P84 | U84: =O85-2*O84+O83 | W84: =W83-1 | X84: =Hedge_Far!G28 | Y84: =IF(B84>$C$20,-1*$H$20,(($C$20-B84)*$G$20)-$H$20) | Z84: =Hedge_Far!G57 | AA84: =IF(B84>$C$21,-1*$H$21,(($C$21-B84)*$G$21)-$H$21) | AB84: =Hedge_Far!G86 | AC84: =IF(B84>$C$22,-1*$H$22,(($C$22-B84)*$G$22)-$H$22) | AD84: =Hedge_Far!G115 | AE84: =IF(B84>$C$23,-1*$H$23,(($C$23-B84)*$G$23)-$H$23) | AF84: =Hedge_Far!G145 | AG84: =IF(B84>$C$24,-1*$H$24,(($C$24-B84)*$G$24)-$H$24) | AH84: =Hedge_Far!G175 | AI84: =IF(B84>$C$25,-1*$H$25,(($C$25-B84)*$G$25)-$H$25) | AJ84: =Hedge_Far!G205 | AK84: =IF(B84>$C$26,-1*$H$26,(($C$26-B84)*$G$26)-$H$26) | AL84: =Hedge_Far!G235 | AM84: =IF(B84>$C$27,-1*$H$27,(($C$27-B84)*$G$27)-$H$27) | AN84: =Hedge_Far!G265 | AO84: =IF(B84>$C$28,-1*$H$28,(($C$28-B84)*$G$28)-$H$28) | AP84: =Hedge_Far!G295 | AQ84: =IF(B84>$C$29,-1*$H$29,(($C$29-B84)*$G$29)-$H$29)
B85: =B84-1 | C85: =O85/$H$30 | D85: =P85/$H$30 | E85: =($C$2*B85)-$E$2 | F85: =(E85/$E$2) | M85: =M84-1 | N85: =Hedge_Far!C326 | O85: =Hedge_Far!G326 | P85: =Y85+AA85+AC85+AE85+AG85+AI85+AK85+AM85+AO85+AQ85 | Q85: =S85/$E$2 | R85: =T85/$E$2 | S85: =E85+O85 | T85: =E85+P85 | U85: =O86-2*O85+O84 | W85: =W84-1 | X85: =Hedge_Far!G29 | Y85: =IF(B85>$C$20,-1*$H$20,(($C$20-B85)*$G$20)-$H$20) | Z85: =Hedge_Far!G58 | AA85: =IF(B85>$C$21,-1*$H$21,(($C$21-B85)*$G$21)-$H$21) | AB85: =Hedge_Far!G87 | AC85: =IF(B85>$C$22,-1*$H$22,(($C$22-B85)*$G$22)-$H$22) | AD85: =Hedge_Far!G116 | AE85: =IF(B85>$C$23,-1*$H$23,(($C$23-B85)*$G$23)-$H$23) | AF85: =Hedge_Far!G146 | AG85: =IF(B85>$C$24,-1*$H$24,(($C$24-B85)*$G$24)-$H$24) | AH85: =Hedge_Far!G176 | AI85: =IF(B85>$C$25,-1*$H$25,(($C$25-B85)*$G$25)-$H$25) | AJ85: =Hedge_Far!G206 | AK85: =IF(B85>$C$26,-1*$H$26,(($C$26-B85)*$G$26)-$H$26) | AL85: =Hedge_Far!G236 | AM85: =IF(B85>$C$27,-1*$H$27,(($C$27-B85)*$G$27)-$H$27) | AN85: =Hedge_Far!G266 | AO85: =IF(B85>$C$28,-1*$H$28,(($C$28-B85)*$G$28)-$H$28) | AP85: =Hedge_Far!G296 | AQ85: =IF(B85>$C$29,-1*$H$29,(($C$29-B85)*$G$29)-$H$29)
... B98: =B97-1 | C98: =O98/$H$30 | D98: =P98/$H$30 | E98: =($C$2*B98)-$E$2 | F98: =(E98/$E$2) | M98: =M97-1 | N98: =Hedge_Far!C339 | O98: =Hedge_Far!G339 | P98: =Y98+AA98+AC98+AE98+AG98+AI98+AK98+AM98+AO98+AQ98 | Q98: =S98/$E$2 | R98: =T98/$E$2 | S98: =E98+O98 | T98: =E98+P98 | U98: =O99-2*O98+O97 | W98: =W97-1 | X98: =Hedge_Far!G42 | Y98: =IF(B98>$C$20,-1*$H$20,(($C$20-B98)*$G$20)-$H$20) | Z98: =Hedge_Far!G71 | AA98: =IF(B98>$C$21,-1*$H$21,(($C$21-B98)*$G$21)-$H$21) | AB98: =Hedge_Far!G100 | AC98: =IF(B98>$C$22,-1*$H$22,(($C$22-B98)*$G$22)-$H$22) | AD98: =Hedge_Far!G129 | AE98: =IF(B98>$C$23,-1*$H$23,(($C$23-B98)*$G$23)-$H$23) | AF98: =Hedge_Far!G159 | AG98: =IF(B98>$C$24,-1*$H$24,(($C$24-B98)*$G$24)-$H$24) | AH98: =Hedge_Far!G189 | AI98: =IF(B98>$C$25,-1*$H$25,(($C$25-B98)*$G$25)-$H$25) | AJ98: =Hedge_Far!G219 | AK98: =IF(B98>$C$26,-1*$H$26,(($C$26-B98)*$G$26)-$H$26) | AL98: =Hedge_Far!G249 | AM98: =IF(B98>$C$27,-1*$H$27,(($C$27-B98)*$G$27)-$H$27) | AN98: =Hedge_Far!G279 | AO98: =IF(B98>$C$28,-1*$H$28,(($C$28-B98)*$G$28)-$H$28) | AP98: =Hedge_Far!G309 | AQ98: =IF(B98>$C$29,-1*$H$29,(($C$29-B98)*$G$29)-$H$29)
B99: =B98-1 | C99: =O99/$H$30 | D99: =P99/$H$30 | E99: =($C$2*B99)-$E$2 | F99: =(E99/$E$2) | M99: =M98-1 | N99: =Hedge_Far!C340 | O99: =Hedge_Far!G340 | P99: =Y99+AA99+AC99+AE99+AG99+AI99+AK99+AM99+AO99+AQ99 | Q99: =S99/$E$2 | R99: =T99/$E$2 | S99: =E99+O99 | T99: =E99+P99 | W99: =W98-1 | X99: =Hedge_Far!G43 | Y99: =IF(B99>$C$20,-1*$H$20,(($C$20-B99)*$G$20)-$H$20) | Z99: =Hedge_Far!G72 | AA99: =IF(B99>$C$21,-1*$H$21,(($C$21-B99)*$G$21)-$H$21) | AB99: =Hedge_Far!G101 | AC99: =IF(B99>$C$22,-1*$H$22,(($C$22-B99)*$G$22)-$H$22) | AD99: =Hedge_Far!G130 | AE99: =IF(B99>$C$23,-1*$H$23,(($C$23-B99)*$G$23)-$H$23) | AF99: =Hedge_Far!G160 | AG99: =IF(B99>$C$24,-1*$H$24,(($C$24-B99)*$G$24)-$H$24) | AH99: =Hedge_Far!G190 | AI99: =IF(B99>$C$25,-1*$H$25,(($C$25-B99)*$G$25)-$H$25) | AJ99: =Hedge_Far!G220 | AK99: =IF(B99>$C$26,-1*$H$26,(($C$26-B99)*$G$26)-$H$26) | AL99: =Hedge_Far!G250 | AM99: =IF(B99>$C$27,-1*$H$27,(($C$27-B99)*$G$27)-$H$27) | AN99: =Hedge_Far!G280 | AO99: =IF(B99>$C$28,-1*$H$28,(($C$28-B99)*$G$28)-$H$28) | AP99: =Hedge_Far!G310 | AQ99: =IF(B99>$C$29,-1*$H$29,(($C$29-B99)*$G$29)-$H$29)
C101: =B9 | D101: =B10 | E101: =B11 | F101: =B12 | G101: =B13 | H101: =B14 | I101: =B15 | M101: 1 | N101: 2 | O101: 3 | P101: 4 | Q101: 5 | R101: 6 | S101: 7 | W101: 1 | X101: 2 | Y101: 3 | Z101: 4 | AA101: 5 | AB101: 6 | AC101: 7
B102: =W73 | C102: =VLOOKUP(B102,$W$73:$AQ$99,2,0)/$H$20 | D102: =VLOOKUP(B102,$W$73:$AQ$99,4,0)/$H$21 | E102: =VLOOKUP(B102,$W$73:$AQ$99,6,0)/$H$22 | M102: =C102-C103 | N102: =D102-D103 | W102: =M102-M103 | X102: =N102-N103
B103: =W74 | C103: =VLOOKUP(B103,$W$73:$AQ$99,2,0)/$H$20 | D103: =VLOOKUP(B103,$W$73:$AQ$99,4,0)/$H$21 | E103: =VLOOKUP(B103,$W$73:$AQ$99,6,0)/$H$22 | M103: =C103-C104 | N103: =D103-D104 | W103: =M103-M104 | X103: =N103-N104
B104: =W75 | C104: =VLOOKUP(B104,$W$73:$AQ$99,2,0)/$H$20 | D104: =VLOOKUP(B104,$W$73:$AQ$99,4,0)/$H$21 | E104: =VLOOKUP(B104,$W$73:$AQ$99,6,0)/$H$22 | M104: =C104-C105 | N104: =D104-D105 | W104: =M104-M105 | X104: =N104-N105
B105: =W76 | C105: =VLOOKUP(B105,$W$73:$AQ$99,2,0)/$H$20 | D105: =VLOOKUP(B105,$W$73:$AQ$99,4,0)/$H$21 | E105: =VLOOKUP(B105,$W$73:$AQ$99,6,0)/$H$22 | M105: =C105-C106 | N105: =D105-D106 | W105: =M105-M106 | X105: =N105-N106
B106: =W77 | C106: =VLOOKUP(B106,$W$73:$AQ$99,2,0)/$H$20 | D106: =VLOOKUP(B106,$W$73:$AQ$99,4,0)/$H$21 | E106: =VLOOKUP(B106,$W$73:$AQ$99,6,0)/$H$22 | M106: =C106-C107 | N106: =D106-D107 | W106: =M106-M107 | X106: =N106-N107
B107: =W78 | C107: =VLOOKUP(B107,$W$73:$AQ$99,2,0)/$H$20 | D107: =VLOOKUP(B107,$W$73:$AQ$99,4,0)/$H$21 | E107: =VLOOKUP(B107,$W$73:$AQ$99,6,0)/$H$22 | M107: =C107-C108 | N107: =D107-D108 | W107: =M107-M108 | X107: =N107-N108
B108: =W79 | C108: =VLOOKUP(B108,$W$73:$AQ$99,2,0)/$H$20 | D108: =VLOOKUP(B108,$W$73:$AQ$99,4,0)/$H$21 | E108: =VLOOKUP(B108,$W$73:$AQ$99,6,0)/$H$22 | M108: =C108-C109 | N108: =D108-D109 | W108: =M108-M109 | X108: =N108-N109
B109: =W80 | C109: =VLOOKUP(B109,$W$73:$AQ$99,2,0)/$H$20 | D109: =VLOOKUP(B109,$W$73:$AQ$99,4,0)/$H$21 | E109: =VLOOKUP(B109,$W$73:$AQ$99,6,0)/$H$22 | M109: =C109-C110 | N109: =D109-D110 | W109: =M109-M110 | X109: =N109-N110
B110: =W81 | C110: =VLOOKUP(B110,$W$73:$AQ$99,2,0)/$H$20 | D110: =VLOOKUP(B110,$W$73:$AQ$99,4,0)/$H$21 | E110: =VLOOKUP(B110,$W$73:$AQ$99,6,0)/$H$22 | M110: =C110-C111 | N110: =D110-D111 | W110: =M110-M111 | X110: =N110-N111
B111: =W82 | C111: =VLOOKUP(B111,$W$73:$AQ$99,2,0)/$H$20 | D111: =VLOOKUP(B111,$W$73:$AQ$99,4,0)/$H$21 | E111: =VLOOKUP(B111,$W$73:$AQ$99,6,0)/$H$22 | M111: =C111-C112 | N111: =D111-D112 | W111: =M111-M112 | X111: =N111-N112
B112: =W83 | C112: =VLOOKUP(B112,$W$73:$AQ$99,2,0)/$H$20 | D112: =VLOOKUP(B112,$W$73:$AQ$99,4,0)/$H$21 | E112: =VLOOKUP(B112,$W$73:$AQ$99,6,0)/$H$22 | M112: =C112-C113 | N112: =D112-D113 | W112: =M112-M113 | X112: =N112-N113
B113: =W84 | C113: =VLOOKUP(B113,$W$73:$AQ$99,2,0)/$H$20 | D113: =VLOOKUP(B113,$W$73:$AQ$99,4,0)/$H$21 | E113: =VLOOKUP(B113,$W$73:$AQ$99,6,0)/$H$22 | M113: =C113-C114 | N113: =D113-D114 | W113: =M113-M114 | X113: =N113-N114
... B126: =W97 | C126: =VLOOKUP(B126,$W$73:$AQ$99,2,0)/$H$20 | D126: =VLOOKUP(B126,$W$73:$AQ$99,4,0)/$H$21 | E126: =VLOOKUP(B126,$W$73:$AQ$99,6,0)/$H$22 | M126: =C126-C127 | N126: =D126-D127 | W126: =M126-M127 | X126: =N126-N127
B127: =W98 | C127: =VLOOKUP(B127,$W$73:$AQ$99,2,0)/$H$20 | D127: =VLOOKUP(B127,$W$73:$AQ$99,4,0)/$H$21 | E127: =VLOOKUP(B127,$W$73:$AQ$99,6,0)/$H$22 | M127: =C127-C128 | N127: =D127-D128
B128: =W99 | C128: =VLOOKUP(B128,$W$73:$AQ$99,2,0)/$H$20 | D128: =VLOOKUP(B128,$W$73:$AQ$99,4,0)/$H$21 | E128: =VLOOKUP(B128,$W$73:$AQ$99,6,0)/$H$22

Sheet Hedge_MID
A1: symbol | B1: strike | C1: delta | D1: gamma | E1: vega | F1: theta | G1: mark_price | H1: iv | I1: dte | J1: T | K1: type | L1: spot_price | M1: hedge_cost_per_day | N1: total_price | O1: position | P1: contracts | R1: Start | S1: Current
A2: =MID_laeyr!B23 | B2: =VLOOKUP(A2,OptionBoard!$A$2:$M$86,2,FALSE()) | C2: =VLOOKUP(A2,OptionBoard!$A$2:$M$86,3,0) | D2: =VLOOKUP(A2,OptionBoard!$A$2:$M$86,4,0) | E2: =VLOOKUP(A2,OptionBoard!$A$2:$M$86,5,0) | F2: =VLOOKUP(A2,OptionBoard!$A$2:$M$86,6,0) | G2: =VLOOKUP(A2,MID_laeyr!$B$9:$H$19,7,0) | H2: =VLOOKUP(A2,OptionBoard!$A$2:$M$86,8,0) | I2: =VLOOKUP(A2,OptionBoard!$A$2:$M$86,9,0) | J2: =VLOOKUP(A2,OptionBoard!$A$2:$M$86,10,0) | K2: =VLOOKUP(A2,OptionBoard!$A$2:$M$86,11,FALSE()) | L2: =VLOOKUP(A2,OptionBoard!$A$2:$M$86,12,0) | M2: =VLOOKUP(A2,OptionBoard!$A$2:$M$86,13,0) | N2: =G2*P2 | O2: buy | P2: =MID_laeyr!G23 | R2: =G2 | S2: =VLOOKUP(A2,OptionBoard!$A$2:$G$93,7,FALSE()) | U2: =R2-S2
A3: =MID_laeyr!B24 | B3: =VLOOKUP(A3,OptionBoard!$A$2:$M$86,2,FALSE()) | C3: =VLOOKUP(A3,OptionBoard!$A$2:$M$86,3,0) | D3: =VLOOKUP(A3,OptionBoard!$A$2:$M$86,4,0) | E3: =VLOOKUP(A3,OptionBoard!$A$2:$M$86,5,0) | F3: =VLOOKUP(A3,OptionBoard!$A$2:$M$86,6,0) | G3: =VLOOKUP(A3,MID_laeyr!$B$9:$H$19,7,0) | H3: =VLOOKUP(A3,OptionBoard!$A$2:$M$86,8,0) | I3: =VLOOKUP(A3,OptionBoard!$A$2:$M$86,9,0) | J3: =VLOOKUP(A3,OptionBoard!$A$2:$M$86,10,0) | K3: =VLOOKUP(A3,OptionBoard!$A$2:$M$86,11,FALSE()) | L3: =VLOOKUP(A3,OptionBoard!$A$2:$M$86,12,0) | M3: =VLOOKUP(A3,OptionBoard!$A$2:$M$86,13,0) | N3: =G3*P3 | O3: buy | P3: =MID_laeyr!G24 | R3: =G3 | S3: =VLOOKUP(A3,OptionBoard!$A$2:$G$93,7,FALSE()) | U3: =R3-S3
A4: =MID_laeyr!B25 | B4: =VLOOKUP(A4,OptionBoard!$A$2:$M$86,2,FALSE()) | C4: =VLOOKUP(A4,OptionBoard!$A$2:$M$86,3,0) | D4: =VLOOKUP(A4,OptionBoard!$A$2:$M$86,4,0) | E4: =VLOOKUP(A4,OptionBoard!$A$2:$M$86,5,0) | F4: =VLOOKUP(A4,OptionBoard!$A$2:$M$86,6,0) | G4: =VLOOKUP(A4,MID_laeyr!$B$9:$H$19,7,0) | H4: =VLOOKUP(A4,OptionBoard!$A$2:$M$86,8,0) | I4: =VLOOKUP(A4,OptionBoard!$A$2:$M$86,9,0) | J4: =VLOOKUP(A4,OptionBoard!$A$2:$M$86,10,0) | K4: =VLOOKUP(A4,OptionBoard!$A$2:$M$86,11,FALSE()) | L4: =VLOOKUP(A4,OptionBoard!$A$2:$M$86,12,0) | M4: =VLOOKUP(A4,OptionBoard!$A$2:$M$86,13,0) | N4: =G4*P4 | O4: buy | P4: =MID_laeyr!G25 | R4: 1.4 | S4: =VLOOKUP(A4,OptionBoard!$A$2:$G$93,7,FALSE()) | U4: =R4-S4
A5: =MID_laeyr!B26 | B5: =VLOOKUP(A5,OptionBoard!$A$2:$M$86,2,FALSE()) | C5: =VLOOKUP(A5,OptionBoard!$A$2:$M$86,3,0) | D5: =VLOOKUP(A5,OptionBoard!$A$2:$M$86,4,0) | E5: =VLOOKUP(A5,OptionBoard!$A$2:$M$86,5,0) | F5: =VLOOKUP(A5,OptionBoard!$A$2:$M$86,6,0) | G5: =VLOOKUP(A5,MID_laeyr!$B$9:$H$19,7,0) | H5: =VLOOKUP(A5,OptionBoard!$A$2:$M$86,8,0) | I5: =VLOOKUP(A5,OptionBoard!$A$2:$M$86,9,0) | J5: =VLOOKUP(A5,OptionBoard!$A$2:$M$86,10,0) | K5: =VLOOKUP(A5,OptionBoard!$A$2:$M$86,11,FALSE()) | L5: =VLOOKUP(A5,OptionBoard!$A$2:$M$86,12,0) | M5: =VLOOKUP(A5,OptionBoard!$A$2:$M$86,13,0) | N5: =G5*P5 | O5: buy | P5: =MID_laeyr!G26 | R5: =G5 | S5: =VLOOKUP(A5,OptionBoard!$A$2:$G$93,7,FALSE()) | U5: =R5-S5
A6: =MID_laeyr!B27 | B6: =VLOOKUP(A6,OptionBoard!$A$2:$M$86,2,FALSE()) | C6: =VLOOKUP(A6,OptionBoard!$A$2:$M$86,3,0) | D6: =VLOOKUP(A6,OptionBoard!$A$2:$M$86,4,0) | E6: =VLOOKUP(A6,OptionBoard!$A$2:$M$86,5,0) | F6: =VLOOKUP(A6,OptionBoard!$A$2:$M$86,6,0) | G6: =VLOOKUP(A6,MID_laeyr!$B$9:$H$19,7,0) | H6: =VLOOKUP(A6,OptionBoard!$A$2:$M$86,8,0) | I6: =VLOOKUP(A6,OptionBoard!$A$2:$M$86,9,0) | J6: =VLOOKUP(A6,OptionBoard!$A$2:$M$86,10,0) | K6: =VLOOKUP(A6,OptionBoard!$A$2:$M$86,11,FALSE()) | L6: =VLOOKUP(A6,OptionBoard!$A$2:$M$86,12,0) | M6: =VLOOKUP(A6,OptionBoard!$A$2:$M$86,13,0) | N6: =G6*P6 | O6: buy | P6: =MID_laeyr!G27 | R6: =G6 | S6: =VLOOKUP(A6,OptionBoard!$A$2:$G$93,7,FALSE()) | U6: =R6-S6
A7: =MID_laeyr!B28 | B7: =VLOOKUP(A7,OptionBoard!$A$2:$M$86,2,FALSE()) | C7: =VLOOKUP(A7,OptionBoard!$A$2:$M$86,3,0) | D7: =VLOOKUP(A7,OptionBoard!$A$2:$M$86,4,0) | E7: =VLOOKUP(A7,OptionBoard!$A$2:$M$86,5,0) | F7: =VLOOKUP(A7,OptionBoard!$A$2:$M$86,6,0) | G7: =VLOOKUP(A7,MID_laeyr!$B$9:$H$19,7,0) | H7: =VLOOKUP(A7,OptionBoard!$A$2:$M$86,8,0) | I7: =VLOOKUP(A7,OptionBoard!$A$2:$M$86,9,0) | J7: =VLOOKUP(A7,OptionBoard!$A$2:$M$86,10,0) | K7: =VLOOKUP(A7,OptionBoard!$A$2:$M$86,11,FALSE()) | L7: =VLOOKUP(A7,OptionBoard!$A$2:$M$86,12,0) | M7: =VLOOKUP(A7,OptionBoard!$A$2:$M$86,13,0) | N7: =G7*P7 | O7: buy | P7: =MID_laeyr!G28 | R7: =G7 | S7: =VLOOKUP(A7,OptionBoard!$A$2:$G$93,7,FALSE()) | U7: =R7-S7
A8: =MID_laeyr!B29 | B8: =VLOOKUP(A8,OptionBoard!$A$2:$M$86,2,FALSE()) | C8: =VLOOKUP(A8,OptionBoard!$A$2:$M$86,3,0) | D8: =VLOOKUP(A8,OptionBoard!$A$2:$M$86,4,0) | E8: =VLOOKUP(A8,OptionBoard!$A$2:$M$86,5,0) | F8: =VLOOKUP(A8,OptionBoard!$A$2:$M$86,6,0) | G8: =VLOOKUP(A8,MID_laeyr!$B$9:$H$19,7,0) | H8: =VLOOKUP(A8,OptionBoard!$A$2:$M$86,8,0) | I8: =VLOOKUP(A8,OptionBoard!$A$2:$M$86,9,0) | J8: =VLOOKUP(A8,OptionBoard!$A$2:$M$86,10,0) | K8: =VLOOKUP(A8,OptionBoard!$A$2:$M$86,11,FALSE()) | L8: =VLOOKUP(A8,OptionBoard!$A$2:$M$86,12,0) | M8: =VLOOKUP(A8,OptionBoard!$A$2:$M$86,13,0) | N8: =G8*P8 | O8: buy | P8: =MID_laeyr!G29 | S8: =VLOOKUP(A8,OptionBoard!$A$2:$G$93,7,FALSE()) | U8: =R8-S8
A9: =MID_laeyr!B30 | B9: =VLOOKUP(A9,OptionBoard!$A$2:$M$86,2,FALSE()) | C9: =VLOOKUP(A9,OptionBoard!$A$2:$M$86,3,0) | D9: =VLOOKUP(A9,OptionBoard!$A$2:$M$86,4,0) | E9: =VLOOKUP(A9,OptionBoard!$A$2:$M$86,5,0) | F9: =VLOOKUP(A9,OptionBoard!$A$2:$M$86,6,0) | G9: =VLOOKUP(A9,MID_laeyr!$B$9:$H$19,7,0) | H9: =VLOOKUP(A9,OptionBoard!$A$2:$M$86,8,0) | I9: =VLOOKUP(A9,OptionBoard!$A$2:$M$86,9,0) | J9: =VLOOKUP(A9,OptionBoard!$A$2:$M$86,10,0) | K9: =VLOOKUP(A9,OptionBoard!$A$2:$M$86,11,FALSE()) | L9: =VLOOKUP(A9,OptionBoard!$A$2:$M$86,12,0) | M9: =VLOOKUP(A9,OptionBoard!$A$2:$M$86,13,0) | N9: =G9*P9 | O9: buy | P9: =MID_laeyr!G30 | S9: =VLOOKUP(A9,OptionBoard!$A$2:$G$93,7,FALSE()) | U9: =R9-S9
A10: =MID_laeyr!B31 | B10: =VLOOKUP(A10,OptionBoard!$A$2:$M$86,2,FALSE()) | C10: =VLOOKUP(A10,OptionBoard!$A$2:$M$86,3,0) | D10: =VLOOKUP(A10,OptionBoard!$A$2:$M$86,4,0) | E10: =VLOOKUP(A10,OptionBoard!$A$2:$M$86,5,0) | F10: =VLOOKUP(A10,OptionBoard!$A$2:$M$86,6,0) | G10: =VLOOKUP(A10,MID_laeyr!$B$9:$H$19,7,0) | H10: =VLOOKUP(A10,OptionBoard!$A$2:$M$86,8,0) | I10: =VLOOKUP(A10,OptionBoard!$A$2:$M$86,9,0) | J10: =VLOOKUP(A10,OptionBoard!$A$2:$M$86,10,0) | K10: =VLOOKUP(A10,OptionBoard!$A$2:$M$86,11,FALSE()) | L10: =VLOOKUP(A10,OptionBoard!$A$2:$M$86,12,0) | M10: =VLOOKUP(A10,OptionBoard!$A$2:$M$86,13,0) | N10: =G10*P10 | O10: buy | P10: =MID_laeyr!G31 | S10: =VLOOKUP(A10,OptionBoard!$A$2:$G$93,7,FALSE()) | U10: =R10-S10
A11: =MID_laeyr!B32 | B11: =VLOOKUP(A11,OptionBoard!$A$2:$M$86,2,FALSE()) | C11: =VLOOKUP(A11,OptionBoard!$A$2:$M$86,3,0) | D11: =VLOOKUP(A11,OptionBoard!$A$2:$M$86,4,0) | E11: =VLOOKUP(A11,OptionBoard!$A$2:$M$86,5,0) | F11: =VLOOKUP(A11,OptionBoard!$A$2:$M$86,6,0) | G11: =VLOOKUP(A11,MID_laeyr!$B$9:$H$19,7,0) | H11: =VLOOKUP(A11,OptionBoard!$A$2:$M$86,8,0) | I11: =VLOOKUP(A11,OptionBoard!$A$2:$M$86,9,0) | J11: =VLOOKUP(A11,OptionBoard!$A$2:$M$86,10,0) | K11: =VLOOKUP(A11,OptionBoard!$A$2:$M$86,11,FALSE()) | L11: =VLOOKUP(A11,OptionBoard!$A$2:$M$86,12,0) | M11: =VLOOKUP(A11,OptionBoard!$A$2:$M$86,13,0) | N11: =G11*P11 | O11: buy | P11: =MID_laeyr!G32 | S11: =VLOOKUP(A11,OptionBoard!$A$2:$G$93,7,FALSE()) | U11: =R11-S11
A14: Now_Greeks | C14: =(IF($O$2="buy",1,-1) * C2 * P2)+(IF($O$3="buy",1,-1) * C3 * P3)+(IF($O$4="buy",1,-1) * C4 * P4)+(IF($O$5="buy",1,-1) * C5 * P5)+(IF($O$6="buy",1,-1) * C6 * P6)+(IF($O$7="buy",1,-1) * C7 * P7)+(IF($O$8="buy",1,-1) * C8 * P8)+(IF($O$9="buy",1,-1) * C9 * P9)+(IF($O$10="buy",1,-1) * C10 * P10)+(IF($O$11="buy",1,-1) * C11 * P11) | D14: =(IF($O$2="buy",1,-1) * D2 * P2)+(IF($O$3="buy",1,-1) * D3 * P3)+(IF($O$4="buy",1,-1) * D4 * P4)+(IF($O$5="buy",1,-1) * D5 * P5)+(IF($O$6="buy",1,-1) * D6 * P6)+(IF($O$7="buy",1,-1) * D7 * P7)+(IF($O$8="buy",1,-1) * D8 * P8)+(IF($O$9="buy",1,-1) * D9 * P9)+(IF($O$10="buy",1,-1) * D10 * P10)+(IF($O$11="buy",1,-1) * D11 * P11) | E14: =(IF($O$2="buy",1,-1) * E2 * P2)+(IF($O$3="buy",1,-1) * E3 * P3)+(IF($O$4="buy",1,-1) * E4 * P4)+(IF($O$5="buy",1,-1) * E5 * P5)+(IF($O$6="buy",1,-1) * E6 * P6)+(IF($O$7="buy",1,-1) * E7 * P7)+(IF($O$8="buy",1,-1) * E8 * P8)+(IF($O$9="buy",1,-1) * E9 * P9)+(IF($O$10="buy",1,-1) * E10 * P10)+(IF($O$11="buy",1,-1) * E11 * P11) | F14: =(IF($O$2="buy",1,-1) * F2 * P2)+(IF($O$3="buy",1,-1) * F3 * P3)+(IF($O$4="buy",1,-1) * F4 * P4)+(IF($O$5="buy",1,-1) * F5 * P5)+(IF($O$6="buy",1,-1) * F6 * P6)+(IF($O$7="buy",1,-1) * F7 * P7)+(IF($O$8="buy",1,-1) * F8 * P8)+(IF($O$9="buy",1,-1) * F9 * P9)+(IF($O$10="buy",1,-1) * F10 * P10)+(IF($O$11="buy",1,-1) * F11 * P11) | G14: =(IF($O$2="buy",1,-1) * G2 * P2)+(IF($O$3="buy",1,-1) * G3 * P3)+(IF($O$4="buy",1,-1) * G4 * P4)+(IF($O$5="buy",1,-1) * G5 * P5)+(IF($O$6="buy",1,-1) * G6 * P6)+(IF($O$7="buy",1,-1) * G7 * P7)+(IF($O$8="buy",1,-1) * G8 * P8)+(IF($O$9="buy",1,-1) * G9 * P9)+(IF($O$10="buy",1,-1) * G10 * P10)+(IF($O$11="buy",1,-1) * G11 * P11) | M14: =M2*P2+M3*P3+M5*P5+M4*P4+M6*P6+M7*P7+M8*P8+M9*P9+M10*P10 | S14: =F14/C14
A16: =A2 | C16: delta | D16: gamma | E16: vega | F16: theta | G16: mark_price | I16: d1 | J16: d2
B17: =Portfolio!B28 | C17: =IF($O$2="sell",-1,1) * IF($K$2="call", NORMDIST(I17,0,1,1), NORMDIST(I17,0,1,1)-1 ) * $P$2 | D17: =IF($O$2="sell",-1,1) * NORMDIST(I17,0,1,0)/(B17*$H$2*SQRT($J$2)) * $P$2 | E17: =IF($O$2="sell",-1,1) * (B17*NORMDIST(I17,0,1,0)*SQRT($J$2)/365) * $P$2 | F17: =IF($O$2="sell",-1,1) * (-(B17*NORMDIST(I17,0,1,0)*$H$2)/(2*SQRT($J$2))/365) *$P$2 | G17: =IF($O$2="buy",1,-1)*( IF($K$2="call",B17*NORMDIST(I17,0,1,1) - $B$2*NORMDIST(J17,0,1,1),$B$2*NORMDIST(-J17,0,1,1) - B17*NORMDIST(-I17,0,1,1) ) - $G$2) * $P$2 | I17: =(LN(B17/$B$2)+($H$2^2/2)*($J$2))/($H$2*SQRT($J$2)) | J17: =I17 - $H$2*SQRT($J$2)
B18: =Portfolio!B29 | C18: =IF($O$2="sell",-1,1) * IF($K$2="call", NORMDIST(I18,0,1,1), NORMDIST(I18,0,1,1)-1 ) * $P$2 | D18: =IF($O$2="sell",-1,1) * NORMDIST(I18,0,1,0)/(B18*$H$2*SQRT($J$2)) * $P$2 | E18: =IF($O$2="sell",-1,1) * (B18*NORMDIST(I18,0,1,0)*SQRT($J$2)/365) * $P$2 | F18: =IF($O$2="sell",-1,1) * (-(B18*NORMDIST(I18,0,1,0)*$H$2)/(2*SQRT($J$2))/365) *$P$2 | G18: =IF($O$2="buy",1,-1)*( IF($K$2="call",B18*NORMDIST(I18,0,1,1) - $B$2*NORMDIST(J18,0,1,1),$B$2*NORMDIST(-J18,0,1,1) - B18*NORMDIST(-I18,0,1,1) ) - $G$2) * $P$2 | I18: =(LN(B18/$B$2)+($H$2^2/2)*($J$2))/($H$2*SQRT($J$2)) | J18: =I18 - $H$2*SQRT($J$2)
B19: =Portfolio!B30 | C19: =IF($O$2="sell",-1,1) * IF($K$2="call", NORMDIST(I19,0,1,1), NORMDIST(I19,0,1,1)-1 ) * $P$2 | D19: =IF($O$2="sell",-1,1) * NORMDIST(I19,0,1,0)/(B19*$H$2*SQRT($J$2)) * $P$2 | E19: =IF($O$2="sell",-1,1) * (B19*NORMDIST(I19,0,1,0)*SQRT($J$2)/365) * $P$2 | F19: =IF($O$2="sell",-1,1) * (-(B19*NORMDIST(I19,0,1,0)*$H$2)/(2*SQRT($J$2))/365) *$P$2 | G19: =IF($O$2="buy",1,-1)*( IF($K$2="call",B19*NORMDIST(I19,0,1,1) - $B$2*NORMDIST(J19,0,1,1),$B$2*NORMDIST(-J19,0,1,1) - B19*NORMDIST(-I19,0,1,1) ) - $G$2) * $P$2 | I19: =(LN(B19/$B$2)+($H$2^2/2)*($J$2))/($H$2*SQRT($J$2)) | J19: =I19 - $H$2*SQRT($J$2)
B20: =Portfolio!B31 | C20: =IF($O$2="sell",-1,1) * IF($K$2="call", NORMDIST(I20,0,1,1), NORMDIST(I20,0,1,1)-1 ) * $P$2 | D20: =IF($O$2="sell",-1,1) * NORMDIST(I20,0,1,0)/(B20*$H$2*SQRT($J$2)) * $P$2 | E20: =IF($O$2="sell",-1,1) * (B20*NORMDIST(I20,0,1,0)*SQRT($J$2)/365) * $P$2 | F20: =IF($O$2="sell",-1,1) * (-(B20*NORMDIST(I20,0,1,0)*$H$2)/(2*SQRT($J$2))/365) *$P$2 | G20: =IF($O$2="buy",1,-1)*( IF($K$2="call",B20*NORMDIST(I20,0,1,1) - $B$2*NORMDIST(J20,0,1,1),$B$2*NORMDIST(-J20,0,1,1) - B20*NORMDIST(-I20,0,1,1) ) - $G$2) * $P$2 | I20: =(LN(B20/$B$2)+($H$2^2/2)*($J$2))/($H$2*SQRT($J$2)) | J20: =I20 - $H$2*SQRT($J$2)
B21: =Portfolio!B32 | C21: =IF($O$2="sell",-1,1) * IF($K$2="call", NORMDIST(I21,0,1,1), NORMDIST(I21,0,1,1)-1 ) * $P$2 | D21: =IF($O$2="sell",-1,1) * NORMDIST(I21,0,1,0)/(B21*$H$2*SQRT($J$2)) * $P$2 | E21: =IF($O$2="sell",-1,1) * (B21*NORMDIST(I21,0,1,0)*SQRT($J$2)/365) * $P$2 | F21: =IF($O$2="sell",-1,1) * (-(B21*NORMDIST(I21,0,1,0)*$H$2)/(2*SQRT($J$2))/365) *$P$2 | G21: =IF($O$2="buy",1,-1)*( IF($K$2="call",B21*NORMDIST(I21,0,1,1) - $B$2*NORMDIST(J21,0,1,1),$B$2*NORMDIST(-J21,0,1,1) - B21*NORMDIST(-I21,0,1,1) ) - $G$2) * $P$2 | I21: =(LN(B21/$B$2)+($H$2^2/2)*($J$2))/($H$2*SQRT($J$2)) | J21: =I21 - $H$2*SQRT($J$2)
B22: =Portfolio!B33 | C22: =IF($O$2="sell",-1,1) * IF($K$2="call", NORMDIST(I22,0,1,1), NORMDIST(I22,0,1,1)-1 ) * $P$2 | D22: =IF($O$2="sell",-1,1) * NORMDIST(I22,0,1,0)/(B22*$H$2*SQRT($J$2)) * $P$2 | E22: =IF($O$2="sell",-1,1) * (B22*NORMDIST(I22,0,1,0)*SQRT($J$2)/365) * $P$2 | F22: =IF($O$2="sell",-1,1) * (-(B22*NORMDIST(I22,0,1,0)*$H$2)/(2*SQRT($J$2))/365) *$P$2 | G22: =IF($O$2="buy",1,-1)*( IF($K$2="call",B22*NORMDIST(I22,0,1,1) - $B$2*NORMDIST(J22,0,1,1),$B$2*NORMDIST(-J22,0,1,1) - B22*NORMDIST(-I22,0,1,1) ) - $G$2) * $P$2 | I22: =(LN(B22/$B$2)+($H$2^2/2)*($J$2))/($H$2*SQRT($J$2)) | J22: =I22 - $H$2*SQRT($J$2)
B23: =Portfolio!B34 | C23: =IF($O$2="sell",-1,1) * IF($K$2="call", NORMDIST(I23,0,1,1), NORMDIST(I23,0,1,1)-1 ) * $P$2 | D23: =IF($O$2="sell",-1,1) * NORMDIST(I23,0,1,0)/(B23*$H$2*SQRT($J$2)) * $P$2 | E23: =IF($O$2="sell",-1,1) * (B23*NORMDIST(I23,0,1,0)*SQRT($J$2)/365) * $P$2 | F23: =IF($O$2="sell",-1,1) * (-(B23*NORMDIST(I23,0,1,0)*$H$2)/(2*SQRT($J$2))/365) *$P$2 | G23: =IF($O$2="buy",1,-1)*( IF($K$2="call",B23*NORMDIST(I23,0,1,1) - $B$2*NORMDIST(J23,0,1,1),$B$2*NORMDIST(-J23,0,1,1) - B23*NORMDIST(-I23,0,1,1) ) - $G$2) * $P$2 | I23: =(LN(B23/$B$2)+($H$2^2/2)*($J$2))/($H$2*SQRT($J$2)) | J23: =I23 - $H$2*SQRT($J$2)
B24: =Portfolio!B35 | C24: =IF($O$2="sell",-1,1) * IF($K$2="call", NORMDIST(I24,0,1,1), NORMDIST(I24,0,1,1)-1 ) * $P$2 | D24: =IF($O$2="sell",-1,1) * NORMDIST(I24,0,1,0)/(B24*$H$2*SQRT($J$2)) * $P$2 | E24: =IF($O$2="sell",-1,1) * (B24*NORMDIST(I24,0,1,0)*SQRT($J$2)/365) * $P$2 | F24: =IF($O$2="sell",-1,1) * (-(B24*NORMDIST(I24,0,1,0)*$H$2)/(2*SQRT($J$2))/365) *$P$2 | G24: =IF($O$2="buy",1,-1)*( IF($K$2="call",B24*NORMDIST(I24,0,1,1) - $B$2*NORMDIST(J24,0,1,1),$B$2*NORMDIST(-J24,0,1,1) - B24*NORMDIST(-I24,0,1,1) ) - $G$2) * $P$2 | I24: =(LN(B24/$B$2)+($H$2^2/2)*($J$2))/($H$2*SQRT($J$2)) | J24: =I24 - $H$2*SQRT($J$2)
B25: =Portfolio!B36 | C25: =IF($O$2="sell",-1,1) * IF($K$2="call", NORMDIST(I25,0,1,1), NORMDIST(I25,0,1,1)-1 ) * $P$2 | D25: =IF($O$2="sell",-1,1) * NORMDIST(I25,0,1,0)/(B25*$H$2*SQRT($J$2)) * $P$2 | E25: =IF($O$2="sell",-1,1) * (B25*NORMDIST(I25,0,1,0)*SQRT($J$2)/365) * $P$2 | F25: =IF($O$2="sell",-1,1) * (-(B25*NORMDIST(I25,0,1,0)*$H$2)/(2*SQRT($J$2))/365) *$P$2 | G25: =IF($O$2="buy",1,-1)*( IF($K$2="call",B25*NORMDIST(I25,0,1,1) - $B$2*NORMDIST(J25,0,1,1),$B$2*NORMDIST(-J25,0,1,1) - B25*NORMDIST(-I25,0,1,1) ) - $G$2) * $P$2 | I25: =(LN(B25/$B$2)+($H$2^2/2)*($J$2))/($H$2*SQRT($J$2)) | J25: =I25 - $H$2*SQRT($J$2)
